Workbook
Name TC: 'RESUMEN GLOBAL'!$E$3

Sheet DASHBOARD
B2: DASHBOARD — CONTROL DE REFACCIONES Y COTIZACIONES 2026
B3: Resumen de pedidos, cotizaciones y estado de maquinaria pesada
B5: 📊 RESUMEN DE PARTIDAS
B6: TOTAL PARTIDAS | C6: ENTREGADO | D6: COTIZANDO | E6: EN ALMACÉN | F6: CANCELADO | G6: PEDIDO
B7: =ROWS(Tabla3[PEDIDO]) -> 1326 | C7: =COUNTIF(Tabla3[STATUS],"ENTREGADO") -> 478 | D7: =COUNTIFS(Tabla3[STATUS],"COTIZANDO",Tabla3[TEMA],"<>SERVICIO DE FILTROS") -> 704 | E7: =COUNTIF(Tabla3[STATUS],"EN ALMACEN") -> 50 | F7: =COUNTIF(Tabla3[STATUS],"CANCELADO") -> 31 | G7: =COUNTIF(Tabla3[STATUS],"PEDIDO") -> 58
B8: piezas solicitadas | C8: =TEXT(C7/B7,"0%")&" del total" -> 36% del total | D8: =TEXT(D7/B7,"0%")&" del total" -> 53% del total | E8: =TEXT(E7/B7,"0%")&" del total" -> 4% del total | F8: =TEXT(F7/B7,"0%")&" del total" -> 2% del total | G8: por entregar
B10: 🚜 ESTADO DE MAQUINARIA
B11: UNIDADES ACTIVAS | C11: UNIDADES INACTIVAS | D11: UNIDADES DONANTE | E11: UNIDADES SINIESTRADAS | F11: TOTAL UNIDADES | G11: % DISPONIBILIDAD
B12: =COUNTIFS(MAQUINARIA!$B$3:$B$655,"<>",MAQUINARIA!$B$3:$B$655,"<>Seguimiento",MAQUINARIA!$H$3:$H$655,"ACTIVA") -> 81 | C12: =COUNTIFS(MAQUINARIA!$B$3:$B$655,"<>",MAQUINARIA!$B$3:$B$655,"<>Seguimiento",MAQUINARIA!$H$3:$H$655,"INACTIVA") -> 38 | D12: =COUNTIFS(MAQUINARIA!$B$3:$B$655,"<>",MAQUINARIA!$B$3:$B$655,"<>Seguimiento",MAQUINARIA!$H$3:$H$655,"DONANTE") -> 5 | E12: =COUNTIFS(MAQUINARIA!$B$3:$B$655,"<>",MAQUINARIA!$B$3:$B$655,"<>Seguimiento",MAQUINARIA!$H$3:$H$655,"SINIESTRADO") -> 2 | F12: =SUM(B12:E12) -> 126 | G12: =IF(F12>0,B12/F12,0) -> 0.64285714
B13: en operación | C13: en reparación | D13: para refacciones | E13: fuera de operación | F13: flota total | G13: de la flota
B15: 💰 COMPARATIVO DE COSTOS — PARTIDAS EN COTIZACIÓN (Excluye Servicios de Filtros)
B16: MATCO (MXN) | C16: HAWTHORNE (USD) | D16: CTP (USD) | E16: TIPO DE CAMBIO
B17: =SUMIFS(Tabla3[COSTO TOTAL SIN IVA PESOS EN MATCO],Tabla3[STATUS],"COTIZANDO",Tabla3[TEMA],"<>SERVICIO DE FILTROS") -> 6047672 | C17: =SUMIFS(Tabla3[COSTO TOTAL DOLARES EN HAWTHORNE],Tabla3[STATUS],"COTIZANDO",Tabla3[TEMA],"<>SERVICIO DE FILTROS") -> 191410.88 | D17: =SUMIFS(Tabla3[COSTO TOTAL DOLARES CTP],Tabla3[STATUS],"COTIZANDO",Tabla3[TEMA],"<>SERVICIO DE FILTROS") -> 23109.76 | E17: =IF('RESUMEN GLOBAL'!E3="","$0.00 MXN/USD","$"&TEXT('RESUMEN GLOBAL'!E3,"#,##0.00")&" MXN/USD") -> $17.00 MXN/USD
B18: pesos sin IVA | C18: dólares | D18: dólares | E18: capturado en Resumen
B20: 🔧 MONTOS PARA REPARACIÓN DE UNIDADES INACTIVAS
B21: NÚM. ECON. | C21: MODELO | D21: ESTATUS | E21: COSTO MATCO (MXN) | F21: COSTO CTP (USD) | G21: COSTO HAWTHORNE (USD)
B22: {=IFERROR(INDEX(_xlfn._xlws.FILTER('RESUMEN GLOBAL'!B12:B25,'RESUMEN GLOBAL'!C12:C25="INACTIVA"),1),"")} -> CL-01 | C22: {=IFERROR(INDEX(_xlfn._xlws.FILTER('RESUMEN GLOBAL'!D12:D25,'RESUMEN GLOBAL'!C12:C25="INACTIVA"),1),"")} -> CAMION DE LAVADO 650 | D22: =IF(B22<>"","INACTIVA","") -> INACTIVA | E22: {=IFERROR(INDEX(_xlfn._xlws.FILTER('RESUMEN GLOBAL'!G12:G25,'RESUMEN GLOBAL'!C12:C25="INACTIVA"),1),0)} -> 0 | F22: =IF(B22="",0,IFERROR(_xlfn.NUMBERVALUE(SUBSTITUTE(SUBSTITUTE(_xlfn.XLOOKUP(B22,'RESUMEN GLOBAL'!$B$12:$B$25,'RESUMEN GLOBAL'!$J$12:$J$25)," USD",""),"$",""),".",","),0)) -> 0 | G22: =IF(B22="",0,IFERROR(_xlfn.NUMBERVALUE(SUBSTITUTE(SUBSTITUTE(_xlfn.XLOOKUP(B22,'RESUMEN GLOBAL'!$B$12:$B$25,'RESUMEN GLOBAL'!$H$12:$H$25)," USD",""),"$",""),".",","),0)) -> 0
B23: {=IFERROR(INDEX(_xlfn._xlws.FILTER('RESUMEN GLOBAL'!B12:B25,'RESUMEN GLOBAL'!C12:C25="INACTIVA"),2),"")} -> CM-04 | C23: {=IFERROR(INDEX(_xlfn._xlws.FILTER('RESUMEN GLOBAL'!D12:D25,'RESUMEN GLOBAL'!C12:C25="INACTIVA"),2),"")} -> CAMA BAJA DOLLY | D23: =IF(B23<>"","INACTIVA","") -> INACTIVA | E23: {=IFERROR(INDEX(_xlfn._xlws.FILTER('RESUMEN GLOBAL'!G12:G25,'RESUMEN GLOBAL'!C12:C25="INACTIVA"),2),0)} -> 0 | F23: =IF(B23="",0,IFERROR(_xlfn.NUMBERVALUE(SUBSTITUTE(SUBSTITUTE(_xlfn.XLOOKUP(B23,'RESUMEN GLOBAL'!$B$12:$B$25,'RESUMEN GLOBAL'!$J$12:$J$25)," USD",""),"$",""),".",","),0)) -> 0 | G23: =IF(B23="",0,IFERROR(_xlfn.NUMBERVALUE(SUBSTITUTE(SUBSTITUTE(_xlfn.XLOOKUP(B23,'RESUMEN GLOBAL'!$B$12:$B$25,'RESUMEN GLOBAL'!$H$12:$H$25)," USD",""),"$",""),".",","),0)) -> 0
B24: {=IFERROR(INDEX(_xlfn._xlws.FILTER('RESUMEN GLOBAL'!B12:B25,'RESUMEN GLOBAL'!C12:C25="INACTIVA"),3),"")} -> CRC-04 | C24: {=IFERROR(INDEX(_xlfn._xlws.FILTER('RESUMEN GLOBAL'!D12:D25,'RESUMEN GLOBAL'!C12:C25="INACTIVA"),3),"")} -> CAMION REVOLVEDOR 7 MTS | D24: =IF(B24<>"","INACTIVA","") -> INACTIVA | E24: {=IFERROR(INDEX(_xlfn._xlws.FILTER('RESUMEN GLOBAL'!G12:G25,'RESUMEN GLOBAL'!C12:C25="INACTIVA"),3),0)} -> 0 | F24: =IF(B24="",0,IFERROR(_xlfn.NUMBERVALUE(SUBSTITUTE(SUBSTITUTE(_xlfn.XLOOKUP(B24,'RESUMEN GLOBAL'!$B$12:$B$25,'RESUMEN GLOBAL'!$J$12:$J$25)," USD",""),"$",""),".",","),0)) -> 0 | G24: =IF(B24="",0,IFERROR(_xlfn.NUMBERVALUE(SUBSTITUTE(SUBSTITUTE(_xlfn.XLOOKUP(B24,'RESUMEN GLOBAL'!$B$12:$B$25,'RESUMEN GLOBAL'!$H$12:$H$25)," USD",""),"$",""),".",","),0)) -> 0
B25: {=IFERROR(INDEX(_xlfn._xlws.FILTER('RESUMEN GLOBAL'!B12:B25,'RESUMEN GLOBAL'!C12:C25="INACTIVA"),4),"")} | C25: {=IFERROR(INDEX(_xlfn._xlws.FILTER('RESUMEN GLOBAL'!D12:D25,'RESUMEN GLOBAL'!C12:C25="INACTIVA"),4),"")} | D25: =IF(B25<>"","INACTIVA","") | E25: {=IFERROR(INDEX(_xlfn._xlws.FILTER('RESUMEN GLOBAL'!G12:G25,'RESUMEN GLOBAL'!C12:C25="INACTIVA"),4),0)} -> 0 | F25: =IF(B25="",0,IFERROR(_xlfn.NUMBERVALUE(SUBSTITUTE(SUBSTITUTE(_xlfn.XLOOKUP(B25,'RESUMEN GLOBAL'!$B$12:$B$25,'RESUMEN GLOBAL'!$J$12:$J$25)," USD",""),"$",""),".",","),0)) -> 0 | G25: =IF(B25="",0,IFERROR(_xlfn.NUMBERVALUE(SUBSTITUTE(SUBSTITUTE(_xlfn.XLOOKUP(B25,'RESUMEN GLOBAL'!$B$12:$B$25,'RESUMEN GLOBAL'!$H$12:$H$25)," USD",""),"$",""),".",","),0)) -> 0
B26: {=IFERROR(INDEX(_xlfn._xlws.FILTER('RESUMEN GLOBAL'!B12:B25,'RESUMEN GLOBAL'!C12:C25="INACTIVA"),5),"")} | C26: {=IFERROR(INDEX(_xlfn._xlws.FILTER('RESUMEN GLOBAL'!D12:D25,'RESUMEN GLOBAL'!C12:C25="INACTIVA"),5),"")} | D26: =IF(B26<>"","INACTIVA","") | E26: {=IFERROR(INDEX(_xlfn._xlws.FILTER('RESUMEN GLOBAL'!G12:G25,'RESUMEN GLOBAL'!C12:C25="INACTIVA"),5),0)} -> 0 | F26: =IF(B26="",0,IFERROR(_xlfn.NUMBERVALUE(SUBSTITUTE(SUBSTITUTE(_xlfn.XLOOKUP(B26,'RESUMEN GLOBAL'!$B$12:$B$25,'RESUMEN GLOBAL'!$J$12:$J$25)," USD",""),"$",""),".",","),0)) -> 0 | G26: =IF(B26="",0,IFERROR(_xlfn.NUMBERVALUE(SUBSTITUTE(SUBSTITUTE(_xlfn.XLOOKUP(B26,'RESUMEN GLOBAL'!$B$12:$B$25,'RESUMEN GLOBAL'!$H$12:$H$25)," USD",""),"$",""),".",","),0)) -> 0
B27: {=IFERROR(INDEX(_xlfn._xlws.FILTER('RESUMEN GLOBAL'!B12:B25,'RESUMEN GLOBAL'!C12:C25="INACTIVA"),6),"")} | C27: {=IFERROR(INDEX(_xlfn._xlws.FILTER('RESUMEN GLOBAL'!D12:D25,'RESUMEN GLOBAL'!C12:C25="INACTIVA"),6),"")} | D27: =IF(B27<>"","INACTIVA","") | E27: {=IFERROR(INDEX(_xlfn._xlws.FILTER('RESUMEN GLOBAL'!G12:G25,'RESUMEN GLOBAL'!C12:C25="INACTIVA"),6),0)} -> 0 | F27: =IF(B27="",0,IFERROR(_xlfn.NUMBERVALUE(SUBSTITUTE(SUBSTITUTE(_xlfn.XLOOKUP(B27,'RESUMEN GLOBAL'!$B$12:$B$25,'RESUMEN GLOBAL'!$J$12:$J$25)," USD",""),"$",""),".",","),0)) -> 0 | G27: =IF(B27="",0,IFERROR(_xlfn.NUMBERVALUE(SUBSTITUTE(SUBSTITUTE(_xlfn.XLOOKUP(B27,'RESUMEN GLOBAL'!$B$12:$B$25,'RESUMEN GLOBAL'!$H$12:$H$25)," USD",""),"$",""),".",","),0)) -> 0
B28: {=IFERROR(INDEX(_xlfn._xlws.FILTER('RESUMEN GLOBAL'!B12:B25,'RESUMEN GLOBAL'!C12:C25="INACTIVA"),7),"")} | C28: {=IFERROR(INDEX(_xlfn._xlws.FILTER('RESUMEN GLOBAL'!D12:D25,'RESUMEN GLOBAL'!C12:C25="INACTIVA"),7),"")} | D28: =IF(B28<>"","INACTIVA","") | E28: {=IFERROR(INDEX(_xlfn._xlws.FILTER('RESUMEN GLOBAL'!G12:G25,'RESUMEN GLOBAL'!C12:C25="INACTIVA"),7),0)} -> 0 | F28: =IF(B28="",0,IFERROR(_xlfn.NUMBERVALUE(SUBSTITUTE(SUBSTITUTE(_xlfn.XLOOKUP(B28,'RESUMEN GLOBAL'!$B$12:$B$25,'RESUMEN GLOBAL'!$J$12:$J$25)," USD",""),"$",""),".",","),0)) -> 0 | G28: =IF(B28="",0,IFERROR(_xlfn.NUMBERVALUE(SUBSTITUTE(SUBSTITUTE(_xlfn.XLOOKUP(B28,'RESUMEN GLOBAL'!$B$12:$B$25,'RESUMEN GLOBAL'!$H$12:$H$25)," USD",""),"$",""),".",","),0)) -> 0
B29: {=IFERROR(INDEX(_xlfn._xlws.FILTER('RESUMEN GLOBAL'!B12:B25,'RESUMEN GLOBAL'!C12:C25="INACTIVA"),8),"")} | C29: {=IFERROR(INDEX(_xlfn._xlws.FILTER('RESUMEN GLOBAL'!D12:D25,'RESUMEN GLOBAL'!C12:C25="INACTIVA"),8),"")} | D29: =IF(B29<>"","INACTIVA","") | E29: {=IFERROR(INDEX(_xlfn._xlws.FILTER('RESUMEN GLOBAL'!G12:G25,'RESUMEN GLOBAL'!C12:C25="INACTIVA"),8),0)} -> 0 | F29: =IF(B29="",0,IFERROR(_xlfn.NUMBERVALUE(SUBSTITUTE(SUBSTITUTE(_xlfn.XLOOKUP(B29,'RESUMEN GLOBAL'!$B$12:$B$25,'RESUMEN GLOBAL'!$J$12:$J$25)," USD",""),"$",""),".",","),0)) -> 0 | G29: =IF(B29="",0,IFERROR(_xlfn.NUMBERVALUE(SUBSTITUTE(SUBSTITUTE(_xlfn.XLOOKUP(B29,'RESUMEN GLOBAL'!$B$12:$B$25,'RESUMEN GLOBAL'!$H$12:$H$25)," USD",""),"$",""),".",","),0)) -> 0
B30: {=IFERROR(INDEX(_xlfn._xlws.FILTER('RESUMEN GLOBAL'!B12:B25,'RESUMEN GLOBAL'!C12:C25="INACTIVA"),9),"")} | C30: {=IFERROR(INDEX(_xlfn._xlws.FILTER('RESUMEN GLOBAL'!D12:D25,'RESUMEN GLOBAL'!C12:C25="INACTIVA"),9),"")} | D30: =IF(B30<>"","INACTIVA","") | E30: {=IFERROR(INDEX(_xlfn._xlws.FILTER('RESUMEN GLOBAL'!G12:G25,'RESUMEN GLOBAL'!C12:C25="INACTIVA"),9),0)} -> 0 | F30: =IF(B30="",0,IFERROR(_xlfn.NUMBERVALUE(SUBSTITUTE(SUBSTITUTE(_xlfn.XLOOKUP(B30,'RESUMEN GLOBAL'!$B$12:$B$25,'RESUMEN GLOBAL'!$J$12:$J$25)," USD",""),"$",""),".",","),0)) -> 0 | G30: =IF(B30="",0,IFERROR(_xlfn.NUMBERVALUE(SUBSTITUTE(SUBSTITUTE(_xlfn.XLOOKUP(B30,'RESUMEN GLOBAL'!$B$12:$B$25,'RESUMEN GLOBAL'!$H$12:$H$25)," USD",""),"$",""),".",","),0)) -> 0
B31: {=IFERROR(INDEX(_xlfn._xlws.FILTER('RESUMEN GLOBAL'!B12:B25,'RESUMEN GLOBAL'!C12:C25="INACTIVA"),10),"")} | C31: {=IFERROR(INDEX(_xlfn._xlws.FILTER('RESUMEN GLOBAL'!D12:D25,'RESUMEN GLOBAL'!C12:C25="INACTIVA"),10),"")} | D31: =IF(B31<>"","INACTIVA","") | E31: {=IFERROR(INDEX(_xlfn._xlws.FILTER('RESUMEN GLOBAL'!G12:G25,'RESUMEN GLOBAL'!C12:C25="INACTIVA"),10),0)} -> 0 | F31: =IF(B31="",0,IFERROR(_xlfn.NUMBERVALUE(SUBSTITUTE(SUBSTITUTE(_xlfn.XLOOKUP(B31,'RESUMEN GLOBAL'!$B$12:$B$25,'RESUMEN GLOBAL'!$J$12:$J$25)," USD",""),"$",""),".",","),0)) -> 0 | G31: =IF(B31="",0,IFERROR(_xlfn.NUMBERVALUE(SUBSTITUTE(SUBSTITUTE(_xlfn.XLOOKUP(B31,'RESUMEN GLOBAL'!$B$12:$B$25,'RESUMEN GLOBAL'!$H$12:$H$25)," USD",""),"$",""),".",","),0)) -> 0
B32: TOTAL REQUERIDO PARA REPARACIONES | E32: =SUM(E22:E31) -> 0 | F32: =SUM(F22:F31) -> 0 | G32: =SUM(G22:G31) -> 0
B35: 📈 RESUMEN COMPARATIVO DE PROVEEDORES
B36: PROVEEDOR | C36: PARTIDAS COTIZADAS | D36: COSTO TOTAL | E36: MONEDA
B37: MATCO | C37: =COUNTIFS(Tabla3[STATUS],"COTIZANDO",Tabla3[COSTO TOTAL SIN IVA PESOS EN MATCO],">0") -> 703 | D37: =SUMIF(Tabla3[STATUS],"COTIZANDO",Tabla3[COSTO TOTAL SIN IVA PESOS EN MATCO]) -> 6049092.5 | E37: MXN
B38: HAWTHORNE | C38: {=SUMPRODUCT((Tabla3[STATUS]="COTIZANDO")*(Tabla3[COSTO TOTAL DOLARES EN HAWTHORNE]>0)*1)} -> 190 | D38: =SUMIF(Tabla3[STATUS],"COTIZANDO",Tabla3[COSTO TOTAL DOLARES EN HAWTHORNE]) -> 191410.88 | E38: USD
B39: CTP | C39: {=SUMPRODUCT((Tabla3[STATUS]="COTIZANDO")*(Tabla3[COSTO TOTAL DOLARES CTP]>0)*1)} -> 153 | D39: =SUMIF(Tabla3[STATUS],"COTIZANDO",Tabla3[COSTO TOTAL DOLARES CTP]) -> 23109.76 | E39: USD
B42: 📌 Los datos se actualizan automáticamente desde las hojas CONTROL y MAQUINARIA. Capture el tipo de cambio en RESUMEN GLOBAL para ver conversiones a MXN.
B44: 🔧 SERVICIOS DE FILTROS — Costos Operativos (Separados)
B45: NÚM. ECON. | C45: PEDIDO | D45: PARTIDAS | E45: MATCO (MXN) | F45: CTP (USD)
B46: ='RESUMEN GLOBAL'!B136 -> TM-03 | C46: ='RESUMEN GLOBAL'!C136 -> Pedido 119 | D46: ='RESUMEN GLOBAL'!D136 -> 5 | E46: ='RESUMEN GLOBAL'!E136 -> 1420.55 | F46: ='RESUMEN GLOBAL'!H136 -> 0
B47: ='RESUMEN GLOBAL'!B137 | C47: ='RESUMEN GLOBAL'!C137 | D47: ='RESUMEN GLOBAL'!D137 | E47: ='RESUMEN GLOBAL'!E137 | F47: ='RESUMEN GLOBAL'!H137
B48: ='RESUMEN GLOBAL'!B145 -> TOTAL FILTROS | D48: ='RESUMEN GLOBAL'!D145 -> 5 | E48: ='RESUMEN GLOBAL'!E145 -> 1420.55 | F48: ='RESUMEN GLOBAL'!H145 -> 0

Sheet CONTROL
A1: PEDIDO | B1: FECHA DE SOLICITUD | C1: QUIEN SOLICITA | D1: OC | E1: REQUISICION | F1: FECHA DE REQ | G1: ESTATUS DE NUM ECONOMICO | H1: NUM ECONOMICO | I1: NUMERO DE PARTE | J1: DESCRIPCION | K1: CANTIDAD SOLICTADA | L1: COSTO UNITARIO EN MATCO PESOS | M1: COSTO TOTAL SIN IVA PESOS EN MATCO | N1: DIAS DE ENTREGA TENTATIVO EN MATCO | O1: COSTO UNITARIO DOLARES EN HAWTHORNE | P1: COSTO TOTAL DOLARES EN HAWTHORNE | Q1: DIAS TENTATIVO DE ENTREGA HAWTHORNE | R1: COSTO UNITARIO DOLARES CTP | S1: COSTO TOTAL DOLARES CTP | T1: DIAS TENTATIVO DE ENTREGA CTP | U1: STATUS | V1: NUMERO DE COTIZACION | W1: FECHA DE ENTREGA | X1: EN ESTOCK | Y1: CANTIDAD EN ESTOCK | Z1: PEDIDO A PROVEEDOR | AA1: FECHA DE PEDIDO | AB1: FECHA TENTATIVA DE ENTREGA | AC1: QUIEN RECIBE | AD1: REMISION DE SALIDA | AE1: COMENTARIOS | AF1: COMENTARIOS 2 | AG1: TEMA
A2: 1 | B2: 46163 | C2: SERGIO | E2: 16 | F2: 46171 | G2: =IFERROR(VLOOKUP(Tabla3[[#This Row],[NUM ECONOMICO]],MAQUINARIA!B:H,7,0), " MAQ") -> ACTIVA | H2: MR-01 | I2: 5917178 | K2: 2 | M2: =+L2*K2 -> 0 | P2: =Tabla3[[#This Row],[COSTO UNITARIO DOLARES EN HAWTHORNE]]*Tabla3[[#This Row],[CANTIDAD SOLICTADA]] -> 0 | S2: =+Tabla3[[#This Row],[COSTO UNITARIO DOLARES CTP]]*Tabla3[[#This Row],[CANTIDAD SOLICTADA]] -> 0 | U2: ENTREGADO | V2: QT-08-427805 | W2: 46170 | X2: NO | Y2: SIN EXISTENCIA | Z2: MATCO | AA2: 46167 | AB2: 46170 | AC2: JAVIER G
A3: 1 | B3: 46163 | C3: SERGIO | E3: 16 | F3: 46171 | G3: =IFERROR(VLOOKUP(Tabla3[[#This Row],[NUM ECONOMICO]],MAQUINARIA!B:H,7,0), " MAQ") -> ACTIVA | H3: MR-01 | I3: 1218167 | K3: 2 | M3: =+L3*K3 -> 0 | P3: =Tabla3[[#This Row],[COSTO UNITARIO DOLARES EN HAWTHORNE]]*Tabla3[[#This Row],[CANTIDAD SOLICTADA]] -> 0 | S3: =+Tabla3[[#This Row],[COSTO UNITARIO DOLARES CTP]]*Tabla3[[#This Row],[CANTIDAD SOLICTADA]] -> 0 | U3: ENTREGADO | V3: QT-08-427805 | W3: 46170 | X3: NO | Y3: SIN EXISTENCIA | Z3: MATCO | AA3: 46167 | AB3: 46170 | AC3: JAVIER G
A4: 1 | B4: 46163 | C4: SERGIO | E4: 16 | F4: 46171 | G4: =IFERROR(VLOOKUP(Tabla3[[#This Row],[NUM ECONOMICO]],MAQUINARIA!B:H,7,0), " MAQ") -> ACTIVA | H4: MR-01 | I4: 4364462 | K4: 2 | M4: =+L4*K4 -> 0 | P4: =Tabla3[[#This Row],[COSTO UNITARIO DOLARES EN HAWTHORNE]]*Tabla3[[#This Row],[CANTIDAD SOLICTADA]] -> 0 | S4: =+Tabla3[[#This Row],[COSTO UNITARIO DOLARES CTP]]*Tabla3[[#This Row],[CANTIDAD SOLICTADA]] -> 0 | U4: ENTREGADO | V4: QT-08-427805 | W4: 46170 | X4: NO | Y4: SIN EXISTENCIA | Z4: MATCO | AA4: 46167 | AB4: 46170 | AC4: JAVIER G
A5: 1 | B5: 46163 | C5: SERGIO | E5: 16 | F5: 46171 | G5: =IFERROR(VLOOKUP(Tabla3[[#This Row],[NUM ECONOMICO]],MAQUINARIA!B:H,7,0), " MAQ") -> ACTIVA | H5: MR-01 | I5: 7X5762 | K5: 1 | M5: =+L5*K5 -> 0 | P5: =Tabla3[[#This Row],[COSTO UNITARIO DOLARES EN HAWTHORNE]]*Tabla3[[#This Row],[CANTIDAD SOLICTADA]] -> 0 | S5: =+Tabla3[[#This Row],[COSTO UNITARIO DOLARES CTP]]*Tabla3[[#This Row],[CANTIDAD SOLICTADA]] -> 0 | U5: ENTREGADO | V5: QT-08-427805 | W5: 46170 | X5: NO | Y5: SIN EXISTENCIA | Z5: MATCO | AA5: 46167 | AB5: 46170 | AC5: JAVIER G
A6: 1 | B6: 46163 | C6: SERGIO | E6: 16 | F6: 46171 | G6: =IFERROR(VLOOKUP(Tabla3[[#This Row],[NUM ECONOMICO]],MAQUINARIA!B:H,7,0), " MAQ") -> ACTIVA | H6: MR-01 | I6: 4826731 | K6: 8 | M6: =+L6*K6 -> 0 | P6: =Tabla3[[#This Row],[COSTO UNITARIO DOLARES EN HAWTHORNE]]*Tabla3[[#This Row],[CANTIDAD SOLICTADA]] -> 0 | S6: =+Tabla3[[#This Row],[COSTO UNITARIO DOLARES CTP]]*Tabla3[[#This Row],[CANTIDAD SOLICTADA]] -> 0 | U6: ENTREGADO | V6: QT-08-427805 | W6: 46170 | X6: NO | Y6: SIN EXISTENCIA | Z6: MATCO | AA6: 46167 | AB6: 46170 | AC6: JAVIER G
A7: 1 | B7: 46163 | C7: SERGIO | E7: 16 | F7: 46171 | G7: =IFERROR(VLOOKUP(Tabla3[[#This Row],[NUM ECONOMICO]],MAQUINARIA!B:H,7,0), " MAQ") -> ACTIVA | H7: MR-01 | I7: 4858330 | K7: 8 | M7: =+L7*K7 -> 0 | P7: =Tabla3[[#This Row],[COSTO UNITARIO DOLARES EN HAWTHORNE]]*Tabla3[[#This Row],[CANTIDAD SOLICTADA]] -> 0 | S7: =+Tabla3[[#This Row],[COSTO UNITARIO DOLARES CTP]]*Tabla3[[#This Row],[CANTIDAD SOLICTADA]] -> 0 | U7: ENTREGADO | V7: QT-08-427805 | W7: 46170 | X7: NO | Y7: SIN EXISTENCIA | Z7: MATCO | AA7: 46167 | AB7: 46170 | AC7: JAVIER G
A8: 1 | B8: 46163 | C8: SERGIO | E8: 16 | F8: 46171 | G8: =IFERROR(VLOOKUP(Tabla3[[#This Row],[NUM ECONOMICO]],MAQUINARIA!B:H,7,0), " MAQ") -> ACTIVA | H8: MR-01 | I8: 3752548 | K8: 1 | M8: =+L8*K8 -> 0 | P8: =Tabla3[[#This Row],[COSTO UNITARIO DOLARES EN HAWTHORNE]]*Tabla3[[#This Row],[CANTIDAD SOLICTADA]] -> 0 | S8: =+Tabla3[[#This Row],[COSTO UNITARIO DOLARES CTP]]*Tabla3[[#This Row],[CANTIDAD SOLICTADA]] -> 0 | U8: ENTREGADO | V8: QT-08-427805 | W8: 46170 | X8: NO | Y8: SIN EXISTENCIA | Z8: MATCO | AA8: 46167 | AB8: 46170 | AC8: JAVIER G
A9: 1 | B9: 46163 | C9: SERGIO | E9: 16 | F9: 46171 | G9: =IFERROR(VLOOKUP(Tabla3[[#This Row],[NUM ECONOMICO]],MAQUINARIA!B:H,7,0), " MAQ") -> ACTIVA | H9: MR-01 | I9: 4945603 | K9: 1 | M9: =+L9*K9 -> 0 | P9: =Tabla3[[#This Row],[COSTO UNITARIO DOLARES EN HAWTHORNE]]*Tabla3[[#This Row],[CANTIDAD SOLICTADA]] -> 0 | S9: =+Tabla3[[#This Row],[COSTO UNITARIO DOLARES CTP]]*Tabla3[[#This Row],[CANTIDAD SOLICTADA]] -> 0 | U9: ENTREGADO | V9: QT-08-427805 | W9: 46181 | X9: NO | Y9: SIN EXISTENCIA | AE9: COMENTA BENJAMIN QUE YA SE ENTREGO
A10: 2 | B10: 46163 | C10: SERGIO | G10: =IFERROR(VLOOKUP(Tabla3[[#This Row],[NUM ECONOMICO]],MAQUINARIA!B:H,7,0), " MAQ") -> ACTIVA | H10: MT-08 | I10: 1P3705 | K10: 30 | M10: =+L10*K10 -> 0 | P10: =Tabla3[[#This Row],[COSTO UNITARIO DOLARES EN HAWTHORNE]]*Tabla3[[#This Row],[CANTIDAD SOLICTADA]] -> 0 | S10: =+Tabla3[[#This Row],[COSTO UNITARIO DOLARES CTP]]*Tabla3[[#This Row],[CANTIDAD SOLICTADA]] -> 0 | U10: ENTREGADO | X10: SI | Y10: 6
A11: 2 | B11: 46163 | C11: SERGIO | E11: 1028 | F11: 45952 | G11: =IFERROR(VLOOKUP(Tabla3[[#This Row],[NUM ECONOMICO]],MAQUINARIA!B:H,7,0), " MAQ") -> ACTIVA | H11: MT-08 | I11: 4C4782 / 2701528 | K11: 2 | L11: 25068.48 | M11: =+L11*K11 -> 50136.96 | P11: =Tabla3[[#This Row],[COSTO UNITARIO DOLARES EN HAWTHORNE]]*Tabla3[[#This Row],[CANTIDAD SOLICTADA]] -> 0 | S11: =+Tabla3[[#This Row],[COSTO UNITARIO DOLARES CTP]]*Tabla3[[#This Row],[CANTIDAD SOLICTADA]] -> 0 | U11: ENTREGADO | V11: QT-08-427516 | X11: NO | Y11: SIN EXISTENCIA | AE11: ENTREGADO A BENJAMIN POSIBLE COMPRA CTP | AF11: SOLICITAR A BENJA COMPRA EN CTP | AG11: MALETIN DE SELLOS
A12: 3 | B12: 46164 | C12: SERGIO | G12: =IFERROR(VLOOKUP(Tabla3[[#This Row],[NUM ECONOMICO]],MAQUINARIA!B:H,7,0), " MAQ") -> ACTIVA | H12: MM-02 | I12: 3F5108 | K12: 6 | M12: =+L12*K12 -> 0 | P12: =Tabla3[[#This Row],[COSTO UNITARIO DOLARES EN HAWTHORNE]]*Tabla3[[#This Row],[CANTIDAD SOLICTADA]] -> 0 | S12: =+Tabla3[[#This Row],[COSTO UNITARIO DOLARES CTP]]*Tabla3[[#This Row],[CANTIDAD SOLICTADA]] -> 0 | U12: CANCELADO | W12: 46164 | X12: SI | Y12: 7 | AE12: SE ENTREGARON SOLO 8 DE 4F3653 VER R-1666
A13: 3 | B13: 46164 | C13: SERGIO | G13: =IFERROR(VLOOKUP(Tabla3[[#This Row],[NUM ECONOMICO]],MAQUINARIA!B:H,7,0), " MAQ") -> ACTIVA | H13: MM-02 | I13: 4K0367 | K13: 6 | M13: =+L13*K13 -> 0 | P13: =Tabla3[[#This Row],[COSTO UNITARIO DOLARES EN HAWTHORNE]]*Tabla3[[#This Row],[CANTIDAD SOLICTADA]] -> 0 | S13: =+Tabla3[[#This Row],[COSTO UNITARIO DOLARES CTP]]*Tabla3[[#This Row],[CANTIDAD SOLICTADA]] -> 0 | U13: CANCELADO | W13: 46164 | X13: SI | Y13: 85 | AE13: SE ENTREGARON SOLO 8 DE 4F3653 VER R-1666
A14: 4 | B14: 46164 | C14: SERGIO | D14: CE-1421 | G14: =IFERROR(VLOOKUP(Tabla3[[#This Row],[NUM ECONOMICO]],MAQUINARIA!B:H,7,0), " MAQ") -> ACTIVA | H14: MC-04 | I14: 1781318 | K14: 1 | M14: =+L14*K14 -> 0 | P14: =Tabla3[[#This Row],[COSTO UNITARIO DOLARES EN HAWTHORNE]]*Tabla3[[#This Row],[CANTIDAD SOLICTADA]] -> 0 | S14: =+Tabla3[[#This Row],[COSTO UNITARIO DOLARES CTP]]*Tabla3[[#This Row],[CANTIDAD SOLICTADA]] -> 0 | U14: ENTREGADO | V14: QT-08-427536 | W14: 46168 | X14: NO | Y14: SIN EXISTENCIA | Z14: MATCO | AA14: 46167 | AB14: 46168 | AC14: EDUARDO CHOFER | AE14: SE ENTREGA EN OBRA
A15: 4 | B15: 46164 | C15: SERGIO | G15: =IFERROR(VLOOKUP(Tabla3[[#This Row],[NUM ECONOMICO]],MAQUINARIA!B:H,7,0), " MAQ") -> ACTIVA | H15: MC-04 | I15: 1917944 | K15: 1 | M15: =+L15*K15 -> 0 | P15: =Tabla3[[#This Row],[COSTO UNITARIO DOLARES EN HAWTHORNE]]*Tabla3[[#This Row],[CANTIDAD SOLICTADA]] -> 0 | S15: =+Tabla3[[#This Row],[COSTO UNITARIO DOLARES CTP]]*Tabla3[[#This Row],[CANTIDAD SOLICTADA]] -> 0 | U15: ENTREGADO | X15: SI | Y15: SIN EXISTENCIA | Z15: MATCO | AA15: 46167 | AB15: 46167 | AE15: PENDIENTE POR RECOGER SERGIO
A16: 5 | B16: 46164 | C16: JAVIER | G16: =IFERROR(VLOOKUP(Tabla3[[#This Row],[NUM ECONOMICO]],MAQUINARIA!B:H,7,0), " MAQ") -> ACTIVA | H16: ME-23 | I16: 4J8665 | K16: 2 | M16: =+L16*K16 -> 0 | P16: =Tabla3[[#This Row],[COSTO UNITARIO DOLARES EN HAWTHORNE]]*Tabla3[[#This Row],[CANTIDAD SOLICTADA]] -> 0 | S16: =+Tabla3[[#This Row],[COSTO UNITARIO DOLARES CTP]]*Tabla3[[#This Row],[CANTIDAD SOLICTADA]] -> 0 | U16: ENTREGADO | W16: 46164 | X16: SI | Y16: 0 | AC16: JAVIER G | AD16: R-1663
A17: 5 | B17: 46164 | C17: JAVIER | G17: =IFERROR(VLOOKUP(Tabla3[[#This Row],[NUM ECONOMICO]],MAQUINARIA!B:H,7,0), " MAQ") -> ACTIVA | H17: ME-23 | I17: 9W6092 | K17: 2 | M17: =+L17*K17 -> 0 | P17: =Tabla3[[#This Row],[COSTO UNITARIO DOLARES EN HAWTHORNE]]*Tabla3[[#This Row],[CANTIDAD SOLICTADA]] -> 0 | S17: =+Tabla3[[#This Row],[COSTO UNITARIO DOLARES CTP]]*Tabla3[[#This Row],[CANTIDAD SOLICTADA]] -> 0 | U17: ENTREGADO | W17: 46164 | X17: SI | Y17: 0 | AC17: JAVIER G | AD17: R-1663
A18: 5 | B18: 46164 | C18: JAVIER | G18: =IFERROR(VLOOKUP(Tabla3[[#This Row],[NUM ECONOMICO]],MAQUINARIA!B:H,7,0), " MAQ") -> ACTIVA | H18: ME-23 | I18: 4J9208 | K18: 32 | M18: =+L18*K18 -> 0 | P18: =Tabla3[[#This Row],[COSTO UNITARIO DOLARES EN HAWTHORNE]]*Tabla3[[#This Row],[CANTIDAD SOLICTADA]] -> 0 | S18: =+Tabla3[[#This Row],[COSTO UNITARIO DOLARES CTP]]*Tabla3[[#This Row],[CANTIDAD SOLICTADA]] -> 0 | U18: ENTREGADO | W18: 46164 | X18: SI | Y18: 0 | AC18: JAVIER G | AD18: R-1663
A19: 5 | B19: 46164 | C19: JAVIER | G19: =IFERROR(VLOOKUP(Tabla3[[#This Row],[NUM ECONOMICO]],MAQUINARIA!B:H,7,0), " MAQ") -> ACTIVA | H19: ME-23 | I19: 2J3507 | K19: 32 | M19: =+L19*K19 -> 0 | P19: =Tabla3[[#This Row],[COSTO UNITARIO DOLARES EN HAWTHORNE]]*Tabla3[[#This Row],[CANTIDAD SOLICTADA]] -> 0 | S19: =+Tabla3[[#This Row],[COSTO UNITARIO DOLARES CTP]]*Tabla3[[#This Row],[CANTIDAD SOLICTADA]] -> 0 | U19: ENTREGADO | W19: 46164 | X19: SI | Y19: 682 | AC19: JAVIER G | AD19: R-1663
A20: 6 | B20: 46164 | C20: JAVIER | G20: =IFERROR(VLOOKUP(Tabla3[[#This Row],[NUM ECONOMICO]],MAQUINARIA!B:H,7,0), " MAQ") -> ACTIVA | H20: ME-03 | I20: 4J9208 | K20: 22 | M20: =+L20*K20 -> 0 | P20: =Tabla3[[#This Row],[COSTO UNITARIO DOLARES EN HAWTHORNE]]*Tabla3[[#This Row],[CANTIDAD SOLICTADA]] -> 0 | S20: =+Tabla3[[#This Row],[COSTO UNITARIO DOLARES CTP]]*Tabla3[[#This Row],[CANTIDAD SOLICTADA]] -> 0 | U20: ENTREGADO | W20: 46164 | X20: SI | Y20: 0 | AC20: JAVIER G | AD20: R-1664
A21: 6 | B21: 46164 | C21: JAVIER | G21: =IFERROR(VLOOKUP(Tabla3[[#This Row],[NUM ECONOMICO]],MAQUINARIA!B:H,7,0), " MAQ") -> ACTIVA | H21: ME-03 | I21: 4J9208 | K21: 22 | M21: =+L21*K21 -> 0 | P21: =Tabla3[[#This Row],[COSTO UNITARIO DOLARES EN HAWTHORNE]]*Tabla3[[#This Row],[CANTIDAD SOLICTADA]] -> 0 | S21: =+Tabla3[[#This Row],[COSTO UNITARIO DOLARES CTP]]*Tabla3[[#This Row],[CANTIDAD SOLICTADA]] -> 0 | U21: ENTREGADO | W21: 46164 | X21: SI | Y21: 0 | AC21: JAVIER G | AD21: R-1664
A22: 7 | B22: 46164 | C22: JAVIER | G22: =IFERROR(VLOOKUP(Tabla3[[#This Row],[NUM ECONOMICO]],MAQUINARIA!B:H,7,0), " MAQ") -> ACTIVA | H22: MT-11 | I22: 4T5502 | K22: 2 | M22: =+L22*K22 -> 0 | P22: =Tabla3[[#This Row],[COSTO UNITARIO DOLARES EN HAWTHORNE]]*Tabla3[[#This Row],[CANTIDAD SOLICTADA]] -> 0 | S22: =+Tabla3[[#This Row],[COSTO UNITARIO DOLARES CTP]]*Tabla3[[#This Row],[CANTIDAD SOLICTADA]] -> 0 | U22: ENTREGADO | W22: 46164 | X22: SI | Y22: 0 | AC22: JAVIER G | AD22: R-1665
A23: 7 | B23: 46164 | C23: JAVIER | G23: =IFERROR(VLOOKUP(Tabla3[[#This Row],[NUM ECONOMICO]],MAQUINARIA!B:H,7,0), " MAQ") -> ACTIVA | H23: MT-11 | I23: 6Y1204 | K23: 2 | M23: =+L23*K23 -> 0 | P23: =Tabla3[[#This Row],[COSTO UNITARIO DOLARES EN HAWTHORNE]]*Tabla3[[#This Row],[CANTIDAD SOLICTADA]] -> 0 | S23: =+Tabla3[[#This Row],[COSTO UNITARIO DOLARES CTP]]*Tabla3[[#This Row],[CANTIDAD SOLICTADA]] -> 0 | U23: ENTREGADO | W23: 46164 | X23: SI | Y23: 15 | AC23: JAVIER G | AD23: R-1665
A24: 7 | B24: 46164 | C24: JAVIER | G24: =IFERROR(VLOOKUP(Tabla3[[#This Row],[NUM ECONOMICO]],MAQUINARIA!B:H,7,0), " MAQ") -> ACTIVA | H24: MT-11 | I24: 6Y1205 | K24: 2 | M24: =+L24*K24 -> 0 | P24: =Tabla3[[#This Row],[COSTO UNITARIO DOLARES EN HAWTHORNE]]*Tabla3[[#This Row],[CANTIDAD SOLICTADA]] -> 0 | S24: =+Tabla3[[#This Row],[COSTO UNITARIO DOLARES CTP]]*Tabla3[[#This Row],[CANTIDAD SOLICTADA]] -> 0 | U24: ENTREGADO | W24: 46164 | X24: SI | Y24: 0 | AC24: JAVIER G | AD24: R-1665
A25: 8 | B25: 46164 | C25: DAVID | G25: =IFERROR(VLOOKUP(Tabla3[[#This Row],[NUM ECONOMICO]],MAQUINARIA!B:H,7,0), " MAQ") -> ACTIVA | H25: MM-02 | I25: 4F3653 | K25: 8 | M25: =+L25*K25 -> 0 | P25: =Tabla3[[#This Row],[COSTO UNITARIO DOLARES EN HAWTHORNE]]*Tabla3[[#This Row],[CANTIDAD SOLICTADA]] -> 0 | S25: =+Tabla3[[#This Row],[COSTO UNITARIO DOLARES CTP]]*Tabla3[[#This Row],[CANTIDAD SOLICTADA]] -> 0 | U25: ENTREGADO | W25: 46164 | X25: SI | Y25: SIN EXISTENCIA | AC25: DAVID | AD25: R-1666
A26: 9 | B26: 46164 | C26: SERGIO | G26: =IFERROR(VLOOKUP(Tabla3[[#This Row],[NUM ECONOMICO]],MAQUINARIA!B:H,7,0), " MAQ") -> ACTIVA | H26: ME-32 | I26: 1997954 | K26: 1 | M26: =+L26*K26 -> 0 | P26: =Tabla3[[#This Row],[COSTO UNITARIO DOLARES EN HAWTHORNE]]*Tabla3[[#This Row],[CANTIDAD SOLICTADA]] -> 0 | S26: =+Tabla3[[#This Row],[COSTO UNITARIO DOLARES CTP]]*Tabla3[[#This Row],[CANTIDAD SOLICTADA]] -> 0 | U26: ENTREGADO | W26: 46164 | X26: SI | Y26: 3 | AC26: SERGIO | AD26: R-1667
A27: 10 | B27: 46164 | C27: SERGIO | D27: CE-1423 | G27: =IFERROR(VLOOKUP(Tabla3[[#This Row],[NUM ECONOMICO]],MAQUINARIA!B:H,7,0), " MAQ") -> ACTIVA | H27: MT-03 | I27: 5P7593 | K27: 1 | M27: =+L27*K27 -> 0 | P27: =Tabla3[[#This Row],[COSTO UNITARIO DOLARES EN HAWTHORNE]]*Tabla3[[#This Row],[CANTIDAD SOLICTADA]] -> 0 | S27: =+Tabla3[[#This Row],[COSTO UNITARIO DOLARES CTP]]*Tabla3[[#This Row],[CANTIDAD SOLICTADA]] -> 0 | U27: ENTREGADO | V27: QT-08-427384 | W27: 46169 | X27: NO | Y27: SIN EXISTENCIA | Z27: MATCO | AA27: 46168 | AB27: 46169 | AE27: CONFIRMA SERGIO ENTREGA
A28: 10 | B28: 46164 | C28: SERGIO | D28: CE-1423 | G28: =IFERROR(VLOOKUP(Tabla3[[#This Row],[NUM ECONOMICO]],MAQUINARIA!B:H,7,0), " MAQ") -> ACTIVA | H28: MT-03 | I28: 1U1738 | K28: 1 | M28: =+L28*K28 -> 0 | P28: =Tabla3[[#This Row],[COSTO UNITARIO DOLARES EN HAWTHORNE]]*Tabla3[[#This Row],[CANTIDAD SOLICTADA]] -> 0 | S28: =+Tabla3[[#This Row],[COSTO UNITARIO DOLARES CTP]]*Tabla3[[#This Row],[CANTIDAD SOLICTADA]] -> 0 | U28: ENTREGADO | V28: QT-08-427384 | W28: 46169 | X28: NO | Y28: SIN EXISTENCIA | Z28: MATCO | AA28: 46168 | AB28: 46169 | AE28: CONFIRMA SERGIO ENTREGA
A29: 11 | B29: 46167 | C29: SERGIO | D29: CE-1416 | G29: =IFERROR(VLOOKUP(Tabla3[[#This Row],[NUM ECONOMICO]],MAQUINARIA!B:H,7,0), " MAQ") -> INACTIVA | H29: ME-16 | I29: 1015459 | K29: 1 | M29: =+L29*K29 -> 0 | P29: =Tabla3[[#This Row],[COSTO UNITARIO DOLARES EN HAWTHORNE]]*Tabla3[[#This Row],[CANTIDAD SOLICTADA]] -> 0 | S29: =+Tabla3[[#This Row],[COSTO UNITARIO DOLARES CTP]]*Tabla3[[#This Row],[CANTIDAD SOLICTADA]] -> 0 | U29: ENTREGADO | W29: 46174 | X29: NO | Y29: SIN EXISTENCIA | Z29: MATCO | AA29: 46167 | AB29: 46170 | AC29: CHOFER EDUARDO | AE29: SE ENTREGA A JAVIER
A30: 12 | B30: 46167 | C30: SERGIO | E30: 20 | F30: 46178 | G30: =IFERROR(VLOOKUP(Tabla3[[#This Row],[NUM ECONOMICO]],MAQUINARIA!B:H,7,0), " MAQ") -> INACTIVA | H30: ME-28 | I30: 5L8854 | K30: 2 | M30: =+L30*K30 -> 0 | P30: =Tabla3[[#This Row],[COSTO UNITARIO DOLARES EN HAWTHORNE]]*Tabla3[[#This Row],[CANTIDAD SOLICTADA]] -> 0 | S30: =+Tabla3[[#This Row],[COSTO UNITARIO DOLARES CTP]]*Tabla3[[#This Row],[CANTIDAD SOLICTADA]] -> 0 | U30: ENTREGADO | W30: 46191 | X30: SI | Y30: 3 | AC30: SERGIO | AE30: SE ENTREGA A SERGIO | AG30: SILENCIADOR
A31: 12 | B31: 46167 | C31: SERGIO | E31: 20 | F31: 46178 | G31: =IFERROR(VLOOKUP(Tabla3[[#This Row],[NUM ECONOMICO]],MAQUINARIA!B:H,7,0), " MAQ") -> INACTIVA | H31: ME-28 | I31: 9N1941 | K31: 1 | M31: =+L31*K31 -> 0 | P31: =Tabla3[[#This Row],[COSTO UNITARIO DOLARES EN HAWTHORNE]]*Tabla3[[#This Row],[CANTIDAD SOLICTADA]] -> 0 | S31: =+Tabla3[[#This Row],[COSTO UNITARIO DOLARES CTP]]*Tabla3[[#This Row],[CANTIDAD SOLICTADA]] -> 0 | U31: ENTREGADO | W31: 46191 | X31: SI | Y31: 1 | AC31: SERGIO | AE31: SE ENTREGA A SERGIO | AG31: SILENCIADOR
A32: 12 | B32: 46167 | C32: SERGIO | E32: 20 | F32: 46178 | G32: =IFERROR(VLOOKUP(Tabla3[[#This Row],[NUM ECONOMICO]],MAQUINARIA!B:H,7,0), " MAQ") -> INACTIVA | H32: ME-28 | I32: 1752931 | K32: 1 | L32: 34307.69 | M32: =+L32*K32 -> 34307.69 | P32: =Tabla3[[#This Row],[COSTO UNITARIO DOLARES EN HAWTHORNE]]*Tabla3[[#This Row],[CANTIDAD SOLICTADA]] -> 0 | S32: =+Tabla3[[#This Row],[COSTO UNITARIO DOLARES CTP]]*Tabla3[[#This Row],[CANTIDAD SOLICTADA]] -> 0 | U32: ENTREGADO | V32: QT-08-427469 | W32: 46191 | X32: NO | Y32: SIN EXISTENCIA | AE32: BENJA | AG32: SILENCIADOR
A33: 13 | B33: 46167 | C33: SERGIO | G33: =IFERROR(VLOOKUP(Tabla3[[#This Row],[NUM ECONOMICO]],MAQUINARIA!B:H,7,0), " MAQ") -> ACTIVA | H33: ME-14 | I33: 2N2765 | K33: 4 | M33: =+L33*K33 -> 0 | P33: =Tabla3[[#This Row],[COSTO UNITARIO DOLARES EN HAWTHORNE]]*Tabla3[[#This Row],[CANTIDAD SOLICTADA]] -> 0 | S33: =+Tabla3[[#This Row],[COSTO UNITARIO DOLARES CTP]]*Tabla3[[#This Row],[CANTIDAD SOLICTADA]] -> 0 | U33: ENTREGADO | W33: 46167 | X33: SI | Y33: 32 | AC33: SERGIO | AD33: R-1673
A34: 14 | B34: 46167 | C34: SERGIO | G34: =IFERROR(VLOOKUP(Tabla3[[#This Row],[NUM ECONOMICO]],MAQUINARIA!B:H,7,0), " MAQ") -> ACTIVA | H34: ME-14 | I34: 2N2766 | J34: TUBERÍA A | K34: 4 | M34: =+L34*K34 -> 0 | P34: =Tabla3[[#This Row],[COSTO UNITARIO DOLARES EN HAWTHORNE]]*Tabla3[[#This Row],[CANTIDAD SOLICTADA]] -> 0 | R34: 0.82 | S34: =+Tabla3[[#This Row],[COSTO UNITARIO DOLARES CTP]]*Tabla3[[#This Row],[CANTIDAD SOLICTADA]] -> 3.28 | U34: ENTREGADO | W34: 46167 | X34: SI | Y34: 6 | AC34: SERGIO | AD34: R-1673
A35: 15 | B35: 46167 | C35: SERGIO | G35: =IFERROR(VLOOKUP(Tabla3[[#This Row],[NUM ECONOMICO]],MAQUINARIA!B:H,7,0), " MAQ") -> ACTIVA | H35: ME-14 | I35: 1S4295 | J35: PUMP GR - GEAR FU | K35: 1 | M35: =+L35*K35 -> 0 | P35: =Tabla3[[#This Row],[COSTO UNITARIO DOLARES EN HAWTHORNE]]*Tabla3[[#This Row],[CANTIDAD SOLICTADA]] -> 0 | R35: 3.98 | S35: =+Tabla3[[#This Row],[COSTO UNITARIO DOLARES CTP]]*Tabla3[[#This Row],[CANTIDAD SOLICTADA]] -> 3.98 | U35: ENTREGADO | W35: 46167 | X35: SI | Y35: 22 | AC35: SERGIO | AD35: R-1673
A36: 16 | B36: 46167 | C36: SERGIO | D36: CE-1417 | G36: =IFERROR(VLOOKUP(Tabla3[[#This Row],[NUM ECONOMICO]],MAQUINARIA!B:H,7,0), " MAQ") -> ACTIVA | H36: ME-14 | I36: 9N2038 | K36: 1 | M36: =+L36*K36 -> 0 | P36: =Tabla3[[#This Row],[COSTO UNITARIO DOLARES EN HAWTHORNE]]*Tabla3[[#This Row],[CANTIDAD SOLICTADA]] -> 0 | S36: =+Tabla3[[#This Row],[COSTO UNITARIO DOLARES CTP]]*Tabla3[[#This Row],[CANTIDAD SOLICTADA]] -> 0 | U36: ENTREGADO | W36: 46167 | X36: NO | Y36: 0 | Z36: TDR | AA36: 46167 | AB36: 46167 | AC36: SERGIO
A37: 17 | B37: 46167 | C37: SERGIO | G37: =IFERROR(VLOOKUP(Tabla3[[#This Row],[NUM ECONOMICO]],MAQUINARIA!B:H,7,0), " MAQ") -> ACTIVA | H37: MT-08 | I37: 8T8927 | K37: 16 | M37: =+L37*K37 -> 0 | P37: =Tabla3[[#This Row],[COSTO UNITARIO DOLARES EN HAWTHORNE]]*Tabla3[[#This Row],[CANTIDAD SOLICTADA]] -> 0 | S37: =+Tabla3[[#This Row],[COSTO UNITARIO DOLARES CTP]]*Tabla3[[#This Row],[CANTIDAD SOLICTADA]] -> 0 | U37: ENTREGADO | V37: QT-08-427546 | X37: NO | Y37: SIN EXISTENCIA
A38: 17 | B38: 46167 | C38: SERGIO | G38: =IFERROR(VLOOKUP(Tabla3[[#This Row],[NUM ECONOMICO]],MAQUINARIA!B:H,7,0), " MAQ") -> ACTIVA | H38: MT-08 | I38: 8T5361 | K38: 16 | M38: =+L38*K38 -> 0 | P38: =Tabla3[[#This Row],[COSTO UNITARIO DOLARES EN HAWTHORNE]]*Tabla3[[#This Row],[CANTIDAD SOLICTADA]] -> 0 | S38: =+Tabla3[[#This Row],[COSTO UNITARIO DOLARES CTP]]*Tabla3[[#This Row],[CANTIDAD SOLICTADA]] -> 0 | U38: EN ALMACEN | X38: SI | Y38: 32 | XFD38: =+Tabla3[[#This Row],[ESTATUS DE NUM ECONOMICO]] -> ACTIVA
A39: 17 | B39: 46167 | C39: SERGIO | G39: =IFERROR(VLOOKUP(Tabla3[[#This Row],[NUM ECONOMICO]],MAQUINARIA!B:H,7,0), " MAQ") -> ACTIVA | H39: MT-08 | I39: 7M0475 | K39: 1 | M39: =+L39*K39 -> 0 | P39: =Tabla3[[#This Row],[COSTO UNITARIO DOLARES EN HAWTHORNE]]*Tabla3[[#This Row],[CANTIDAD SOLICTADA]] -> 0 | S39: =+Tabla3[[#This Row],[COSTO UNITARIO DOLARES CTP]]*Tabla3[[#This Row],[CANTIDAD SOLICTADA]] -> 0 | U39: ENTREGADO | V39: QT-08-427546 | X39: NO | Y39: 1 | XFD39: =+Tabla3[[#This Row],[ESTATUS DE NUM ECONOMICO]] -> ACTIVA
A40: 17 | B40: 46167 | C40: SERGIO | G40: =IFERROR(VLOOKUP(Tabla3[[#This Row],[NUM ECONOMICO]],MAQUINARIA!B:H,7,0), " MAQ") -> ACTIVA | H40: MT-08 | I40: 2160273 | K40: 1 | M40: =+L40*K40 -> 0 | P40: =Tabla3[[#This Row],[COSTO UNITARIO DOLARES EN HAWTHORNE]]*Tabla3[[#This Row],[CANTIDAD SOLICTADA]] -> 0 | S40: =+Tabla3[[#This Row],[COSTO UNITARIO DOLARES CTP]]*Tabla3[[#This Row],[CANTIDAD SOLICTADA]] -> 0 | U40: ENTREGADO | V40: QT-08-427546 | X40: NO | Y40: 1 | XFD40: =+Tabla3[[#This Row],[ESTATUS DE NUM ECONOMICO]] -> ACTIVA
A41: 18 | B41: 46167 | C41: SERGIO | D41: CE-1418 | F41: 46167 | G41: =IFERROR(VLOOKUP(Tabla3[[#This Row],[NUM ECONOMICO]],MAQUINARIA!B:H,7,0), " MAQ") -> INACTIVA | H41: ME-34 | I41: 2435803 | K41: 1 | M41: =+L41*K41 -> 0 | P41: =Tabla3[[#This Row],[COSTO UNITARIO DOLARES EN HAWTHORNE]]*Tabla3[[#This Row],[CANTIDAD SOLICTADA]] -> 0 | S41: =+Tabla3[[#This Row],[COSTO UNITARIO DOLARES CTP]]*Tabla3[[#This Row],[CANTIDAD SOLICTADA]] -> 0 | U41: ENTREGADO | V41: QT-08-427503 | W41: 46167 | X41: NO | Y41: 0 | Z41: MATCO | AA41: 46167 | AB41: 46167 | AC41: SERGIO | AE41: SOLICITAN QUE SE ENTREGE DIRECTO EN PUERTA | XFD41: =+Tabla3[[#This Row],[ESTATUS DE NUM ECONOMICO]] -> INACTIVA
A42: 19 | B42: 46167 | C42: SERGIO | G42: =IFERROR(VLOOKUP(Tabla3[[#This Row],[NUM ECONOMICO]],MAQUINARIA!B:H,7,0), " MAQ") -> INACTIVA | H42: ME-02 | I42: 9J0948 | K42: 4 | M42: =+L42*K42 -> 0 | P42: =Tabla3[[#This Row],[COSTO UNITARIO DOLARES EN HAWTHORNE]]*Tabla3[[#This Row],[CANTIDAD SOLICTADA]] -> 0 | S42: =+Tabla3[[#This Row],[COSTO UNITARIO DOLARES CTP]]*Tabla3[[#This Row],[CANTIDAD SOLICTADA]] -> 0 | U42: CANCELADO | V42: QT-08-427650 | X42: NO | Y42: SIN EXISTENCIA | AE42: BENJA | AG42: BUJES DE BRONCE | XFD42: =+Tabla3[[#This Row],[ESTATUS DE NUM ECONOMICO]] -> INACTIVA
A43: 19 | B43: 46167 | C43: SERGIO | G43: =IFERROR(VLOOKUP(Tabla3[[#This Row],[NUM ECONOMICO]],MAQUINARIA!B:H,7,0), " MAQ") -> INACTIVA | H43: ME-02 | I43: 5P8245 | K43: 10 | M43: =+L43*K43 -> 0 | P43: =Tabla3[[#This Row],[COSTO UNITARIO DOLARES EN HAWTHORNE]]*Tabla3[[#This Row],[CANTIDAD SOLICTADA]] -> 0 | S43: =+Tabla3[[#This Row],[COSTO UNITARIO DOLARES CTP]]*Tabla3[[#This Row],[CANTIDAD SOLICTADA]] -> 0 | U43: CANCELADO | V43: QT-08-427650 | X43: NO | Y43: SIN EXISTENCIA | XFD43: =+Tabla3[[#This Row],[ESTATUS DE NUM ECONOMICO]] -> INACTIVA
A44: 20 | B44: 46167 | C44: SERGIO | G44: =IFERROR(VLOOKUP(Tabla3[[#This Row],[NUM ECONOMICO]],MAQUINARIA!B:H,7,0), " MAQ") -> ACTIVA | H44: ME-24 | I44: 8T4896 | K44: 4 | M44: =+L44*K44 -> 0 | P44: =Tabla3[[#This Row],[COSTO UNITARIO DOLARES EN HAWTHORNE]]*Tabla3[[#This Row],[CANTIDAD SOLICTADA]] -> 0 | S44: =+Tabla3[[#This Row],[COSTO UNITARIO DOLARES CTP]]*Tabla3[[#This Row],[CANTIDAD SOLICTADA]] -> 0 | U44: EN ALMACEN | X44: SI | Y44: 1 | XFD44: =+Tabla3[[#This Row],[ESTATUS DE NUM ECONOMICO]] -> ACTIVA
A45: 20 | B45: 46167 | C45: SERGIO | G45: =IFERROR(VLOOKUP(Tabla3[[#This Row],[NUM ECONOMICO]],MAQUINARIA!B:H,7,0), " MAQ") -> ACTIVA | H45: ME-24 | I45: 5P5588 | K45: 2 | M45: =+L45*K45 -> 0 | P45: =Tabla3[[#This Row],[COSTO UNITARIO DOLARES EN HAWTHORNE]]*Tabla3[[#This Row],[CANTIDAD SOLICTADA]] -> 0 | S45: =+Tabla3[[#This Row],[COSTO UNITARIO DOLARES CTP]]*Tabla3[[#This Row],[CANTIDAD SOLICTADA]] -> 0 | U45: EN ALMACEN | X45: SI | Y45: 2 | XFD45: =+Tabla3[[#This Row],[ESTATUS DE NUM ECONOMICO]] -> ACTIVA
A46: 20 | B46: 46167 | C46: SERGIO | G46: =IFERROR(VLOOKUP(Tabla3[[#This Row],[NUM ECONOMICO]],MAQUINARIA!B:H,7,0), " MAQ") -> ACTIVA | H46: ME-24 | I46: 1B3980 | J46: CONO RODAMIENTO | K46: 4 | L46: 1294.62 | M46: =+L46*K46 -> 5178.48 | O46: 63.03 | P46: =Tabla3[[#This Row],[COSTO UNITARIO DOLARES EN HAWTHORNE]]*Tabla3[[#This Row],[CANTIDAD SOLICTADA]] -> 252.12 | Q46: 3-4 | R46: 12.08 | S46: =+Tabla3[[#This Row],[COSTO UNITARIO DOLARES CTP]]*Tabla3[[#This Row],[CANTIDAD SOLICTADA]] -> 48.32 | U46: ENTREGADO | V46: QT-08-427548 | X46: SI | Y46: 1 | AC46: SERGIO | AE46: BENJA | XFD46: =+Tabla3[[#This Row],[ESTATUS DE NUM ECONOMICO]] -> ACTIVA
A47: 20 | B47: 46167 | C47: SERGIO | G47: =IFERROR(VLOOKUP(Tabla3[[#This Row],[NUM ECONOMICO]],MAQUINARIA!B:H,7,0), " MAQ") -> ACTIVA | H47: ME-24 | I47: 1B3978 | J47: COPA DE COJINETE | K47: 4 | L47: 938.27 | M47: =+L47*K47 -> 3753.08 | O47: 47.66 | P47: =Tabla3[[#This Row],[COSTO UNITARIO DOLARES EN HAWTHORNE]]*Tabla3[[#This Row],[CANTIDAD SOLICTADA]] -> 190.64 | Q47: 3-4 | R47: 6.2 | S47: =+Tabla3[[#This Row],[COSTO UNITARIO DOLARES CTP]]*Tabla3[[#This Row],[CANTIDAD SOLICTADA]] -> 24.8 | U47: ENTREGADO | V47: QT-08-427548 | X47: NO | Y47: SIN EXISTENCIA | AC47: SERGIO | AE47: BENJA | XFD47: =+Tabla3[[#This Row],[ESTATUS DE NUM ECONOMICO]] -> ACTIVA
A48: 20 | B48: 46167 | C48: SERGIO | G48: =IFERROR(VLOOKUP(Tabla3[[#This Row],[NUM ECONOMICO]],MAQUINARIA!B:H,7,0), " MAQ") -> ACTIVA | H48: ME-24 | I48: 1447320 | J48: CUBIERTA | K48: 1 | L48: 2465.56 | M48: =+L48*K48 -> 2465.56 | O48: 111.07 | P48: =Tabla3[[#This Row],[COSTO UNITARIO DOLARES EN HAWTHORNE]]*Tabla3[[#This Row],[CANTIDAD SOLICTADA]] -> 111.07 | Q48: 3-4 | R48: 0 | S48: =+Tabla3[[#This Row],[COSTO UNITARIO DOLARES CTP]]*Tabla3[[#This Row],[CANTIDAD SOLICTADA]] -> 0 | U48: ENTREGADO | V48: QT-08-427548 | X48: NO | Y48: SIN EXISTENCIA | AC48: SERGIO | AE48: BENJA | XFD48: =+Tabla3[[#This Row],[ESTATUS DE NUM ECONOMICO]] -> ACTIVA
A49: 20 | B49: 46167 | C49: SERGIO | G49: =IFERROR(VLOOKUP(Tabla3[[#This Row],[NUM ECONOMICO]],MAQUINARIA!B:H,7,0), " MAQ") -> ACTIVA | H49: ME-24 | I49: 312523 | J49: Sello O ring | K49: 6 | L49: 24.99 | M49: =+L49*K49 -> 149.94 | O49: 1.38 | P49: =Tabla3[[#This Row],[COSTO UNITARIO DOLARES EN HAWTHORNE]]*Tabla3[[#This Row],[CANTIDAD SOLICTADA]] -> 8.28 | Q49: 3-4 | R49: 0 | S49: =+Tabla3[[#This Row],[COSTO UNITARIO DOLARES CTP]]*Tabla3[[#This Row],[CANTIDAD SOLICTADA]] -> 0 | U49: ENTREGADO | V49: QT-08-427548 | X49: NO | Y49: SIN EXISTENCIA | AC49: SERGIO | AE49: BENJA | XFD49: =+Tabla3[[#This Row],[ESTATUS DE NUM ECONOMICO]] -> ACTIVA
A50: 20 | B50: 46167 | C50: SERGIO | G50: =IFERROR(VLOOKUP(Tabla3[[#This Row],[NUM ECONOMICO]],MAQUINARIA!B:H,7,0), " MAQ") -> ACTIVA | H50: ME-24 | I50: 1U4242 | J50: TORNILLO AUTOMÁTICO DE CERROJO | K50: 1 | L50: 2369.7 | M50: =+L50*K50 -> 2369.7 | O50: 106.75 | P50: =Tabla3[[#This Row],[COSTO UNITARIO DOLARES EN HAWTHORNE]]*Tabla3[[#This Row],[CANTIDAD SOLICTADA]] -> 106.75 | Q50: 3-4 | R50: 0 | S50: =+Tabla3[[#This Row],[COSTO UNITARIO DOLARES CTP]]*Tabla3[[#This Row],[CANTIDAD SOLICTADA]] -> 0 | U50: ENTREGADO | V50: QT-08-427548 | X50: NO | Y50: SIN EXISTENCIA | AC50: SERGIO | AE50: BENJA | XFD50: =+Tabla3[[#This Row],[ESTATUS DE NUM ECONOMICO]] -> ACTIVA
A51: 20 | B51: 46167 | C51: SERGIO | G51: =IFERROR(VLOOKUP(Tabla3[[#This Row],[NUM ECONOMICO]],MAQUINARIA!B:H,7,0), " MAQ") -> ACTIVA | H51: ME-24 | I51: 1447295 | J51: TORNILLO AUTOMÁTICO DE CERROJO | K51: 2 | L51: 93.56 | M51: =+L51*K51 -> 187.12 | O51: 5.2 | P51: =Tabla3[[#This Row],[COSTO UNITARIO DOLARES EN HAWTHORNE]]*Tabla3[[#This Row],[CANTIDAD SOLICTADA]] -> 10.4 | Q51: 3-4 | R51: 0 | S51: =+Tabla3[[#This Row],[COSTO UNITARIO DOLARES CTP]]*Tabla3[[#This Row],[CANTIDAD SOLICTADA]] -> 0 | U51: ENTREGADO | V51: QT-08-427548 | X51: NO | Y51: SIN EXISTENCIA | AC51: SERGIO | AE51: BENJA | XFD51: =+Tabla3[[#This Row],[ESTATUS DE NUM ECONOMICO]] -> ACTIVA
A52: 21 | B52: 46167 | C52: BENJAMIN | D52: CE-1420 | E52: 32 | F52: 46156 | G52: =IFERROR(VLOOKUP(Tabla3[[#This Row],[NUM ECONOMICO]],MAQUINARIA!B:H,7,0), " MAQ") -> ACTIVA | H52: MX-06 | I52: 5054113 | K52: 5 | M52: =+L52*K52 -> 0 | P52: =Tabla3[[#This Row],[COSTO UNITARIO DOLARES EN HAWTHORNE]]*Tabla3[[#This Row],[CANTIDAD SOLICTADA]] -> 0 | S52: =+Tabla3[[#This Row],[COSTO UNITARIO DOLARES CTP]]*Tabla3[[#This Row],[CANTIDAD SOLICTADA]] -> 0 | U52: ENTREGADO | V52: QT-08-427531 | W52: 46167 | X52: NO | Y52: SIN EXISTENCIA | Z52: MATCO | AA52: 46167 | AB52: 46168 | AC52: EDUARDO CHOFER | AE52: PEDIDO FINCADO. EN ESPERA DE PASAR X EL A SUCURSAL | XFD52: =+Tabla3[[#This Row],[ESTATUS DE NUM ECONOMICO]] -> ACTIVA
A53: 22 | B53: 46168 | C53: SERGIO | G53: =IFERROR(VLOOKUP(Tabla3[[#This Row],[NUM ECONOMICO]],MAQUINARIA!B:H,7,0), " MAQ") -> INACTIVA | H53: ME-02 | I53: 9J0950 | K53: 4 | L53: 11263.54 | M53: =+L53*K53 -> 45054.16 | P53: =Tabla3[[#This Row],[COSTO UNITARIO DOLARES EN HAWTHORNE]]*Tabla3[[#This Row],[CANTIDAD SOLICTADA]] -> 0 | S53: =+Tabla3[[#This Row],[COSTO UNITARIO DOLARES CTP]]*Tabla3[[#This Row],[CANTIDAD SOLICTADA]] -> 0 | U53: EN ALMACEN | V53: QT-08-427586 | X53: NO | Y53: SIN EXISTENCIA | AE53: PASADO A BENJA | XFD53: =+Tabla3[[#This Row],[ESTATUS DE NUM ECONOMICO]] -> INACTIVA
A54: 22 | B54: 46168 | C54: SERGIO | G54: =IFERROR(VLOOKUP(Tabla3[[#This Row],[NUM ECONOMICO]],MAQUINARIA!B:H,7,0), " MAQ") -> INACTIVA | H54: ME-02 | I54: 9J0931 | K54: 8 | L54: 4618.9 | M54: =+L54*K54 -> 36951.2 | P54: =Tabla3[[#This Row],[COSTO UNITARIO DOLARES EN HAWTHORNE]]*Tabla3[[#This Row],[CANTIDAD SOLICTADA]] -> 0 | S54: =+Tabla3[[#This Row],[COSTO UNITARIO DOLARES CTP]]*Tabla3[[#This Row],[CANTIDAD SOLICTADA]] -> 0 | U54: CANCELADO | V54: QT-08-427586 | X54: NO | Y54: SIN EXISTENCIA | AE54: PASADO A BENJA | XFD54: =+Tabla3[[#This Row],[ESTATUS DE NUM ECONOMICO]] -> INACTIVA
A55: 23 | B55: 46168 | C55: EDUARDO | G55: =IFERROR(VLOOKUP(Tabla3[[#This Row],[NUM ECONOMICO]],MAQUINARIA!B:H,7,0), " MAQ") -> ACTIVA | H55: MT-09 | I55: 9W8874 | K55: 1 | M55: =+L55*K55 -> 0 | P55: =Tabla3[[#This Row],[COSTO UNITARIO DOLARES EN HAWTHORNE]]*Tabla3[[#This Row],[CANTIDAD SOLICTADA]] -> 0 | S55: =+Tabla3[[#This Row],[COSTO UNITARIO DOLARES CTP]]*Tabla3[[#This Row],[CANTIDAD SOLICTADA]] -> 0 | U55: CANCELADO | V55: QT-08-427569 | X55: NO | Y55: SIN EXISTENCIA | AE55: REPETIDO DE 53 | AG55: REPETIDO DE 53 | XFD55: =+Tabla3[[#This Row],[ESTATUS DE NUM ECONOMICO]] -> ACTIVA
A56: 23 | B56: 46168 | C56: EDUARDO | G56: =IFERROR(VLOOKUP(Tabla3[[#This Row],[NUM ECONOMICO]],MAQUINARIA!B:H,7,0), " MAQ") -> ACTIVA | H56: MT-09 | I56: 9W8875 | K56: 1 | M56: =+L56*K56 -> 0 | P56: =Tabla3[[#This Row],[COSTO UNITARIO DOLARES EN HAWTHORNE]]*Tabla3[[#This Row],[CANTIDAD SOLICTADA]] -> 0 | S56: =+Tabla3[[#This Row],[COSTO UNITARIO DOLARES CTP]]*Tabla3[[#This Row],[CANTIDAD SOLICTADA]] -> 0 | U56: CANCELADO | V56: QT-08-427569 | X56: NO | Y56: SIN EXISTENCIA | AE56: REPETIDO DE 53 | AG56: REPETIDO DE 53 | XFD56: =+Tabla3[[#This Row],[ESTATUS DE NUM ECONOMICO]] -> ACTIVA
A57: 23 | B57: 46168 | C57: EDUARDO | G57: =IFERROR(VLOOKUP(Tabla3[[#This Row],[NUM ECONOMICO]],MAQUINARIA!B:H,7,0), " MAQ") -> ACTIVA | H57: MT-09 | I57: 5J4773 | K57: 28 | M57: =+L57*K57 -> 0 | P57: =Tabla3[[#This Row],[COSTO UNITARIO DOLARES EN HAWTHORNE]]*Tabla3[[#This Row],[CANTIDAD SOLICTADA]] -> 0 | S57: =+Tabla3[[#This Row],[COSTO UNITARIO DOLARES CTP]]*Tabla3[[#This Row],[CANTIDAD SOLICTADA]] -> 0 | U57: CANCELADO | V57: QT-08-427569 | X57: NO | Y57: 0 | AE57: REPETIDO DE 53 | AG57: REPETIDO DE 53 | XFD57: =+Tabla3[[#This Row],[ESTATUS DE NUM ECONOMICO]] -> ACTIVA
A58: 23 | B58: 46168 | C58: EDUARDO | G58: =IFERROR(VLOOKUP(Tabla3[[#This Row],[NUM ECONOMICO]],MAQUINARIA!B:H,7,0), " MAQ") -> ACTIVA | H58: MT-09 | I58: 5P8248 | K58: 28 | M58: =+L58*K58 -> 0 | P58: =Tabla3[[#This Row],[COSTO UNITARIO DOLARES EN HAWTHORNE]]*Tabla3[[#This Row],[CANTIDAD SOLICTADA]] -> 0 | S58: =+Tabla3[[#This Row],[COSTO UNITARIO DOLARES CTP]]*Tabla3[[#This Row],[CANTIDAD SOLICTADA]] -> 0 | U58: CANCELADO | V58: QT-08-427569 | X58: NO | Y58: 2 | AE58: REPETIDO DE 53 | AG58: REPETIDO DE 53 | XFD58: =+Tabla3[[#This Row],[ESTATUS DE NUM ECONOMICO]] -> ACTIVA
A59: 23 | B59: 46168 | C59: EDUARDO | G59: =IFERROR(VLOOKUP(Tabla3[[#This Row],[NUM ECONOMICO]],MAQUINARIA!B:H,7,0), " MAQ") -> ACTIVA | H59: MT-09 | I59: 2J3506 | K59: 28 | M59: =+L59*K59 -> 0 | P59: =Tabla3[[#This Row],[COSTO UNITARIO DOLARES EN HAWTHORNE]]*Tabla3[[#This Row],[CANTIDAD SOLICTADA]] -> 0 | S59: =+Tabla3[[#This Row],[COSTO UNITARIO DOLARES CTP]]*Tabla3[[#This Row],[CANTIDAD SOLICTADA]] -> 0 | U59: CANCELADO | V59: QT-08-427569 | X59: NO | Y59: 0 | AE59: REPETIDO DE 53 | AG59: REPETIDO DE 53 | XFD59: =+Tabla3[[#This Row],[ESTATUS DE NUM ECONOMICO]] -> ACTIVA
A60: 24 | B60: 46168 | C60: SERGIO | G60: =IFERROR(VLOOKUP(Tabla3[[#This Row],[NUM ECONOMICO]],MAQUINARIA!B:H,7,0), " MAQ") -> INACTIVA | H60: ME-02 | I60: 9J0950 | K60: 4 | M60: =+L60*K60 -> 0 | P60: =Tabla3[[#This Row],[COSTO UNITARIO DOLARES EN HAWTHORNE]]*Tabla3[[#This Row],[CANTIDAD SOLICTADA]] -> 0 | S60: =+Tabla3[[#This Row],[COSTO UNITARIO DOLARES CTP]]*Tabla3[[#This Row],[CANTIDAD SOLICTADA]] -> 0 | U60: CANCELADO | V60: QT-08-427586 | X60: NO | Y60: SIN EXISTENCIA | AE60: SE REPITIO CONCEC | XFD60: =+Tabla3[[#This Row],[ESTATUS DE NUM ECONOMICO]] -> INACTIVA
A61: 25 | B61: 46168 | C61: SERGIO | E61: 12 | F61: 46178 | G61: =IFERROR(VLOOKUP(Tabla3[[#This Row],[NUM ECONOMICO]],MAQUINARIA!B:H,7,0), " MAQ") -> ACTIVA | H61: MT-11 | I61: 1544492 | J61: BRAZO | K61: 1 | M61: =+L61*K61 -> 0 | P61: =Tabla3[[#This Row],[COSTO UNITARIO DOLARES EN HAWTHORNE]]*Tabla3[[#This Row],[CANTIDAD SOLICTADA]] -> 0 | R61: 6.22 | S61: =+Tabla3[[#This Row],[COSTO UNITARIO DOLARES CTP]]*Tabla3[[#This Row],[CANTIDAD SOLICTADA]] -> 6.22 | U61: ENTREGADO | V61: QT-08-427598 | W61: 46168 | X61: SI | Y61: 1 | AE61: SE TOMARON REFACCIONES DEL PEDIDO ESTANCADO DEL MT-02 | XFD61: =+Tabla3[[#This Row],[ESTATUS DE NUM ECONOMICO]] -> ACTIVA
A62: 25 | B62: 46168 | C62: SERGIO | E62: 12 | F62: 46178 | G62: =IFERROR(VLOOKUP(Tabla3[[#This Row],[NUM ECONOMICO]],MAQUINARIA!B:H,7,0), " MAQ") -> ACTIVA | H62: MT-11 | I62: 3E6757 | K62: 4 | M62: =+L62*K62 -> 0 | P62: =Tabla3[[#This Row],[COSTO UNITARIO DOLARES EN HAWTHORNE]]*Tabla3[[#This Row],[CANTIDAD SOLICTADA]] -> 0 | S62: =+Tabla3[[#This Row],[COSTO UNITARIO DOLARES CTP]]*Tabla3[[#This Row],[CANTIDAD SOLICTADA]] -> 0 | U62: ENTREGADO | V62: QT-08-427598 | W62: 46168 | X62: SI | Y62: SIN EXISTENCIA | AE62: SE TOMARON REFACCIONES DEL PEDIDO ESTANCADO DEL MT-02 | XFD62: =+Tabla3[[#This Row],[ESTATUS DE NUM ECONOMICO]] -> ACTIVA
A63: 25 | B63: 46168 | C63: SERGIO | E63: 12 | F63: 46178 | G63: =IFERROR(VLOOKUP(Tabla3[[#This Row],[NUM ECONOMICO]],MAQUINARIA!B:H,7,0), " MAQ") -> ACTIVA | H63: MT-11 | I63: 1112104 | K63: 1 | M63: =+L63*K63 -> 0 | P63: =Tabla3[[#This Row],[COSTO UNITARIO DOLARES EN HAWTHORNE]]*Tabla3[[#This Row],[CANTIDAD SOLICTADA]] -> 0 | S63: =+Tabla3[[#This Row],[COSTO UNITARIO DOLARES CTP]]*Tabla3[[#This Row],[CANTIDAD SOLICTADA]] -> 0 | U63: ENTREGADO | V63: QT-08-427598 | W63: 46168 | X63: SI | Y63: SIN EXISTENCIA | AE63: SE TOMARON REFACCIONES DEL PEDIDO ESTANCADO DEL MT-02 | XFD63: =+Tabla3[[#This Row],[ESTATUS DE NUM ECONOMICO]] -> ACTIVA
A64: 25 | B64: 46168 | C64: SERGIO | E64: 12 | F64: 46178 | G64: =IFERROR(VLOOKUP(Tabla3[[#This Row],[NUM ECONOMICO]],MAQUINARIA!B:H,7,0), " MAQ") -> ACTIVA | H64: MT-11 | I64: 6V8628 | K64: 1 | M64: =+L64*K64 -> 0 | P64: =Tabla3[[#This Row],[COSTO UNITARIO DOLARES EN HAWTHORNE]]*Tabla3[[#This Row],[CANTIDAD SOLICTADA]] -> 0 | S64: =+Tabla3[[#This Row],[COSTO UNITARIO DOLARES CTP]]*Tabla3[[#This Row],[CANTIDAD SOLICTADA]] -> 0 | U64: ENTREGADO | V64: QT-08-427598 | W64: 46168 | X64: SI | Y64: 8 | AE64: SE TOMARON REFACCIONES DEL PEDIDO ESTANCADO DEL MT-02 | XFD64: =+Tabla3[[#This Row],[ESTATUS DE NUM ECONOMICO]] -> ACTIVA
A65: 26 | B65: 46168 | C65: SERGIO | G65: =IFERROR(VLOOKUP(Tabla3[[#This Row],[NUM ECONOMICO]],MAQUINARIA!B:H,7,0), " MAQ") -> INACTIVA | H65: MT-07 | I65: 1298171 | K65: 1 | M65: =+L65*K65 -> 0 | P65: =Tabla3[[#This Row],[COSTO UNITARIO DOLARES EN HAWTHORNE]]*Tabla3[[#This Row],[CANTIDAD SOLICTADA]] -> 0 | S65: =+Tabla3[[#This Row],[COSTO UNITARIO DOLARES CTP]]*Tabla3[[#This Row],[CANTIDAD SOLICTADA]] -> 0 | U65: ENTREGADO | V65: QT-08-427613 | X65: SI | Y65: 1 | AB65: 46168 | AE65: ENTREGADO | AG65: BUJE DE MAZA | XFD65: =+Tabla3[[#This Row],[ESTATUS DE NUM ECONOMICO]] -> INACTIVA
A66: 26 | B66: 46168 | C66: SERGIO | G66: =IFERROR(VLOOKUP(Tabla3[[#This Row],[NUM ECONOMICO]],MAQUINARIA!B:H,7,0), " MAQ") -> INACTIVA | H66: MT-07 | I66: 7X0343 | K66: 4 | M66: =+L66*K66 -> 0 | P66: =Tabla3[[#This Row],[COSTO UNITARIO DOLARES EN HAWTHORNE]]*Tabla3[[#This Row],[CANTIDAD SOLICTADA]] -> 0 | S66: =+Tabla3[[#This Row],[COSTO UNITARIO DOLARES CTP]]*Tabla3[[#This Row],[CANTIDAD SOLICTADA]] -> 0 | U66: ENTREGADO | V66: QT-08-427613 | X66: SI | Y66: 8 | AB66: 46168 | AE66: ENTREGADO | AG66: BUJE DE MAZA | XFD66: =+Tabla3[[#This Row],[ESTATUS DE NUM ECONOMICO]] -> INACTIVA
A67: 26 | B67: 46168 | C67: SERGIO | G67: =IFERROR(VLOOKUP(Tabla3[[#This Row],[NUM ECONOMICO]],MAQUINARIA!B:H,7,0), " MAQ") -> INACTIVA | H67: MT-07 | I67: 1298172 | K67: 1 | M67: =+L67*K67 -> 0 | P67: =Tabla3[[#This Row],[COSTO UNITARIO DOLARES EN HAWTHORNE]]*Tabla3[[#This Row],[CANTIDAD SOLICTADA]] -> 0 | S67: =+Tabla3[[#This Row],[COSTO UNITARIO DOLARES CTP]]*Tabla3[[#This Row],[CANTIDAD SOLICTADA]] -> 0 | U67: ENTREGADO | V67: QT-08-427613 | X67: SI | Y67: 1 | AB67: 46168 | AE67: ENTREGADO | AG67: BUJE DE MAZA | XFD67: =+Tabla3[[#This Row],[ESTATUS DE NUM ECONOMICO]] -> INACTIVA
A68: 27 | B68: 46168 | C68: SERGIO | E68: 13 | F68: 46178 | G68: =IFERROR(VLOOKUP(Tabla3[[#This Row],[NUM ECONOMICO]],MAQUINARIA!B:H,7,0), " MAQ") -> ACTIVA | H68: MP-03 | I68: 2S2923 | J68: RETENEDOR | K68: 1 | L68: 240.64 | M68: =+L68*K68 -> 240.64 | O68: 13.1 | P68: =Tabla3[[#This Row],[COSTO UNITARIO DOLARES EN HAWTHORNE]]*Tabla3[[#This Row],[CANTIDAD SOLICTADA]] -> 13.1 | Q68: 0 | R68: 4.99 | S68: =+Tabla3[[#This Row],[COSTO UNITARIO DOLARES CTP]]*Tabla3[[#This Row],[CANTIDAD SOLICTADA]] -> 4.99 | U68: EN ALMACEN | V68: QT-08-427611 | X68: NO | Y68: SIN EXISTENCIA | AE68: BENJA | AG68: COMPRESOR DE AIRE | XFD68: =+Tabla3[[#This Row],[ESTATUS DE NUM ECONOMICO]] -> ACTIVA
A69: 27 | B69: 46168 | C69: SERGIO | E69: 13 | F69: 46178 | G69: =IFERROR(VLOOKUP(Tabla3[[#This Row],[NUM ECONOMICO]],MAQUINARIA!B:H,7,0), " MAQ") -> ACTIVA | H69: MP-03 | I69: 0R2901 / 7E7739 | J69: COMPRESOR | K69: 1 | L69: 52280.56 | M69: =+L69*K69 -> 52280.56 | O69: 908.57 | P69: =Tabla3[[#This Row],[COSTO UNITARIO DOLARES EN HAWTHORNE]]*Tabla3[[#This Row],[CANTIDAD SOLICTADA]] -> 908.57 | Q69: 3-4 | R69: 0 | S69: =+Tabla3[[#This Row],[COSTO UNITARIO DOLARES CTP]]*Tabla3[[#This Row],[CANTIDAD SOLICTADA]] -> 0 | U69: ENTREGADO | V69: QT-08-427611 | W69: 46209 | X69: NO | Y69: SIN EXISTENCIA | AB69: 46209 | AC69: JAVIER G | AE69: ENTREGADO A JAVIER | AG69: COMPRESOR DE AIRE | XFD69: =+Tabla3[[#This Row],[ESTATUS DE NUM ECONOMICO]] -> ACTIVA
A70: 27 | B70: 46168 | C70: SERGIO | E70: 13 | F70: 46178 | G70: =IFERROR(VLOOKUP(Tabla3[[#This Row],[NUM ECONOMICO]],MAQUINARIA!B:H,7,0), " MAQ") -> ACTIVA | H70: MP-03 | I70: 106178 | K70: 1 | M70: =+L70*K70 -> 0 | P70: =Tabla3[[#This Row],[COSTO UNITARIO DOLARES EN HAWTHORNE]]*Tabla3[[#This Row],[CANTIDAD SOLICTADA]] -> 0 | S70: =+Tabla3[[#This Row],[COSTO UNITARIO DOLARES CTP]]*Tabla3[[#This Row],[CANTIDAD SOLICTADA]] -> 0 | U70: EN ALMACEN | X70: SI | Y70: SIN EXISTENCIA | AE70: BENJA | AG70: COMPRESOR DE AIRE | XFD70: =+Tabla3[[#This Row],[ESTATUS DE NUM ECONOMICO]] -> ACTIVA
A71: 27 | B71: 46168 | C71: SERGIO | E71: 13 | F71: 46178 | G71: =IFERROR(VLOOKUP(Tabla3[[#This Row],[NUM ECONOMICO]],MAQUINARIA!B:H,7,0), " MAQ") -> ACTIVA | H71: MP-03 | I71: 8F4994 | J71: Sello O ring | K71: 2 | L71: 60.6 | M71: =+L71*K71 -> 121.2 | O71: 3.35 | P71: =Tabla3[[#This Row],[COSTO UNITARIO DOLARES EN HAWTHORNE]]*Tabla3[[#This Row],[CANTIDAD SOLICTADA]] -> 6.7 | Q71: 3-4 | R71: 0.21 | S71: =+Tabla3[[#This Row],[COSTO UNITARIO DOLARES CTP]]*Tabla3[[#This Row],[CANTIDAD SOLICTADA]] -> 0.42 | U71: EN ALMACEN | V71: QT-08-427611 | X71: NO | Y71: 2 | AE71: BENJA | AG71: COMPRESOR DE AIRE | XFD71: =+Tabla3[[#This Row],[ESTATUS DE NUM ECONOMICO]] -> ACTIVA
A72: 27 | B72: 46168 | C72: SERGIO | E72: 13 | F72: 46178 | G72: =IFERROR(VLOOKUP(Tabla3[[#This Row],[NUM ECONOMICO]],MAQUINARIA!B:H,7,0), " MAQ") -> ACTIVA | H72: MP-03 | I72: 1293948 | J72: JUNTA DE MONTAJE | K72: 1 | L72: 387 | M72: =+L72*K72 -> 387 | O72: 21.41 | P72: =Tabla3[[#This Row],[COSTO UNITARIO DOLARES EN HAWTHORNE]]*Tabla3[[#This Row],[CANTIDAD SOLICTADA]] -> 21.41 | Q72: 3-4 | R72: 9.34 | S72: =+Tabla3[[#This Row],[COSTO UNITARIO DOLARES CTP]]*Tabla3[[#This Row],[CANTIDAD SOLICTADA]] -> 9.34 | U72: COTIZANDO | V72: QT-08-427611 | X72: NO | Y72: SIN EXISTENCIA | AE72: BENJA | AF72: REVISANDO CON BENJA SI LO PIDIO A PROVEEDOR | AG72: COMPRESOR DE AIRE | XFD72: =+Tabla3[[#This Row],[ESTATUS DE NUM ECONOMICO]] -> ACTIVA
A73: 28 | B73: 46168 | C73: BENJAMIN | D73: CE-1424 | G73: =IFERROR(VLOOKUP(Tabla3[[#This Row],[NUM ECONOMICO]],MAQUINARIA!B:H,7,0), " MAQ") -> ACTIVA | H73: MT-02 | I73: 2566453 | K73: 1 | M73: =+L73*K73 -> 0 | P73: =Tabla3[[#This Row],[COSTO UNITARIO DOLARES EN HAWTHORNE]]*Tabla3[[#This Row],[CANTIDAD SOLICTADA]] -> 0 | S73: =+Tabla3[[#This Row],[COSTO UNITARIO DOLARES CTP]]*Tabla3[[#This Row],[CANTIDAD SOLICTADA]] -> 0 | U73: ENTREGADO | V73: QT-08-427595 | W73: 46169 | X73: NO | Y73: SIN EXISTENCIA | Z73: MATCO | AA73: 46168 | AB73: 46169 | AC73: PABLO | AE73: PABLO PUBLICA | AG73: SENSOR DE TEMPERATURA | XFD73: =+Tabla3[[#This Row],[ESTATUS DE NUM ECONOMICO]] -> ACTIVA
A74: 28 | B74: 46168 | C74: BENJAMIN | D74: CE-1424 | G74: =IFERROR(VLOOKUP(Tabla3[[#This Row],[NUM ECONOMICO]],MAQUINARIA!B:H,7,0), " MAQ") -> ACTIVA | H74: MT-02 | I74: 2304011 | K74: 1 | M74: =+L74*K74 -> 0 | P74: =Tabla3[[#This Row],[COSTO UNITARIO DOLARES EN HAWTHORNE]]*Tabla3[[#This Row],[CANTIDAD SOLICTADA]] -> 0 | S74: =+Tabla3[[#This Row],[COSTO UNITARIO DOLARES CTP]]*Tabla3[[#This Row],[CANTIDAD SOLICTADA]] -> 0 | U74: ENTREGADO | V74: QT-08-427595 | W74: 46169 | X74: NO | Y74: SIN EXISTENCIA | Z74: MATCO | AA74: 46168 | AB74: 46169 | AC74: PABLO | AE74: PABLO PUBLICA | AG74: ENCHUFE DE CONECTOR | XFD74: =+Tabla3[[#This Row],[ESTATUS DE NUM ECONOMICO]] -> ACTIVA
A75: 28 | B75: 46168 | C75: BENJAMIN | D75: CE-1424 | G75: =IFERROR(VLOOKUP(Tabla3[[#This Row],[NUM ECONOMICO]],MAQUINARIA!B:H,7,0), " MAQ") -> ACTIVA | H75: MT-02 | I75: 9X3402 | K75: 2 | M75: =+L75*K75 -> 0 | P75: =Tabla3[[#This Row],[COSTO UNITARIO DOLARES EN HAWTHORNE]]*Tabla3[[#This Row],[CANTIDAD SOLICTADA]] -> 0 | S75: =+Tabla3[[#This Row],[COSTO UNITARIO DOLARES CTP]]*Tabla3[[#This Row],[CANTIDAD SOLICTADA]] -> 0 | U75: ENTREGADO | V75: QT-08-427595 | W75: 46169 | X75: NO | Y75: 0 | Z75: MATCO | AA75: 46168 | AB75: 46169 | AC75: PABLO | AE75: PABLO PUBLICA | AG75: ENCHUFE DE CONECTOR | XFD75: =+Tabla3[[#This Row],[ESTATUS DE NUM ECONOMICO]] -> ACTIVA
A76: 29 | B76: 46169 | C76: SERGIO | G76: =IFERROR(VLOOKUP(Tabla3[[#This Row],[NUM ECONOMICO]],MAQUINARIA!B:H,7,0), " MAQ") -> ACTIVA | H76: MC-04 | I76: 2350969 | K76: 1 | L76: 3917.34 | M76: =+L76*K76 -> 3917.34 | P76: =Tabla3[[#This Row],[COSTO UNITARIO DOLARES EN HAWTHORNE]]*Tabla3[[#This Row],[CANTIDAD SOLICTADA]] -> 0 | S76: =+Tabla3[[#This Row],[COSTO UNITARIO DOLARES CTP]]*Tabla3[[#This Row],[CANTIDAD SOLICTADA]] -> 0 | U76: ENTREGADO | V76: QT-08-430945 | W76: 46088 | X76: NO | Y76: SIN EXISTENCIA | Z76: LOCAL | AC76: JAVIER G | AE76: ENTREGADO | AG76: KIT DE SELLOS PARA PISTONES | XFD76: =+Tabla3[[#This Row],[ESTATUS DE NUM ECONOMICO]] -> ACTIVA
A77: 29 | B77: 46169 | C77: SERGIO | G77: =IFERROR(VLOOKUP(Tabla3[[#This Row],[NUM ECONOMICO]],MAQUINARIA!B:H,7,0), " MAQ") -> ACTIVA | H77: MC-04 | I77: 2310898 | K77: 1 | L77: 3549.06 | M77: =+L77*K77 -> 3549.06 | P77: =Tabla3[[#This Row],[COSTO UNITARIO DOLARES EN HAWTHORNE]]*Tabla3[[#This Row],[CANTIDAD SOLICTADA]] -> 0 | S77: =+Tabla3[[#This Row],[COSTO UNITARIO DOLARES CTP]]*Tabla3[[#This Row],[CANTIDAD SOLICTADA]] -> 0 | U77: ENTREGADO | V77: QT-08-430945 | W77: 46206 | X77: NO | Y77: 3 | Z77: LOCAL | AC77: JAVIER G | AE77: ENTREGADO | AG77: KIT DE SELLOS PARA PISTONES | XFD77: =+Tabla3[[#This Row],[ESTATUS DE NUM ECONOMICO]] -> ACTIVA
A78: 30 | B78: 46169 | C78: BENJAMIN | E78: 79 | F78: 46147 | G78: =IFERROR(VLOOKUP(Tabla3[[#This Row],[NUM ECONOMICO]],MAQUINARIA!B:H,7,0), " MAQ") -> ACTIVA | H78: MT-05 | I78: 10R1267 | K78: 3 | M78: =+L78*K78 -> 0 | P78: =Tabla3[[#This Row],[COSTO UNITARIO DOLARES EN HAWTHORNE]]*Tabla3[[#This Row],[CANTIDAD SOLICTADA]] -> 0 | S78: =+Tabla3[[#This Row],[COSTO UNITARIO DOLARES CTP]]*Tabla3[[#This Row],[CANTIDAD SOLICTADA]] -> 0 | U78: ENTREGADO | V78: QT-08-427753 | W78: 46170 | X78: NO | Y78: SIN EXISTENCIA | Z78: CATERPILLAR | AA78: 46170 | AB78: 46170 | AC78: EDUARDO TORRES | AD78: R-1685 | AE78: INYECTORES | XFD78: =+Tabla3[[#This Row],[ESTATUS DE NUM ECONOMICO]] -> ACTIVA
A79: 31 | B79: 46169 | C79: SERGIO | G79: =IFERROR(VLOOKUP(Tabla3[[#This Row],[NUM ECONOMICO]],MAQUINARIA!B:H,7,0), " MAQ") -> ACTIVA | H79: MT-13 | I79: 6H3957 | K79: 2 | M79: =+L79*K79 -> 0 | P79: =Tabla3[[#This Row],[COSTO UNITARIO DOLARES EN HAWTHORNE]]*Tabla3[[#This Row],[CANTIDAD SOLICTADA]] -> 0 | S79: =+Tabla3[[#This Row],[COSTO UNITARIO DOLARES CTP]]*Tabla3[[#This Row],[CANTIDAD SOLICTADA]] -> 0 | U79: CANCELADO | V79: QT-08-428290 | X79: NO | Y79: SIN EXISTENCIA | AE79: BENJA | AF79: SERGIO MENCIONA QUE SE CANCELA, ESTA FUNCIONANDO BIEN LA UNIDAD | AG79: DESGASTE EN PZAS DEL POSTENFRIADOR | XFD79: =+Tabla3[[#This Row],[ESTATUS DE NUM ECONOMICO]] -> ACTIVA
A80: 31 | B80: 46169 | C80: SERGIO | G80: =IFERROR(VLOOKUP(Tabla3[[#This Row],[NUM ECONOMICO]],MAQUINARIA!B:H,7,0), " MAQ") -> ACTIVA | H80: MT-13 | I80: 5P9597 | K80: 1 | M80: =+L80*K80 -> 0 | P80: =Tabla3[[#This Row],[COSTO UNITARIO DOLARES EN HAWTHORNE]]*Tabla3[[#This Row],[CANTIDAD SOLICTADA]] -> 0 | S80: =+Tabla3[[#This Row],[COSTO UNITARIO DOLARES CTP]]*Tabla3[[#This Row],[CANTIDAD SOLICTADA]] -> 0 | U80: CANCELADO | V80: QT-08-428290 | X80: NO | Y80: 2 | AE80: BENJA | AF80: SERGIO MENCIONA QUE SE CANCELA, ESTA FUNCIONANDO BIEN LA UNIDAD | AG80: DESGASTE EN PZAS DEL POSTENFRIADOR | XFD80: =+Tabla3[[#This Row],[ESTATUS DE NUM ECONOMICO]] -> ACTIVA
A81: 31 | B81: 46169 | C81: SERGIO | G81: =IFERROR(VLOOKUP(Tabla3[[#This Row],[NUM ECONOMICO]],MAQUINARIA!B:H,7,0), " MAQ") -> ACTIVA | H81: MT-13 | I81: 2142296 | K81: 1 | M81: =+L81*K81 -> 0 | P81: =Tabla3[[#This Row],[COSTO UNITARIO DOLARES EN HAWTHORNE]]*Tabla3[[#This Row],[CANTIDAD SOLICTADA]] -> 0 | S81: =+Tabla3[[#This Row],[COSTO UNITARIO DOLARES CTP]]*Tabla3[[#This Row],[CANTIDAD SOLICTADA]] -> 0 | U81: CANCELADO | V81: QT-08-428290 | X81: NO | Y81: SIN EXISTENCIA | AE81: BENJA | AF81: SERGIO MENCIONA QUE SE CANCELA, ESTA FUNCIONANDO BIEN LA UNIDAD | AG81: DESGASTE EN PZAS DEL POSTENFRIADOR | XFD81: =+Tabla3[[#This Row],[ESTATUS DE NUM ECONOMICO]] -> ACTIVA
A82: 32 | B82: 46169 | C82: SERGIO | E82: 81 | F82: 46178 | G82: =IFERROR(VLOOKUP(Tabla3[[#This Row],[NUM ECONOMICO]],MAQUINARIA!B:H,7,0), " MAQ") -> INACTIVA | H82: MT-01 | I82: 8P0058 | J82: EMPAQUE | K82: 1 | L82: 95.2 | M82: =+L82*K82 -> 95.2 | O82: 6.75 | P82: =Tabla3[[#This Row],[COSTO UNITARIO DOLARES EN HAWTHORNE]]*Tabla3[[#This Row],[CANTIDAD SOLICTADA]] -> 6.75 | Q82: 3-4 | R82: 0.79 | S82: =+Tabla3[[#This Row],[COSTO UNITARIO DOLARES CTP]]*Tabla3[[#This Row],[CANTIDAD SOLICTADA]] -> 0.79 | U82: COTIZANDO | V82: QT-08-427760 | X82: NO | Y82: SIN EXISTENCIA | Z82: ACTP | AA82: 46170 | AB82: 46118 | AE82: COTIZANDO BENJAMIN | AF82: COTIZANDO BENJAMIN | AG82: REPARACION DE TRANSMISION Y CONVERTIDOR | XFD82: =+Tabla3[[#This Row],[ESTATUS DE NUM ECONOMICO]] -> INACTIVA
A83: 32 | B83: 46169 | C83: SERGIO | E83: 81 | F83: 46178 | G83: =IFERROR(VLOOKUP(Tabla3[[#This Row],[NUM ECONOMICO]],MAQUINARIA!B:H,7,0), " MAQ") -> INACTIVA | H83: MT-01 | I83: 1863161 | J83: EMPAQUE | K83: 1 | L83: 357.18 | M83: =+L83*K83 -> 357.18 | O83: 25.31 | P83: =Tabla3[[#This Row],[COSTO UNITARIO DOLARES EN HAWTHORNE]]*Tabla3[[#This Row],[CANTIDAD SOLICTADA]] -> 25.31 | Q83: 3-4 | R83: 3.02 | S83: =+Tabla3[[#This Row],[COSTO UNITARIO DOLARES CTP]]*Tabla3[[#This Row],[CANTIDAD SOLICTADA]] -> 3.02 | U83: COTIZANDO | V83: QT-08-427760 | X83: NO | Y83: SIN EXISTENCIA | Z83: ACTP | AA83: 46170 | AB83: 46118 | AE83: COTIZANDO BENJAMIN | AF83: COTIZANDO BENJAMIN | AG83: REPARACION DE TRANSMISION Y CONVERTIDOR | XFD83: =+Tabla3[[#This Row],[ESTATUS DE NUM ECONOMICO]] -> INACTIVA
A84: 32 | B84: 46169 | C84: SERGIO | D84: CE-1442 | E84: 80 | F84: 46178 | G84: =IFERROR(VLOOKUP(Tabla3[[#This Row],[NUM ECONOMICO]],MAQUINARIA!B:H,7,0), " MAQ") -> INACTIVA | H84: MT-01 | I84: 9M9647 | K84: 3 | M84: =+L84*K84 -> 0 | P84: =Tabla3[[#This Row],[COSTO UNITARIO DOLARES EN HAWTHORNE]]*Tabla3[[#This Row],[CANTIDAD SOLICTADA]] -> 0 | S84: =+Tabla3[[#This Row],[COSTO UNITARIO DOLARES CTP]]*Tabla3[[#This Row],[CANTIDAD SOLICTADA]] -> 0 | U84: ENTREGADO | V84: QT-08-427760 | W84: 46174 | X84: NO | Y84: 1 | Z84: MATCO | AA84: 46171 | AB84: 46175 | AC84: JOSE EDUARDO | AE84: SE ENTREGA A JAVIER | AG84: REPARACION DE TRANSMISION Y CONVERTIDOR | XFD84: =+Tabla3[[#This Row],[ESTATUS DE NUM ECONOMICO]] -> INACTIVA
A85: 32 | B85: 46169 | C85: SERGIO | D85: CE-1442 | E85: 80 | F85: 46178 | G85: =IFERROR(VLOOKUP(Tabla3[[#This Row],[NUM ECONOMICO]],MAQUINARIA!B:H,7,0), " MAQ") -> INACTIVA | H85: MT-01 | I85: 5P9519 | K85: 1 | M85: =+L85*K85 -> 0 | P85: =Tabla3[[#This Row],[COSTO UNITARIO DOLARES EN HAWTHORNE]]*Tabla3[[#This Row],[CANTIDAD SOLICTADA]] -> 0 | S85: =+Tabla3[[#This Row],[COSTO UNITARIO DOLARES CTP]]*Tabla3[[#This Row],[CANTIDAD SOLICTADA]] -> 0 | U85: ENTREGADO | V85: QT-08-427760 | W85: 46174 | X85: NO | Y85: SIN EXISTENCIA | Z85: MATCO | AA85: 46171 | AB85: 46175 | AC85: JOSE EDUARDO | AE85: SE ENTREGA A JAVIER | AG85: REPARACION DE TRANSMISION Y CONVERTIDOR | XFD85: =+Tabla3[[#This Row],[ESTATUS DE NUM ECONOMICO]] -> INACTIVA
A86: 32 | B86: 46169 | C86: SERGIO | D86: CE-1442 | E86: 80 | F86: 46178 | G86: =IFERROR(VLOOKUP(Tabla3[[#This Row],[NUM ECONOMICO]],MAQUINARIA!B:H,7,0), " MAQ") -> INACTIVA | H86: MT-01 | I86: 6L9284 | K86: 1 | M86: =+L86*K86 -> 0 | P86: =Tabla3[[#This Row],[COSTO UNITARIO DOLARES EN HAWTHORNE]]*Tabla3[[#This Row],[CANTIDAD SOLICTADA]] -> 0 | S86: =+Tabla3[[#This Row],[COSTO UNITARIO DOLARES CTP]]*Tabla3[[#This Row],[CANTIDAD SOLICTADA]] -> 0 | U86: ENTREGADO | V86: QT-08-427760 | W86: 46174 | X86: NO | Y86: SIN EXISTENCIA | Z86: MATCO | AA86: 46171 | AB86: 46175 | AC86: JOSE EDUARDO | AE86: SE ENTREGA A JAVIER | AG86: REPARACION DE TRANSMISION Y CONVERTIDOR | XFD86: =+Tabla3[[#This Row],[ESTATUS DE NUM ECONOMICO]] -> INACTIVA
A87: 32 | B87: 46169 | C87: SERGIO | E87: 80 | F87: 46178 | G87: =IFERROR(VLOOKUP(Tabla3[[#This Row],[NUM ECONOMICO]],MAQUINARIA!B:H,7,0), " MAQ") -> INACTIVA | H87: MT-01 | I87: 6V3965 | K87: 3 | M87: =+L87*K87 -> 0 | P87: =Tabla3[[#This Row],[COSTO UNITARIO DOLARES EN HAWTHORNE]]*Tabla3[[#This Row],[CANTIDAD SOLICTADA]] -> 0 | S87: =+Tabla3[[#This Row],[COSTO UNITARIO DOLARES CTP]]*Tabla3[[#This Row],[CANTIDAD SOLICTADA]] -> 0 | U87: ENTREGADO | X87: SI | Y87: 1 | AE87: COTIZANDO BENJAMIN | AG87: REPARACION DE TRANSMISION Y CONVERTIDOR | XFD87: =+Tabla3[[#This Row],[ESTATUS DE NUM ECONOMICO]] -> INACTIVA
A88: 32 | B88: 46169 | C88: SERGIO | D88: CE-1442 | E88: 80 | F88: 46178 | G88: =IFERROR(VLOOKUP(Tabla3[[#This Row],[NUM ECONOMICO]],MAQUINARIA!B:H,7,0), " MAQ") -> INACTIVA | H88: MT-01 | I88: 2147568 | K88: 5 | M88: =+L88*K88 -> 0 | P88: =Tabla3[[#This Row],[COSTO UNITARIO DOLARES EN HAWTHORNE]]*Tabla3[[#This Row],[CANTIDAD SOLICTADA]] -> 0 | S88: =+Tabla3[[#This Row],[COSTO UNITARIO DOLARES CTP]]*Tabla3[[#This Row],[CANTIDAD SOLICTADA]] -> 0 | U88: ENTREGADO | V88: QT-08-427760 | W88: 46174 | X88: NO | Y88: 3 | Z88: MATCO | AA88: 46171 | AB88: 46175 | AC88: JOSE EDUARDO | AE88: SE ENTREGA A JAVIER | AG88: REPARACION DE TRANSMISION Y CONVERTIDOR | XFD88: =+Tabla3[[#This Row],[ESTATUS DE NUM ECONOMICO]] -> INACTIVA
A89: 32 | B89: 46169 | C89: SERGIO | E89: 80 | F89: 46178 | G89: =IFERROR(VLOOKUP(Tabla3[[#This Row],[NUM ECONOMICO]],MAQUINARIA!B:H,7,0), " MAQ") -> INACTIVA | H89: MT-01 | I89: 5P7815 | K89: 3 | M89: =+L89*K89 -> 0 | P89: =Tabla3[[#This Row],[COSTO UNITARIO DOLARES EN HAWTHORNE]]*Tabla3[[#This Row],[CANTIDAD SOLICTADA]] -> 0 | S89: =+Tabla3[[#This Row],[COSTO UNITARIO DOLARES CTP]]*Tabla3[[#This Row],[CANTIDAD SOLICTADA]] -> 0 | U89: ENTREGADO | X89: SI | Y89: 3 | AE89: COTIZANDO BENJAMIN | AG89: REPARACION DE TRANSMISION Y CONVERTIDOR | XFD89: =+Tabla3[[#This Row],[ESTATUS DE NUM ECONOMICO]] -> INACTIVA
A90: 32 | B90: 46169 | C90: SERGIO | E90: 81 | F90: 46178 | G90: =IFERROR(VLOOKUP(Tabla3[[#This Row],[NUM ECONOMICO]],MAQUINARIA!B:H,7,0), " MAQ") -> INACTIVA | H90: MT-01 | I90: 6L9965 | J90: INTEGRAL DE LA GUARNIGA | K90: 1 | L90: 184.8 | M90: =+L90*K90 -> 184.8 | O90: 13.13 | P90: =Tabla3[[#This Row],[COSTO UNITARIO DOLARES EN HAWTHORNE]]*Tabla3[[#This Row],[CANTIDAD SOLICTADA]] -> 13.13 | Q90: 3-4 | R90: 0.59 | S90: =+Tabla3[[#This Row],[COSTO UNITARIO DOLARES CTP]]*Tabla3[[#This Row],[CANTIDAD SOLICTADA]] -> 0.59 | U90: COTIZANDO | V90: QT-08-427760 | X90: NO | Y90: SIN EXISTENCIA | Z90: ACTP | AA90: 46170 | AB90: 46118 | AE90: COTIZANDO BENJAMIN | AF90: COTIZANDO BENJAMIN | AG90: REPARACION DE TRANSMISION Y CONVERTIDOR | XFD90: =+Tabla3[[#This Row],[ESTATUS DE NUM ECONOMICO]] -> INACTIVA
A91: 32 | B91: 46169 | C91: SERGIO | D91: CE-1442 | E91: 80 | F91: 46178 | G91: =IFERROR(VLOOKUP(Tabla3[[#This Row],[NUM ECONOMICO]],MAQUINARIA!B:H,7,0), " MAQ") -> INACTIVA | H91: MT-01 | I91: 6V3250 | K91: 4 | M91: =+L91*K91 -> 0 | P91: =Tabla3[[#This Row],[COSTO UNITARIO DOLARES EN HAWTHORNE]]*Tabla3[[#This Row],[CANTIDAD SOLICTADA]] -> 0 | S91: =+Tabla3[[#This Row],[COSTO UNITARIO DOLARES CTP]]*Tabla3[[#This Row],[CANTIDAD SOLICTADA]] -> 0 | U91: ENTREGADO | V91: QT-08-427760 | W91: 46174 | X91: NO | Y91: SIN EXISTENCIA | Z91: MATCO | AA91: 46171 | AB91: 46175 | AC91: JOSE EDUARDO | AE91: SE ENTREGA A JAVIER | AG91: REPARACION DE TRANSMISION Y CONVERTIDOR | XFD91: =+Tabla3[[#This Row],[ESTATUS DE NUM ECONOMICO]] -> INACTIVA
A92: 32 | B92: 46169 | C92: SERGIO | E92: 81 | F92: 46178 | G92: =IFERROR(VLOOKUP(Tabla3[[#This Row],[NUM ECONOMICO]],MAQUINARIA!B:H,7,0), " MAQ") -> INACTIVA | H92: MT-01 | I92: 1046730 | J92: EMPAQUE | K92: 1 | L92: 55.65 | M92: =+L92*K92 -> 55.65 | O92: 3.94 | P92: =Tabla3[[#This Row],[COSTO UNITARIO DOLARES EN HAWTHORNE]]*Tabla3[[#This Row],[CANTIDAD SOLICTADA]] -> 3.94 | Q92: 3-4 | R92: 0.54 | S92: =+Tabla3[[#This Row],[COSTO UNITARIO DOLARES CTP]]*Tabla3[[#This Row],[CANTIDAD SOLICTADA]] -> 0.54 | U92: COTIZANDO | V92: QT-08-427760 | X92: NO | Y92: SIN EXISTENCIA | Z92: ACTP | AA92: 46170 | AB92: 46118 | AE92: COTIZANDO BENJAMIN | AF92: COTIZANDO BENJAMIN | AG92: REPARACION DE TRANSMISION Y CONVERTIDOR | XFD92: =+Tabla3[[#This Row],[ESTATUS DE NUM ECONOMICO]] -> INACTIVA
A93: 32 | B93: 46169 | C93: SERGIO | E93: 81 | F93: 46178 | G93: =IFERROR(VLOOKUP(Tabla3[[#This Row],[NUM ECONOMICO]],MAQUINARIA!B:H,7,0), " MAQ") -> INACTIVA | H93: MT-01 | I93: 6J2419 | J93: EMPAQUE | K93: 1 | L93: 40.43 | M93: =+L93*K93 -> 40.43 | O93: 2.85 | P93: =Tabla3[[#This Row],[COSTO UNITARIO DOLARES EN HAWTHORNE]]*Tabla3[[#This Row],[CANTIDAD SOLICTADA]] -> 2.85 | Q93: 3-4 | R93: 0.19 | S93: =+Tabla3[[#This Row],[COSTO UNITARIO DOLARES CTP]]*Tabla3[[#This Row],[CANTIDAD SOLICTADA]] -> 0.19 | U93: COTIZANDO | V93: QT-08-427760 | X93: NO | Y93: 0 | Z93: ACTP | AA93: 46170 | AB93: 46118 | AE93: COTIZANDO BENJAMIN | AF93: COTIZANDO BENJAMIN | AG93: REPARACION DE TRANSMISION Y CONVERTIDOR | XFD93: =+Tabla3[[#This Row],[ESTATUS DE NUM ECONOMICO]] -> INACTIVA
A94: 32 | B94: 46169 | C94: SERGIO | E94: 80 | F94: 46178 | G94: =IFERROR(VLOOKUP(Tabla3[[#This Row],[NUM ECONOMICO]],MAQUINARIA!B:H,7,0), " MAQ") -> INACTIVA | H94: MT-01 | I94: 8M4432 | K94: 6 | M94: =+L94*K94 -> 0 | P94: =Tabla3[[#This Row],[COSTO UNITARIO DOLARES EN HAWTHORNE]]*Tabla3[[#This Row],[CANTIDAD SOLICTADA]] -> 0 | S94: =+Tabla3[[#This Row],[COSTO UNITARIO DOLARES CTP]]*Tabla3[[#This Row],[CANTIDAD SOLICTADA]] -> 0 | U94: ENTREGADO | X94: NO | Y94: 13 | AE94: COTIZANDO BENJAMIN | AG94: REPARACION DE TRANSMISION Y CONVERTIDOR | XFD94: =+Tabla3[[#This Row],[ESTATUS DE NUM ECONOMICO]] -> INACTIVA
A95: 32 | B95: 46169 | C95: SERGIO | E95: 81 | F95: 46178 | G95: =IFERROR(VLOOKUP(Tabla3[[#This Row],[NUM ECONOMICO]],MAQUINARIA!B:H,7,0), " MAQ") -> INACTIVA | H95: MT-01 | I95: 2443114 | J95: SELLADO DE JUNTA TÓRICA | K95: 1 | L95: 6175.58 | M95: =+L95*K95 -> 6175.58 | O95: 353.01 | P95: =Tabla3[[#This Row],[COSTO UNITARIO DOLARES EN HAWTHORNE]]*Tabla3[[#This Row],[CANTIDAD SOLICTADA]] -> 353.01 | Q95: 3-4 | R95: 123.26 | S95: =+Tabla3[[#This Row],[COSTO UNITARIO DOLARES CTP]]*Tabla3[[#This Row],[CANTIDAD SOLICTADA]] -> 123.26 | U95: COTIZANDO | V95: QT-08-427760 | X95: NO | Y95: SIN EXISTENCIA | Z95: ACTP | AA95: 46170 | AB95: 46118 | AE95: COTIZANDO BENJAMIN | AF95: COTIZANDO BENJAMIN | AG95: REPARACION DE TRANSMISION Y CONVERTIDOR | XFD95: =+Tabla3[[#This Row],[ESTATUS DE NUM ECONOMICO]] -> INACTIVA
A96: 32 | B96: 46169 | C96: SERGIO | D96: CE-1442 | E96: 80 | F96: 46178 | G96: =IFERROR(VLOOKUP(Tabla3[[#This Row],[NUM ECONOMICO]],MAQUINARIA!B:H,7,0), " MAQ") -> INACTIVA | H96: MT-01 | I96: 8M5661 | K96: 1 | M96: =+L96*K96 -> 0 | P96: =Tabla3[[#This Row],[COSTO UNITARIO DOLARES EN HAWTHORNE]]*Tabla3[[#This Row],[CANTIDAD SOLICTADA]] -> 0 | S96: =+Tabla3[[#This Row],[COSTO UNITARIO DOLARES CTP]]*Tabla3[[#This Row],[CANTIDAD SOLICTADA]] -> 0 | U96: ENTREGADO | V96: QT-08-427760 | W96: 46174 | X96: NO | Y96: 2 | Z96: MATCO | AA96: 46171 | AB96: 46175 | AC96: JOSE EDUARDO | AE96: SE ENTREGA A JAVIER | AG96: REPARACION DE TRANSMISION Y CONVERTIDOR | XFD96: =+Tabla3[[#This Row],[ESTATUS DE NUM ECONOMICO]] -> INACTIVA
A97: 32 | B97: 46169 | C97: SERGIO | D97: CE-1442 | E97: 80 | F97: 46178 | G97: =IFERROR(VLOOKUP(Tabla3[[#This Row],[NUM ECONOMICO]],MAQUINARIA!B:H,7,0), " MAQ") -> INACTIVA | H97: MT-01 | I97: 6F0156 | K97: 1 | M97: =+L97*K97 -> 0 | P97: =Tabla3[[#This Row],[COSTO UNITARIO DOLARES EN HAWTHORNE]]*Tabla3[[#This Row],[CANTIDAD SOLICTADA]] -> 0 | S97: =+Tabla3[[#This Row],[COSTO UNITARIO DOLARES CTP]]*Tabla3[[#This Row],[CANTIDAD SOLICTADA]] -> 0 | U97: ENTREGADO | V97: QT-08-427760 | W97: 46174 | X97: NO | Y97: 1 | Z97: MATCO | AA97: 46171 | AB97: 46175 | AC97: JOSE EDUARDO | AE97: SE ENTREGA A JAVIER | AG97: REPARACION DE TRANSMISION Y CONVERTIDOR | XFD97: =+Tabla3[[#This Row],[ESTATUS DE NUM ECONOMICO]] -> INACTIVA
A98: 32 | B98: 46169 | C98: SERGIO | E98: 81 | F98: 46178 | G98: =IFERROR(VLOOKUP(Tabla3[[#This Row],[NUM ECONOMICO]],MAQUINARIA!B:H,7,0), " MAQ") -> INACTIVA | H98: MT-01 | I98: 1067798 | J98: JUNTA-CTP [FC] | K98: 2 | L98: 1256.15 | M98: =+L98*K98 -> 2512.3 | O98: 78.38 | P98: =Tabla3[[#This Row],[COSTO UNITARIO DOLARES EN HAWTHORNE]]*Tabla3[[#This Row],[CANTIDAD SOLICTADA]] -> 156.76 | Q98: 3-4 | R98: 34.64 | S98: =+Tabla3[[#This Row],[COSTO UNITARIO DOLARES CTP]]*Tabla3[[#This Row],[CANTIDAD SOLICTADA]] -> 69.28 | U98: COTIZANDO | V98: QT-08-427760 | X98: NO | Y98: 2 | Z98: ACTP | AA98: 46170 | AB98: 46118 | AE98: COTIZANDO BENJAMIN | AF98: COTIZANDO BENJAMIN | AG98: REPARACION DE TRANSMISION Y CONVERTIDOR | XFD98: =+Tabla3[[#This Row],[ESTATUS DE NUM ECONOMICO]] -> INACTIVA
A99: 32 | B99: 46169 | C99: SERGIO | D99: CE-1442 | E99: 80 | F99: 46178 | G99: =IFERROR(VLOOKUP(Tabla3[[#This Row],[NUM ECONOMICO]],MAQUINARIA!B:H,7,0), " MAQ") -> INACTIVA | H99: MT-01 | I99: 9F3788 | K99: 1 | M99: =+L99*K99 -> 0 | P99: =Tabla3[[#This Row],[COSTO UNITARIO DOLARES EN HAWTHORNE]]*Tabla3[[#This Row],[CANTIDAD SOLICTADA]] -> 0 | S99: =+Tabla3[[#This Row],[COSTO UNITARIO DOLARES CTP]]*Tabla3[[#This Row],[CANTIDAD SOLICTADA]] -> 0 | U99: ENTREGADO | V99: QT-08-427760 | W99: 46174 | X99: NO | Y99: SIN EXISTENCIA | Z99: MATCO | AA99: 46171 | AB99: 46175 | AC99: JOSE EDUARDO | AE99: SE ENTREGA A JAVIER | AG99: REPARACION DE TRANSMISION Y CONVERTIDOR | XFD99: =+Tabla3[[#This Row],[ESTATUS DE NUM ECONOMICO]] -> INACTIVA
A100: 32 | B100: 46169 | C100: SERGIO | D100: CE-1442 | E100: 80 | F100: 46178 | G100: =IFERROR(VLOOKUP(Tabla3[[#This Row],[NUM ECONOMICO]],MAQUINARIA!B:H,7,0), " MAQ") -> INACTIVA | H100: MT-01 | I100: 3P3321 | K100: 2 | M100: =+L100*K100 -> 0 | P100: =Tabla3[[#This Row],[COSTO UNITARIO DOLARES EN HAWTHORNE]]*Tabla3[[#This Row],[CANTIDAD SOLICTADA]] -> 0 | S100: =+Tabla3[[#This Row],[COSTO UNITARIO DOLARES CTP]]*Tabla3[[#This Row],[CANTIDAD SOLICTADA]] -> 0 | U100: ENTREGADO | V100: QT-08-427760 | W100: 46174 | X100: NO | Y100: SIN EXISTENCIA | Z100: MATCO | AA100: 46171 | AB100: 46175 | AC100: JOSE EDUARDO | AE100: SE ENTREGA A JAVIER | AG100: REPARACION DE TRANSMISION Y CONVERTIDOR | XFD100: =+Tabla3[[#This Row],[ESTATUS DE NUM ECONOMICO]] -> INACTIVA
...

Sheet RESUMEN GLOBAL
B2: COMPARATIVO DE COTIZACIÓN DE REFACCIONES — 2026
B3: TIPO DE CAMBIO DEL DÍA (MXN/USD): | E3: 17 | F3: ⬅ Captura aquí el tipo de cambio del día
B5: RESUMEN GLOBAL — PARTIDAS EN COTIZACIÓN (Excluye Servicios de Filtros) | N5: Proveedor | O5: Costo MXN
B6: Unidades con pedidos | C6: Pedidos en cotización | D6: Partidas totales | E6: Costo total MATCO (MXN s/IVA) | F6: Costo total HAWTHORNE (USD) | G6: Costo total CTP (USD) | H6: Partidas con costo MATCO | I6: Sin precio MATCO | J6: Partidas cotizadas HAWTHORNE | K6: Partidas cotizadas CTP | N6: MATCO | O6: =E8 -> 6047672
B7: {=ROWS(_xlfn.UNIQUE(_xlfn._xlws.FILTER(Tabla3[NUM ECONOMICO],(Tabla3[STATUS]="COTIZANDO")*(Tabla3[TEMA]<>"SERVICIO DE FILTROS"))))} -> 13 | C7: {=ROWS(_xlfn.UNIQUE(_xlfn._xlws.FILTER(Tabla3[PEDIDO],(Tabla3[STATUS]="COTIZANDO")*(Tabla3[TEMA]<>"SERVICIO DE FILTROS"))))} -> 18 | D7: =COUNTIFS(Tabla3[STATUS],"COTIZANDO",Tabla3[TEMA],"<>SERVICIO DE FILTROS") -> 704 | E7: =SUMIFS(Tabla3[COSTO TOTAL SIN IVA PESOS EN MATCO],Tabla3[STATUS],"COTIZANDO",Tabla3[TEMA],"<>SERVICIO DE FILTROS") -> 6047672 | F7: =SUMIFS(Tabla3[COSTO TOTAL DOLARES EN HAWTHORNE],Tabla3[STATUS],"COTIZANDO",Tabla3[TEMA],"<>SERVICIO DE FILTROS") -> 191410.88 | G7: =SUMIFS(Tabla3[COSTO TOTAL DOLARES CTP],Tabla3[STATUS],"COTIZANDO",Tabla3[TEMA],"<>SERVICIO DE FILTROS") -> 23109.76 | H7: =COUNTIFS(Tabla3[STATUS],"COTIZANDO",Tabla3[COSTO TOTAL SIN IVA PESOS EN MATCO],">0",Tabla3[TEMA],"<>SERVICIO DE FILTROS") -> 699 | I7: =COUNTIFS(Tabla3[STATUS],"COTIZANDO",Tabla3[COSTO TOTAL SIN IVA PESOS EN MATCO],"=0",Tabla3[TEMA],"<>SERVICIO DE FILTROS") -> 5 | J7: =COUNTIFS(Tabla3[STATUS],"COTIZANDO",Tabla3[COSTO TOTAL DOLARES EN HAWTHORNE],">0",Tabla3[TEMA],"<>SERVICIO DE FILTROS") -> 190 | K7: =COUNTIFS(Tabla3[STATUS],"COTIZANDO",Tabla3[COSTO TOTAL DOLARES CTP],">0",Tabla3[TEMA],"<>SERVICIO DE FILTROS") -> 153 | N7: HAWTHORNE | O7: =F8 -> 3253985
D8: Costo equivalente en MXN | E8: =E7 -> 6047672 | F8: =IF($E$3>0,F7*$E$3,0) -> 3253985 | G8: =IF($E$3>0,G7*$E$3,0) -> 392865.92 | N8: CTP | O8: =G8 -> 392865.92
B10: RESUMEN POR UNIDAD ECONÓMICA (Excluye Servicios de Filtros)
B11: NÚM. ECON. | C11: ESTATUS | D11: FAMILIA / MODELO | E11: PEDIDOS | F11: PARTIDAS | G11: COSTO MATCO (MXN s/IVA) | H11: COSTO HAWTHORNE (USD) | I11: HAWTHORNE EN MXN * | J11: COSTO CTP (USD) | K11: CTP EN MXN * | L11: DÍAS MATCO
B12: =MAQUINARIA!B421 -> BC-01 | C12: =MAQUINARIA!H421 -> ACTIVA | D12: =IFERROR(TRIM(MAQUINARIA!C421&" "&MAQUINARIA!E421),"—") -> BOMBA DE CONCRETO | E12: {=IF(B12="",0,IFERROR(ROWS(_xlfn.UNIQUE(_xlfn._xlws.FILTER(Tabla3[PEDIDO],(Tabla3[STATUS]="COTIZANDO")*(Tabla3[NUM ECONOMICO]=B12)*(Tabla3[TEMA]<>"SERVICIO DE FILTROS")))),0))} -> 0 | F12: =IF(B12="",0,COUNTIFS(Tabla3[STATUS],"COTIZANDO",Tabla3[NUM ECONOMICO],B12,Tabla3[TEMA],"<>SERVICIO DE FILTROS")) -> 0 | G12: =IF(B12="",0,SUMIFS(Tabla3[COSTO TOTAL SIN IVA PESOS EN MATCO],Tabla3[STATUS],"COTIZANDO",Tabla3[NUM ECONOMICO],B12,Tabla3[TEMA],"<>SERVICIO DE FILTROS")) -> 0 | H12: =IF(B12="",0,SUMIFS(Tabla3[COSTO TOTAL DOLARES EN HAWTHORNE],Tabla3[STATUS],"COTIZANDO",Tabla3[NUM ECONOMICO],B12,Tabla3[TEMA],"<>SERVICIO DE FILTROS")) -> 0 | I12: =IF(B12="","",_xlfn.LET(_xlpm.totalUSD,SUMIFS(Tabla3[COSTO TOTAL DOLARES EN HAWTHORNE],Tabla3[STATUS],"COTIZANDO",Tabla3[NUM ECONOMICO],B12,Tabla3[TEMA],"<>SERVICIO DE FILTROS"),IF(OR(TC="",_xlpm.totalUSD=0),"—",_xlpm.totalUSD*TC))) -> — | J12: =IF(B12="",0,SUMIFS(Tabla3[COSTO TOTAL DOLARES CTP],Tabla3[STATUS],"COTIZANDO",Tabla3[NUM ECONOMICO],B12,Tabla3[TEMA],"<>SERVICIO DE FILTROS")) -> 0 | K12: =IF(B12="","",_xlfn.LET(_xlpm.totalUSD,SUMIFS(Tabla3[COSTO TOTAL DOLARES CTP],Tabla3[STATUS],"COTIZANDO",Tabla3[NUM ECONOMICO],B12,Tabla3[TEMA],"<>SERVICIO DE FILTROS"),IF(OR(TC="",_xlpm.totalUSD=0),"—",_xlpm.totalUSD*TC))) -> — | L12: {=IF(B12="",0,IFERROR(MAX(_xlfn._xlws.FILTER(Tabla3[DIAS DE ENTREGA TENTATIVO EN MATCO],(Tabla3[STATUS]="COTIZANDO")*(Tabla3[NUM ECONOMICO]=B12)*(Tabla3[TEMA]<>"SERVICIO DE FILTROS"))),0))} -> 0
B13: =MAQUINARIA!B462 -> CGP-01 | C13: =MAQUINARIA!H462 -> ACTIVA | D13: =IFERROR(TRIM(MAQUINARIA!C462&" "&MAQUINARIA!E462),"—") -> CAMION GRUA PERFORADOR | E13: {=IF(B13="",0,IFERROR(ROWS(_xlfn.UNIQUE(_xlfn._xlws.FILTER(Tabla3[PEDIDO],(Tabla3[STATUS]="COTIZANDO")*(Tabla3[NUM ECONOMICO]=B13)*(Tabla3[TEMA]<>"SERVICIO DE FILTROS")))),0))} -> 0 | F13: =IF(B13="",0,COUNTIFS(Tabla3[STATUS],"COTIZANDO",Tabla3[NUM ECONOMICO],B13,Tabla3[TEMA],"<>SERVICIO DE FILTROS")) -> 0 | G13: =IF(B13="",0,SUMIFS(Tabla3[COSTO TOTAL SIN IVA PESOS EN MATCO],Tabla3[STATUS],"COTIZANDO",Tabla3[NUM ECONOMICO],B13,Tabla3[TEMA],"<>SERVICIO DE FILTROS")) -> 0 | H13: =IF(B13="",0,SUMIFS(Tabla3[COSTO TOTAL DOLARES EN HAWTHORNE],Tabla3[STATUS],"COTIZANDO",Tabla3[NUM ECONOMICO],B13,Tabla3[TEMA],"<>SERVICIO DE FILTROS")) -> 0 | I13: =IF(B13="","",_xlfn.LET(_xlpm.totalUSD,SUMIFS(Tabla3[COSTO TOTAL DOLARES EN HAWTHORNE],Tabla3[STATUS],"COTIZANDO",Tabla3[NUM ECONOMICO],B13,Tabla3[TEMA],"<>SERVICIO DE FILTROS"),IF(OR(TC="",_xlpm.totalUSD=0),"—",_xlpm.totalUSD*TC))) -> — | J13: =IF(B13="",0,SUMIFS(Tabla3[COSTO TOTAL DOLARES CTP],Tabla3[STATUS],"COTIZANDO",Tabla3[NUM ECONOMICO],B13,Tabla3[TEMA],"<>SERVICIO DE FILTROS")) -> 0 | K13: =IF(B13="","",_xlfn.LET(_xlpm.totalUSD,SUMIFS(Tabla3[COSTO TOTAL DOLARES CTP],Tabla3[STATUS],"COTIZANDO",Tabla3[NUM ECONOMICO],B13,Tabla3[TEMA],"<>SERVICIO DE FILTROS"),IF(OR(TC="",_xlpm.totalUSD=0),"—",_xlpm.totalUSD*TC))) -> — | L13: {=IF(B13="",0,IFERROR(MAX(_xlfn._xlws.FILTER(Tabla3[DIAS DE ENTREGA TENTATIVO EN MATCO],(Tabla3[STATUS]="COTIZANDO")*(Tabla3[NUM ECONOMICO]=B13)*(Tabla3[TEMA]<>"SERVICIO DE FILTROS"))),0))} -> 0
B14: =MAQUINARIA!B493 -> CL-01 | C14: =MAQUINARIA!H493 -> INACTIVA | D14: =IFERROR(TRIM(MAQUINARIA!C493&" "&MAQUINARIA!E493),"—") -> CAMION DE LAVADO 650 | E14: {=IF(B14="",0,IFERROR(ROWS(_xlfn.UNIQUE(_xlfn._xlws.FILTER(Tabla3[PEDIDO],(Tabla3[STATUS]="COTIZANDO")*(Tabla3[NUM ECONOMICO]=B14)*(Tabla3[TEMA]<>"SERVICIO DE FILTROS")))),0))} -> 0 | F14: =IF(B14="",0,COUNTIFS(Tabla3[STATUS],"COTIZANDO",Tabla3[NUM ECONOMICO],B14,Tabla3[TEMA],"<>SERVICIO DE FILTROS")) -> 0 | G14: =IF(B14="",0,SUMIFS(Tabla3[COSTO TOTAL SIN IVA PESOS EN MATCO],Tabla3[STATUS],"COTIZANDO",Tabla3[NUM ECONOMICO],B14,Tabla3[TEMA],"<>SERVICIO DE FILTROS")) -> 0 | H14: =IF(B14="",0,SUMIFS(Tabla3[COSTO TOTAL DOLARES EN HAWTHORNE],Tabla3[STATUS],"COTIZANDO",Tabla3[NUM ECONOMICO],B14,Tabla3[TEMA],"<>SERVICIO DE FILTROS")) -> 0 | I14: =IF(B14="","",_xlfn.LET(_xlpm.totalUSD,SUMIFS(Tabla3[COSTO TOTAL DOLARES EN HAWTHORNE],Tabla3[STATUS],"COTIZANDO",Tabla3[NUM ECONOMICO],B14,Tabla3[TEMA],"<>SERVICIO DE FILTROS"),IF(OR(TC="",_xlpm.totalUSD=0),"—",_xlpm.totalUSD*TC))) -> — | J14: =IF(B14="",0,SUMIFS(Tabla3[COSTO TOTAL DOLARES CTP],Tabla3[STATUS],"COTIZANDO",Tabla3[NUM ECONOMICO],B14,Tabla3[TEMA],"<>SERVICIO DE FILTROS")) -> 0 | K14: =IF(B14="","",_xlfn.LET(_xlpm.totalUSD,SUMIFS(Tabla3[COSTO TOTAL DOLARES CTP],Tabla3[STATUS],"COTIZANDO",Tabla3[NUM ECONOMICO],B14,Tabla3[TEMA],"<>SERVICIO DE FILTROS"),IF(OR(TC="",_xlpm.totalUSD=0),"—",_xlpm.totalUSD*TC))) -> — | L14: {=IF(B14="",0,IFERROR(MAX(_xlfn._xlws.FILTER(Tabla3[DIAS DE ENTREGA TENTATIVO EN MATCO],(Tabla3[STATUS]="COTIZANDO")*(Tabla3[NUM ECONOMICO]=B14)*(Tabla3[TEMA]<>"SERVICIO DE FILTROS"))),0))} -> 0
B15: =MAQUINARIA!B481 -> CM-01 | C15: =MAQUINARIA!H481 -> ACTIVA | D15: =IFERROR(TRIM(MAQUINARIA!C481&" "&MAQUINARIA!E481),"—") -> CAMA BAJA | E15: {=IF(B15="",0,IFERROR(ROWS(_xlfn.UNIQUE(_xlfn._xlws.FILTER(Tabla3[PEDIDO],(Tabla3[STATUS]="COTIZANDO")*(Tabla3[NUM ECONOMICO]=B15)*(Tabla3[TEMA]<>"SERVICIO DE FILTROS")))),0))} -> 0 | F15: =IF(B15="",0,COUNTIFS(Tabla3[STATUS],"COTIZANDO",Tabla3[NUM ECONOMICO],B15,Tabla3[TEMA],"<>SERVICIO DE FILTROS")) -> 0 | G15: =IF(B15="",0,SUMIFS(Tabla3[COSTO TOTAL SIN IVA PESOS EN MATCO],Tabla3[STATUS],"COTIZANDO",Tabla3[NUM ECONOMICO],B15,Tabla3[TEMA],"<>SERVICIO DE FILTROS")) -> 0 | H15: =IF(B15="",0,SUMIFS(Tabla3[COSTO TOTAL DOLARES EN HAWTHORNE],Tabla3[STATUS],"COTIZANDO",Tabla3[NUM ECONOMICO],B15,Tabla3[TEMA],"<>SERVICIO DE FILTROS")) -> 0 | I15: =IF(B15="","",_xlfn.LET(_xlpm.totalUSD,SUMIFS(Tabla3[COSTO TOTAL DOLARES EN HAWTHORNE],Tabla3[STATUS],"COTIZANDO",Tabla3[NUM ECONOMICO],B15,Tabla3[TEMA],"<>SERVICIO DE FILTROS"),IF(OR(TC="",_xlpm.totalUSD=0),"—",_xlpm.totalUSD*TC))) -> — | J15: =IF(B15="",0,SUMIFS(Tabla3[COSTO TOTAL DOLARES CTP],Tabla3[STATUS],"COTIZANDO",Tabla3[NUM ECONOMICO],B15,Tabla3[TEMA],"<>SERVICIO DE FILTROS")) -> 0 | K15: =IF(B15="","",_xlfn.LET(_xlpm.totalUSD,SUMIFS(Tabla3[COSTO TOTAL DOLARES CTP],Tabla3[STATUS],"COTIZANDO",Tabla3[NUM ECONOMICO],B15,Tabla3[TEMA],"<>SERVICIO DE FILTROS"),IF(OR(TC="",_xlpm.totalUSD=0),"—",_xlpm.totalUSD*TC))) -> — | L15: {=IF(B15="",0,IFERROR(MAX(_xlfn._xlws.FILTER(Tabla3[DIAS DE ENTREGA TENTATIVO EN MATCO],(Tabla3[STATUS]="COTIZANDO")*(Tabla3[NUM ECONOMICO]=B15)*(Tabla3[TEMA]<>"SERVICIO DE FILTROS"))),0))} -> 0
B16: =MAQUINARIA!B482 -> CM-02 | C16: =MAQUINARIA!H482 -> ACTIVA | D16: =IFERROR(TRIM(MAQUINARIA!C482&" "&MAQUINARIA!E482),"—") -> CAMA BAJA WITZCO | E16: {=IF(B16="",0,IFERROR(ROWS(_xlfn.UNIQUE(_xlfn._xlws.FILTER(Tabla3[PEDIDO],(Tabla3[STATUS]="COTIZANDO")*(Tabla3[NUM ECONOMICO]=B16)*(Tabla3[TEMA]<>"SERVICIO DE FILTROS")))),0))} -> 0 | F16: =IF(B16="",0,COUNTIFS(Tabla3[STATUS],"COTIZANDO",Tabla3[NUM ECONOMICO],B16,Tabla3[TEMA],"<>SERVICIO DE FILTROS")) -> 0 | G16: =IF(B16="",0,SUMIFS(Tabla3[COSTO TOTAL SIN IVA PESOS EN MATCO],Tabla3[STATUS],"COTIZANDO",Tabla3[NUM ECONOMICO],B16,Tabla3[TEMA],"<>SERVICIO DE FILTROS")) -> 0 | H16: =IF(B16="",0,SUMIFS(Tabla3[COSTO TOTAL DOLARES EN HAWTHORNE],Tabla3[STATUS],"COTIZANDO",Tabla3[NUM ECONOMICO],B16,Tabla3[TEMA],"<>SERVICIO DE FILTROS")) -> 0 | I16: =IF(B16="","",_xlfn.LET(_xlpm.totalUSD,SUMIFS(Tabla3[COSTO TOTAL DOLARES EN HAWTHORNE],Tabla3[STATUS],"COTIZANDO",Tabla3[NUM ECONOMICO],B16,Tabla3[TEMA],"<>SERVICIO DE FILTROS"),IF(OR(TC="",_xlpm.totalUSD=0),"—",_xlpm.totalUSD*TC))) -> — | J16: =IF(B16="",0,SUMIFS(Tabla3[COSTO TOTAL DOLARES CTP],Tabla3[STATUS],"COTIZANDO",Tabla3[NUM ECONOMICO],B16,Tabla3[TEMA],"<>SERVICIO DE FILTROS")) -> 0 | K16: =IF(B16="","",_xlfn.LET(_xlpm.totalUSD,SUMIFS(Tabla3[COSTO TOTAL DOLARES CTP],Tabla3[STATUS],"COTIZANDO",Tabla3[NUM ECONOMICO],B16,Tabla3[TEMA],"<>SERVICIO DE FILTROS"),IF(OR(TC="",_xlpm.totalUSD=0),"—",_xlpm.totalUSD*TC))) -> — | L16: {=IF(B16="",0,IFERROR(MAX(_xlfn._xlws.FILTER(Tabla3[DIAS DE ENTREGA TENTATIVO EN MATCO],(Tabla3[STATUS]="COTIZANDO")*(Tabla3[NUM ECONOMICO]=B16)*(Tabla3[TEMA]<>"SERVICIO DE FILTROS"))),0))} -> 0
B17: =MAQUINARIA!B483 -> CM-03 | C17: =MAQUINARIA!H483 -> ACTIVA | D17: =IFERROR(TRIM(MAQUINARIA!C483&" "&MAQUINARIA!E483),"—") -> CAMA BAJA | E17: {=IF(B17="",0,IFERROR(ROWS(_xlfn.UNIQUE(_xlfn._xlws.FILTER(Tabla3[PEDIDO],(Tabla3[STATUS]="COTIZANDO")*(Tabla3[NUM ECONOMICO]=B17)*(Tabla3[TEMA]<>"SERVICIO DE FILTROS")))),0))} -> 0 | F17: =IF(B17="",0,COUNTIFS(Tabla3[STATUS],"COTIZANDO",Tabla3[NUM ECONOMICO],B17,Tabla3[TEMA],"<>SERVICIO DE FILTROS")) -> 0 | G17: =IF(B17="",0,SUMIFS(Tabla3[COSTO TOTAL SIN IVA PESOS EN MATCO],Tabla3[STATUS],"COTIZANDO",Tabla3[NUM ECONOMICO],B17,Tabla3[TEMA],"<>SERVICIO DE FILTROS")) -> 0 | H17: =IF(B17="",0,SUMIFS(Tabla3[COSTO TOTAL DOLARES EN HAWTHORNE],Tabla3[STATUS],"COTIZANDO",Tabla3[NUM ECONOMICO],B17,Tabla3[TEMA],"<>SERVICIO DE FILTROS")) -> 0 | I17: =IF(B17="","",_xlfn.LET(_xlpm.totalUSD,SUMIFS(Tabla3[COSTO TOTAL DOLARES EN HAWTHORNE],Tabla3[STATUS],"COTIZANDO",Tabla3[NUM ECONOMICO],B17,Tabla3[TEMA],"<>SERVICIO DE FILTROS"),IF(OR(TC="",_xlpm.totalUSD=0),"—",_xlpm.totalUSD*TC))) -> — | J17: =IF(B17="",0,SUMIFS(Tabla3[COSTO TOTAL DOLARES CTP],Tabla3[STATUS],"COTIZANDO",Tabla3[NUM ECONOMICO],B17,Tabla3[TEMA],"<>SERVICIO DE FILTROS")) -> 0 | K17: =IF(B17="","",_xlfn.LET(_xlpm.totalUSD,SUMIFS(Tabla3[COSTO TOTAL DOLARES CTP],Tabla3[STATUS],"COTIZANDO",Tabla3[NUM ECONOMICO],B17,Tabla3[TEMA],"<>SERVICIO DE FILTROS"),IF(OR(TC="",_xlpm.totalUSD=0),"—",_xlpm.totalUSD*TC))) -> — | L17: {=IF(B17="",0,IFERROR(MAX(_xlfn._xlws.FILTER(Tabla3[DIAS DE ENTREGA TENTATIVO EN MATCO],(Tabla3[STATUS]="COTIZANDO")*(Tabla3[NUM ECONOMICO]=B17)*(Tabla3[TEMA]<>"SERVICIO DE FILTROS"))),0))} -> 0
B18: =MAQUINARIA!B484 -> CM-04 | C18: =MAQUINARIA!H484 -> INACTIVA | D18: =IFERROR(TRIM(MAQUINARIA!C484&" "&MAQUINARIA!E484),"—") -> CAMA BAJA DOLLY | E18: {=IF(B18="",0,IFERROR(ROWS(_xlfn.UNIQUE(_xlfn._xlws.FILTER(Tabla3[PEDIDO],(Tabla3[STATUS]="COTIZANDO")*(Tabla3[NUM ECONOMICO]=B18)*(Tabla3[TEMA]<>"SERVICIO DE FILTROS")))),0))} -> 0 | F18: =IF(B18="",0,COUNTIFS(Tabla3[STATUS],"COTIZANDO",Tabla3[NUM ECONOMICO],B18,Tabla3[TEMA],"<>SERVICIO DE FILTROS")) -> 0 | G18: =IF(B18="",0,SUMIFS(Tabla3[COSTO TOTAL SIN IVA PESOS EN MATCO],Tabla3[STATUS],"COTIZANDO",Tabla3[NUM ECONOMICO],B18,Tabla3[TEMA],"<>SERVICIO DE FILTROS")) -> 0 | H18: =IF(B18="",0,SUMIFS(Tabla3[COSTO TOTAL DOLARES EN HAWTHORNE],Tabla3[STATUS],"COTIZANDO",Tabla3[NUM ECONOMICO],B18,Tabla3[TEMA],"<>SERVICIO DE FILTROS")) -> 0 | I18: =IF(B18="","",_xlfn.LET(_xlpm.totalUSD,SUMIFS(Tabla3[COSTO TOTAL DOLARES EN HAWTHORNE],Tabla3[STATUS],"COTIZANDO",Tabla3[NUM ECONOMICO],B18,Tabla3[TEMA],"<>SERVICIO DE FILTROS"),IF(OR(TC="",_xlpm.totalUSD=0),"—",_xlpm.totalUSD*TC))) -> — | J18: =IF(B18="",0,SUMIFS(Tabla3[COSTO TOTAL DOLARES CTP],Tabla3[STATUS],"COTIZANDO",Tabla3[NUM ECONOMICO],B18,Tabla3[TEMA],"<>SERVICIO DE FILTROS")) -> 0 | K18: =IF(B18="","",_xlfn.LET(_xlpm.totalUSD,SUMIFS(Tabla3[COSTO TOTAL DOLARES CTP],Tabla3[STATUS],"COTIZANDO",Tabla3[NUM ECONOMICO],B18,Tabla3[TEMA],"<>SERVICIO DE FILTROS"),IF(OR(TC="",_xlpm.totalUSD=0),"—",_xlpm.totalUSD*TC))) -> — | L18: {=IF(B18="",0,IFERROR(MAX(_xlfn._xlws.FILTER(Tabla3[DIAS DE ENTREGA TENTATIVO EN MATCO],(Tabla3[STATUS]="COTIZANDO")*(Tabla3[NUM ECONOMICO]=B18)*(Tabla3[TEMA]<>"SERVICIO DE FILTROS"))),0))} -> 0
B19: =MAQUINARIA!B420 -> CMX-01 | C19: =MAQUINARIA!H420 -> ACTIVA | D19: =IFERROR(TRIM(MAQUINARIA!C420&" "&MAQUINARIA!E420),"—") -> PLANTA DE CONCRETO MOVIL | E19: {=IF(B19="",0,IFERROR(ROWS(_xlfn.UNIQUE(_xlfn._xlws.FILTER(Tabla3[PEDIDO],(Tabla3[STATUS]="COTIZANDO")*(Tabla3[NUM ECONOMICO]=B19)*(Tabla3[TEMA]<>"SERVICIO DE FILTROS")))),0))} -> 0 | F19: =IF(B19="",0,COUNTIFS(Tabla3[STATUS],"COTIZANDO",Tabla3[NUM ECONOMICO],B19,Tabla3[TEMA],"<>SERVICIO DE FILTROS")) -> 0 | G19: =IF(B19="",0,SUMIFS(Tabla3[COSTO TOTAL SIN IVA PESOS EN MATCO],Tabla3[STATUS],"COTIZANDO",Tabla3[NUM ECONOMICO],B19,Tabla3[TEMA],"<>SERVICIO DE FILTROS")) -> 0 | H19: =IF(B19="",0,SUMIFS(Tabla3[COSTO TOTAL DOLARES EN HAWTHORNE],Tabla3[STATUS],"COTIZANDO",Tabla3[NUM ECONOMICO],B19,Tabla3[TEMA],"<>SERVICIO DE FILTROS")) -> 0 | I19: =IF(B19="","",_xlfn.LET(_xlpm.totalUSD,SUMIFS(Tabla3[COSTO TOTAL DOLARES EN HAWTHORNE],Tabla3[STATUS],"COTIZANDO",Tabla3[NUM ECONOMICO],B19,Tabla3[TEMA],"<>SERVICIO DE FILTROS"),IF(OR(TC="",_xlpm.totalUSD=0),"—",_xlpm.totalUSD*TC))) -> — | J19: =IF(B19="",0,SUMIFS(Tabla3[COSTO TOTAL DOLARES CTP],Tabla3[STATUS],"COTIZANDO",Tabla3[NUM ECONOMICO],B19,Tabla3[TEMA],"<>SERVICIO DE FILTROS")) -> 0 | K19: =IF(B19="","",_xlfn.LET(_xlpm.totalUSD,SUMIFS(Tabla3[COSTO TOTAL DOLARES CTP],Tabla3[STATUS],"COTIZANDO",Tabla3[NUM ECONOMICO],B19,Tabla3[TEMA],"<>SERVICIO DE FILTROS"),IF(OR(TC="",_xlpm.totalUSD=0),"—",_xlpm.totalUSD*TC))) -> — | L19: {=IF(B19="",0,IFERROR(MAX(_xlfn._xlws.FILTER(Tabla3[DIAS DE ENTREGA TENTATIVO EN MATCO],(Tabla3[STATUS]="COTIZANDO")*(Tabla3[NUM ECONOMICO]=B19)*(Tabla3[TEMA]<>"SERVICIO DE FILTROS"))),0))} -> 0
B20: =MAQUINARIA!B422 -> CRC-03 | C20: =MAQUINARIA!H422 -> ACTIVA | D20: =IFERROR(TRIM(MAQUINARIA!C422&" "&MAQUINARIA!E422),"—") -> CAMION REVOLVEDOR 7 MTS | E20: {=IF(B20="",0,IFERROR(ROWS(_xlfn.UNIQUE(_xlfn._xlws.FILTER(Tabla3[PEDIDO],(Tabla3[STATUS]="COTIZANDO")*(Tabla3[NUM ECONOMICO]=B20)*(Tabla3[TEMA]<>"SERVICIO DE FILTROS")))),0))} -> 0 | F20: =IF(B20="",0,COUNTIFS(Tabla3[STATUS],"COTIZANDO",Tabla3[NUM ECONOMICO],B20,Tabla3[TEMA],"<>SERVICIO DE FILTROS")) -> 0 | G20: =IF(B20="",0,SUMIFS(Tabla3[COSTO TOTAL SIN IVA PESOS EN MATCO],Tabla3[STATUS],"COTIZANDO",Tabla3[NUM ECONOMICO],B20,Tabla3[TEMA],"<>SERVICIO DE FILTROS")) -> 0 | H20: =IF(B20="",0,SUMIFS(Tabla3[COSTO TOTAL DOLARES EN HAWTHORNE],Tabla3[STATUS],"COTIZANDO",Tabla3[NUM ECONOMICO],B20,Tabla3[TEMA],"<>SERVICIO DE FILTROS")) -> 0 | I20: =IF(B20="","",_xlfn.LET(_xlpm.totalUSD,SUMIFS(Tabla3[COSTO TOTAL DOLARES EN HAWTHORNE],Tabla3[STATUS],"COTIZANDO",Tabla3[NUM ECONOMICO],B20,Tabla3[TEMA],"<>SERVICIO DE FILTROS"),IF(OR(TC="",_xlpm.totalUSD=0),"—",_xlpm.totalUSD*TC))) -> — | J20: =IF(B20="",0,SUMIFS(Tabla3[COSTO TOTAL DOLARES CTP],Tabla3[STATUS],"COTIZANDO",Tabla3[NUM ECONOMICO],B20,Tabla3[TEMA],"<>SERVICIO DE FILTROS")) -> 0 | K20: =IF(B20="","",_xlfn.LET(_xlpm.totalUSD,SUMIFS(Tabla3[COSTO TOTAL DOLARES CTP],Tabla3[STATUS],"COTIZANDO",Tabla3[NUM ECONOMICO],B20,Tabla3[TEMA],"<>SERVICIO DE FILTROS"),IF(OR(TC="",_xlpm.totalUSD=0),"—",_xlpm.totalUSD*TC))) -> — | L20: {=IF(B20="",0,IFERROR(MAX(_xlfn._xlws.FILTER(Tabla3[DIAS DE ENTREGA TENTATIVO EN MATCO],(Tabla3[STATUS]="COTIZANDO")*(Tabla3[NUM ECONOMICO]=B20)*(Tabla3[TEMA]<>"SERVICIO DE FILTROS"))),0))} -> 0
B21: =MAQUINARIA!B423 -> CRC-04 | C21: =MAQUINARIA!H423 -> INACTIVA | D21: =IFERROR(TRIM(MAQUINARIA!C423&" "&MAQUINARIA!E423),"—") -> CAMION REVOLVEDOR 7 MTS | E21: {=IF(B21="",0,IFERROR(ROWS(_xlfn.UNIQUE(_xlfn._xlws.FILTER(Tabla3[PEDIDO],(Tabla3[STATUS]="COTIZANDO")*(Tabla3[NUM ECONOMICO]=B21)*(Tabla3[TEMA]<>"SERVICIO DE FILTROS")))),0))} -> 0 | F21: =IF(B21="",0,COUNTIFS(Tabla3[STATUS],"COTIZANDO",Tabla3[NUM ECONOMICO],B21,Tabla3[TEMA],"<>SERVICIO DE FILTROS")) -> 0 | G21: =IF(B21="",0,SUMIFS(Tabla3[COSTO TOTAL SIN IVA PESOS EN MATCO],Tabla3[STATUS],"COTIZANDO",Tabla3[NUM ECONOMICO],B21,Tabla3[TEMA],"<>SERVICIO DE FILTROS")) -> 0 | H21: =IF(B21="",0,SUMIFS(Tabla3[COSTO TOTAL DOLARES EN HAWTHORNE],Tabla3[STATUS],"COTIZANDO",Tabla3[NUM ECONOMICO],B21,Tabla3[TEMA],"<>SERVICIO DE FILTROS")) -> 0 | I21: =IF(B21="","",_xlfn.LET(_xlpm.totalUSD,SUMIFS(Tabla3[COSTO TOTAL DOLARES EN HAWTHORNE],Tabla3[STATUS],"COTIZANDO",Tabla3[NUM ECONOMICO],B21,Tabla3[TEMA],"<>SERVICIO DE FILTROS"),IF(OR(TC="",_xlpm.totalUSD=0),"—",_xlpm.totalUSD*TC))) -> — | J21: =IF(B21="",0,SUMIFS(Tabla3[COSTO TOTAL DOLARES CTP],Tabla3[STATUS],"COTIZANDO",Tabla3[NUM ECONOMICO],B21,Tabla3[TEMA],"<>SERVICIO DE FILTROS")) -> 0 | K21: =IF(B21="","",_xlfn.LET(_xlpm.totalUSD,SUMIFS(Tabla3[COSTO TOTAL DOLARES CTP],Tabla3[STATUS],"COTIZANDO",Tabla3[NUM ECONOMICO],B21,Tabla3[TEMA],"<>SERVICIO DE FILTROS"),IF(OR(TC="",_xlpm.totalUSD=0),"—",_xlpm.totalUSD*TC))) -> — | L21: {=IF(B21="",0,IFERROR(MAX(_xlfn._xlws.FILTER(Tabla3[DIAS DE ENTREGA TENTATIVO EN MATCO],(Tabla3[STATUS]="COTIZANDO")*(Tabla3[NUM ECONOMICO]=B21)*(Tabla3[TEMA]<>"SERVICIO DE FILTROS"))),0))} -> 0
B22: =MAQUINARIA!B424 -> CRC-05 | C22: =MAQUINARIA!H424 -> ACTIVA | D22: =IFERROR(TRIM(MAQUINARIA!C424&" "&MAQUINARIA!E424),"—") -> CAMION REVOLVEDOR 7 MTS | E22: {=IF(B22="",0,IFERROR(ROWS(_xlfn.UNIQUE(_xlfn._xlws.FILTER(Tabla3[PEDIDO],(Tabla3[STATUS]="COTIZANDO")*(Tabla3[NUM ECONOMICO]=B22)*(Tabla3[TEMA]<>"SERVICIO DE FILTROS")))),0))} -> 0 | F22: =IF(B22="",0,COUNTIFS(Tabla3[STATUS],"COTIZANDO",Tabla3[NUM ECONOMICO],B22,Tabla3[TEMA],"<>SERVICIO DE FILTROS")) -> 0 | G22: =IF(B22="",0,SUMIFS(Tabla3[COSTO TOTAL SIN IVA PESOS EN MATCO],Tabla3[STATUS],"COTIZANDO",Tabla3[NUM ECONOMICO],B22,Tabla3[TEMA],"<>SERVICIO DE FILTROS")) -> 0 | H22: =IF(B22="",0,SUMIFS(Tabla3[COSTO TOTAL DOLARES EN HAWTHORNE],Tabla3[STATUS],"COTIZANDO",Tabla3[NUM ECONOMICO],B22,Tabla3[TEMA],"<>SERVICIO DE FILTROS")) -> 0 | I22: =IF(B22="","",_xlfn.LET(_xlpm.totalUSD,SUMIFS(Tabla3[COSTO TOTAL DOLARES EN HAWTHORNE],Tabla3[STATUS],"COTIZANDO",Tabla3[NUM ECONOMICO],B22,Tabla3[TEMA],"<>SERVICIO DE FILTROS"),IF(OR(TC="",_xlpm.totalUSD=0),"—",_xlpm.totalUSD*TC))) -> — | J22: =IF(B22="",0,SUMIFS(Tabla3[COSTO TOTAL DOLARES CTP],Tabla3[STATUS],"COTIZANDO",Tabla3[NUM ECONOMICO],B22,Tabla3[TEMA],"<>SERVICIO DE FILTROS")) -> 0 | K22: =IF(B22="","",_xlfn.LET(_xlpm.totalUSD,SUMIFS(Tabla3[COSTO TOTAL DOLARES CTP],Tabla3[STATUS],"COTIZANDO",Tabla3[NUM ECONOMICO],B22,Tabla3[TEMA],"<>SERVICIO DE FILTROS"),IF(OR(TC="",_xlpm.totalUSD=0),"—",_xlpm.totalUSD*TC))) -> — | L22: {=IF(B22="",0,IFERROR(MAX(_xlfn._xlws.FILTER(Tabla3[DIAS DE ENTREGA TENTATIVO EN MATCO],(Tabla3[STATUS]="COTIZANDO")*(Tabla3[NUM ECONOMICO]=B22)*(Tabla3[TEMA]<>"SERVICIO DE FILTROS"))),0))} -> 0
B23: =MAQUINARIA!B361 -> CV-01 | C23: =MAQUINARIA!H361 -> ACTIVA | D23: =IFERROR(TRIM(MAQUINARIA!C361&" "&MAQUINARIA!E361),"—") -> CAMION VOLTEO 7 M3 | E23: {=IF(B23="",0,IFERROR(ROWS(_xlfn.UNIQUE(_xlfn._xlws.FILTER(Tabla3[PEDIDO],(Tabla3[STATUS]="COTIZANDO")*(Tabla3[NUM ECONOMICO]=B23)*(Tabla3[TEMA]<>"SERVICIO DE FILTROS")))),0))} -> 0 | F23: =IF(B23="",0,COUNTIFS(Tabla3[STATUS],"COTIZANDO",Tabla3[NUM ECONOMICO],B23,Tabla3[TEMA],"<>SERVICIO DE FILTROS")) -> 0 | G23: =IF(B23="",0,SUMIFS(Tabla3[COSTO TOTAL SIN IVA PESOS EN MATCO],Tabla3[STATUS],"COTIZANDO",Tabla3[NUM ECONOMICO],B23,Tabla3[TEMA],"<>SERVICIO DE FILTROS")) -> 0 | H23: =IF(B23="",0,SUMIFS(Tabla3[COSTO TOTAL DOLARES EN HAWTHORNE],Tabla3[STATUS],"COTIZANDO",Tabla3[NUM ECONOMICO],B23,Tabla3[TEMA],"<>SERVICIO DE FILTROS")) -> 0 | I23: =IF(B23="","",_xlfn.LET(_xlpm.totalUSD,SUMIFS(Tabla3[COSTO TOTAL DOLARES EN HAWTHORNE],Tabla3[STATUS],"COTIZANDO",Tabla3[NUM ECONOMICO],B23,Tabla3[TEMA],"<>SERVICIO DE FILTROS"),IF(OR(TC="",_xlpm.totalUSD=0),"—",_xlpm.totalUSD*TC))) -> — | J23: =IF(B23="",0,SUMIFS(Tabla3[COSTO TOTAL DOLARES CTP],Tabla3[STATUS],"COTIZANDO",Tabla3[NUM ECONOMICO],B23,Tabla3[TEMA],"<>SERVICIO DE FILTROS")) -> 0 | K23: =IF(B23="","",_xlfn.LET(_xlpm.totalUSD,SUMIFS(Tabla3[COSTO TOTAL DOLARES CTP],Tabla3[STATUS],"COTIZANDO",Tabla3[NUM ECONOMICO],B23,Tabla3[TEMA],"<>SERVICIO DE FILTROS"),IF(OR(TC="",_xlpm.totalUSD=0),"—",_xlpm.totalUSD*TC))) -> — | L23: {=IF(B23="",0,IFERROR(MAX(_xlfn._xlws.FILTER(Tabla3[DIAS DE ENTREGA TENTATIVO EN MATCO],(Tabla3[STATUS]="COTIZANDO")*(Tabla3[NUM ECONOMICO]=B23)*(Tabla3[TEMA]<>"SERVICIO DE FILTROS"))),0))} -> 0
B24: =MAQUINARIA!B366 -> CV-02 | C24: =MAQUINARIA!H366 -> ACTIVA | D24: =IFERROR(TRIM(MAQUINARIA!C366&" "&MAQUINARIA!E366),"—") -> CAMION VOLTEO 11 M3 | E24: {=IF(B24="",0,IFERROR(ROWS(_xlfn.UNIQUE(_xlfn._xlws.FILTER(Tabla3[PEDIDO],(Tabla3[STATUS]="COTIZANDO")*(Tabla3[NUM ECONOMICO]=B24)*(Tabla3[TEMA]<>"SERVICIO DE FILTROS")))),0))} -> 0 | F24: =IF(B24="",0,COUNTIFS(Tabla3[STATUS],"COTIZANDO",Tabla3[NUM ECONOMICO],B24,Tabla3[TEMA],"<>SERVICIO DE FILTROS")) -> 0 | G24: =IF(B24="",0,SUMIFS(Tabla3[COSTO TOTAL SIN IVA PESOS EN MATCO],Tabla3[STATUS],"COTIZANDO",Tabla3[NUM ECONOMICO],B24,Tabla3[TEMA],"<>SERVICIO DE FILTROS")) -> 0 | H24: =IF(B24="",0,SUMIFS(Tabla3[COSTO TOTAL DOLARES EN HAWTHORNE],Tabla3[STATUS],"COTIZANDO",Tabla3[NUM ECONOMICO],B24,Tabla3[TEMA],"<>SERVICIO DE FILTROS")) -> 0 | I24: =IF(B24="","",_xlfn.LET(_xlpm.totalUSD,SUMIFS(Tabla3[COSTO TOTAL DOLARES EN HAWTHORNE],Tabla3[STATUS],"COTIZANDO",Tabla3[NUM ECONOMICO],B24,Tabla3[TEMA],"<>SERVICIO DE FILTROS"),IF(OR(TC="",_xlpm.totalUSD=0),"—",_xlpm.totalUSD*TC))) -> — | J24: =IF(B24="",0,SUMIFS(Tabla3[COSTO TOTAL DOLARES CTP],Tabla3[STATUS],"COTIZANDO",Tabla3[NUM ECONOMICO],B24,Tabla3[TEMA],"<>SERVICIO DE FILTROS")) -> 0 | K24: =IF(B24="","",_xlfn.LET(_xlpm.totalUSD,SUMIFS(Tabla3[COSTO TOTAL DOLARES CTP],Tabla3[STATUS],"COTIZANDO",Tabla3[NUM ECONOMICO],B24,Tabla3[TEMA],"<>SERVICIO DE FILTROS"),IF(OR(TC="",_xlpm.totalUSD=0),"—",_xlpm.totalUSD*TC))) -> — | L24: {=IF(B24="",0,IFERROR(MAX(_xlfn._xlws.FILTER(Tabla3[DIAS DE ENTREGA TENTATIVO EN MATCO],(Tabla3[STATUS]="COTIZANDO")*(Tabla3[NUM ECONOMICO]=B24)*(Tabla3[TEMA]<>"SERVICIO DE FILTROS"))),0))} -> 0
B25: =MAQUINARIA!B372 -> CV-03 | C25: =MAQUINARIA!H372 -> ACTIVA | D25: =IFERROR(TRIM(MAQUINARIA!C372&" "&MAQUINARIA!E372),"—") -> CAMION VOLTEO 9 M3 | E25: {=IF(B25="",0,IFERROR(ROWS(_xlfn.UNIQUE(_xlfn._xlws.FILTER(Tabla3[PEDIDO],(Tabla3[STATUS]="COTIZANDO")*(Tabla3[NUM ECONOMICO]=B25)*(Tabla3[TEMA]<>"SERVICIO DE FILTROS")))),0))} -> 0 | F25: =IF(B25="",0,COUNTIFS(Tabla3[STATUS],"COTIZANDO",Tabla3[NUM ECONOMICO],B25,Tabla3[TEMA],"<>SERVICIO DE FILTROS")) -> 0 | G25: =IF(B25="",0,SUMIFS(Tabla3[COSTO TOTAL SIN IVA PESOS EN MATCO],Tabla3[STATUS],"COTIZANDO",Tabla3[NUM ECONOMICO],B25,Tabla3[TEMA],"<>SERVICIO DE FILTROS")) -> 0 | H25: =IF(B25="",0,SUMIFS(Tabla3[COSTO TOTAL DOLARES EN HAWTHORNE],Tabla3[STATUS],"COTIZANDO",Tabla3[NUM ECONOMICO],B25,Tabla3[TEMA],"<>SERVICIO DE FILTROS")) -> 0 | I25: =IF(B25="","",_xlfn.LET(_xlpm.totalUSD,SUMIFS(Tabla3[COSTO TOTAL DOLARES EN HAWTHORNE],Tabla3[STATUS],"COTIZANDO",Tabla3[NUM ECONOMICO],B25,Tabla3[TEMA],"<>SERVICIO DE FILTROS"),IF(OR(TC="",_xlpm.totalUSD=0),"—",_xlpm.totalUSD*TC))) -> — | J25: =IF(B25="",0,SUMIFS(Tabla3[COSTO TOTAL DOLARES CTP],Tabla3[STATUS],"COTIZANDO",Tabla3[NUM ECONOMICO],B25,Tabla3[TEMA],"<>SERVICIO DE FILTROS")) -> 0 | K25: =IF(B25="","",_xlfn.LET(_xlpm.totalUSD,SUMIFS(Tabla3[COSTO TOTAL DOLARES CTP],Tabla3[STATUS],"COTIZANDO",Tabla3[NUM ECONOMICO],B25,Tabla3[TEMA],"<>SERVICIO DE FILTROS"),IF(OR(TC="",_xlpm.totalUSD=0),"—",_xlpm.totalUSD*TC))) -> — | L25: {=IF(B25="",0,IFERROR(MAX(_xlfn._xlws.FILTER(Tabla3[DIAS DE ENTREGA TENTATIVO EN MATCO],(Tabla3[STATUS]="COTIZANDO")*(Tabla3[NUM ECONOMICO]=B25)*(Tabla3[TEMA]<>"SERVICIO DE FILTROS"))),0))} -> 0
B26: =MAQUINARIA!B377 -> CV-05 | C26: =MAQUINARIA!H377 -> ACTIVA | D26: =IFERROR(TRIM(MAQUINARIA!C377&" "&MAQUINARIA!E377),"—") -> CAMION VOLTEO 11 M3 | E26: {=IF(B26="",0,IFERROR(ROWS(_xlfn.UNIQUE(_xlfn._xlws.FILTER(Tabla3[PEDIDO],(Tabla3[STATUS]="COTIZANDO")*(Tabla3[NUM ECONOMICO]=B26)*(Tabla3[TEMA]<>"SERVICIO DE FILTROS")))),0))} -> 0 | F26: =IF(B26="",0,COUNTIFS(Tabla3[STATUS],"COTIZANDO",Tabla3[NUM ECONOMICO],B26,Tabla3[TEMA],"<>SERVICIO DE FILTROS")) -> 0 | G26: =IF(B26="",0,SUMIFS(Tabla3[COSTO TOTAL SIN IVA PESOS EN MATCO],Tabla3[STATUS],"COTIZANDO",Tabla3[NUM ECONOMICO],B26,Tabla3[TEMA],"<>SERVICIO DE FILTROS")) -> 0 | H26: =IF(B26="",0,SUMIFS(Tabla3[COSTO TOTAL DOLARES EN HAWTHORNE],Tabla3[STATUS],"COTIZANDO",Tabla3[NUM ECONOMICO],B26,Tabla3[TEMA],"<>SERVICIO DE FILTROS")) -> 0 | I26: =IF(B26="","",_xlfn.LET(_xlpm.totalUSD,SUMIFS(Tabla3[COSTO TOTAL DOLARES EN HAWTHORNE],Tabla3[STATUS],"COTIZANDO",Tabla3[NUM ECONOMICO],B26,Tabla3[TEMA],"<>SERVICIO DE FILTROS"),IF(OR(TC="",_xlpm.totalUSD=0),"—",_xlpm.totalUSD*TC))) -> — | J26: =IF(B26="",0,SUMIFS(Tabla3[COSTO TOTAL DOLARES CTP],Tabla3[STATUS],"COTIZANDO",Tabla3[NUM ECONOMICO],B26,Tabla3[TEMA],"<>SERVICIO DE FILTROS")) -> 0 | K26: =IF(B26="","",_xlfn.LET(_xlpm.totalUSD,SUMIFS(Tabla3[COSTO TOTAL DOLARES CTP],Tabla3[STATUS],"COTIZANDO",Tabla3[NUM ECONOMICO],B26,Tabla3[TEMA],"<>SERVICIO DE FILTROS"),IF(OR(TC="",_xlpm.totalUSD=0),"—",_xlpm.totalUSD*TC))) -> — | L26: {=IF(B26="",0,IFERROR(MAX(_xlfn._xlws.FILTER(Tabla3[DIAS DE ENTREGA TENTATIVO EN MATCO],(Tabla3[STATUS]="COTIZANDO")*(Tabla3[NUM ECONOMICO]=B26)*(Tabla3[TEMA]<>"SERVICIO DE FILTROS"))),0))} -> 0
B27: =MAQUINARIA!B455 -> GR-01 | C27: =MAQUINARIA!H455 -> ACTIVA | D27: =IFERROR(TRIM(MAQUINARIA!C455&" "&MAQUINARIA!E455),"—") -> GRUA FMC LINK-BELT | E27: {=IF(B27="",0,IFERROR(ROWS(_xlfn.UNIQUE(_xlfn._xlws.FILTER(Tabla3[PEDIDO],(Tabla3[STATUS]="COTIZANDO")*(Tabla3[NUM ECONOMICO]=B27)*(Tabla3[TEMA]<>"SERVICIO DE FILTROS")))),0))} -> 0 | F27: =IF(B27="",0,COUNTIFS(Tabla3[STATUS],"COTIZANDO",Tabla3[NUM ECONOMICO],B27,Tabla3[TEMA],"<>SERVICIO DE FILTROS")) -> 0 | G27: =IF(B27="",0,SUMIFS(Tabla3[COSTO TOTAL SIN IVA PESOS EN MATCO],Tabla3[STATUS],"COTIZANDO",Tabla3[NUM ECONOMICO],B27,Tabla3[TEMA],"<>SERVICIO DE FILTROS")) -> 0 | H27: =IF(B27="",0,SUMIFS(Tabla3[COSTO TOTAL DOLARES EN HAWTHORNE],Tabla3[STATUS],"COTIZANDO",Tabla3[NUM ECONOMICO],B27,Tabla3[TEMA],"<>SERVICIO DE FILTROS")) -> 0 | I27: =IF(B27="","",_xlfn.LET(_xlpm.totalUSD,SUMIFS(Tabla3[COSTO TOTAL DOLARES EN HAWTHORNE],Tabla3[STATUS],"COTIZANDO",Tabla3[NUM ECONOMICO],B27,Tabla3[TEMA],"<>SERVICIO DE FILTROS"),IF(OR(TC="",_xlpm.totalUSD=0),"—",_xlpm.totalUSD*TC))) -> — | J27: =IF(B27="",0,SUMIFS(Tabla3[COSTO TOTAL DOLARES CTP],Tabla3[STATUS],"COTIZANDO",Tabla3[NUM ECONOMICO],B27,Tabla3[TEMA],"<>SERVICIO DE FILTROS")) -> 0 | K27: =IF(B27="","",_xlfn.LET(_xlpm.totalUSD,SUMIFS(Tabla3[COSTO TOTAL DOLARES CTP],Tabla3[STATUS],"COTIZANDO",Tabla3[NUM ECONOMICO],B27,Tabla3[TEMA],"<>SERVICIO DE FILTROS"),IF(OR(TC="",_xlpm.totalUSD=0),"—",_xlpm.totalUSD*TC))) -> — | L27: {=IF(B27="",0,IFERROR(MAX(_xlfn._xlws.FILTER(Tabla3[DIAS DE ENTREGA TENTATIVO EN MATCO],(Tabla3[STATUS]="COTIZANDO")*(Tabla3[NUM ECONOMICO]=B27)*(Tabla3[TEMA]<>"SERVICIO DE FILTROS"))),0))} -> 0
B28: =MAQUINARIA!B460 -> GR-02 | C28: =MAQUINARIA!H460 -> ACTIVA | D28: =IFERROR(TRIM(MAQUINARIA!C460&" "&MAQUINARIA!E460),"—") -> GRUA TITAN FORD | E28: {=IF(B28="",0,IFERROR(ROWS(_xlfn.UNIQUE(_xlfn._xlws.FILTER(Tabla3[PEDIDO],(Tabla3[STATUS]="COTIZANDO")*(Tabla3[NUM ECONOMICO]=B28)*(Tabla3[TEMA]<>"SERVICIO DE FILTROS")))),0))} -> 0 | F28: =IF(B28="",0,COUNTIFS(Tabla3[STATUS],"COTIZANDO",Tabla3[NUM ECONOMICO],B28,Tabla3[TEMA],"<>SERVICIO DE FILTROS")) -> 0 | G28: =IF(B28="",0,SUMIFS(Tabla3[COSTO TOTAL SIN IVA PESOS EN MATCO],Tabla3[STATUS],"COTIZANDO",Tabla3[NUM ECONOMICO],B28,Tabla3[TEMA],"<>SERVICIO DE FILTROS")) -> 0 | H28: =IF(B28="",0,SUMIFS(Tabla3[COSTO TOTAL DOLARES EN HAWTHORNE],Tabla3[STATUS],"COTIZANDO",Tabla3[NUM ECONOMICO],B28,Tabla3[TEMA],"<>SERVICIO DE FILTROS")) -> 0 | I28: =IF(B28="","",_xlfn.LET(_xlpm.totalUSD,SUMIFS(Tabla3[COSTO TOTAL DOLARES EN HAWTHORNE],Tabla3[STATUS],"COTIZANDO",Tabla3[NUM ECONOMICO],B28,Tabla3[TEMA],"<>SERVICIO DE FILTROS"),IF(OR(TC="",_xlpm.totalUSD=0),"—",_xlpm.totalUSD*TC))) -> — | J28: =IF(B28="",0,SUMIFS(Tabla3[COSTO TOTAL DOLARES CTP],Tabla3[STATUS],"COTIZANDO",Tabla3[NUM ECONOMICO],B28,Tabla3[TEMA],"<>SERVICIO DE FILTROS")) -> 0 | K28: =IF(B28="","",_xlfn.LET(_xlpm.totalUSD,SUMIFS(Tabla3[COSTO TOTAL DOLARES CTP],Tabla3[STATUS],"COTIZANDO",Tabla3[NUM ECONOMICO],B28,Tabla3[TEMA],"<>SERVICIO DE FILTROS"),IF(OR(TC="",_xlpm.totalUSD=0),"—",_xlpm.totalUSD*TC))) -> — | L28: {=IF(B28="",0,IFERROR(MAX(_xlfn._xlws.FILTER(Tabla3[DIAS DE ENTREGA TENTATIVO EN MATCO],(Tabla3[STATUS]="COTIZANDO")*(Tabla3[NUM ECONOMICO]=B28)*(Tabla3[TEMA]<>"SERVICIO DE FILTROS"))),0))} -> 0
B29: =MAQUINARIA!B497 -> HT-01 | C29: =MAQUINARIA!H497 -> ACTIVA | D29: =IFERROR(TRIM(MAQUINARIA!C497&" "&MAQUINARIA!E497),"—") -> HIDROTRACK DC700 | E29: {=IF(B29="",0,IFERROR(ROWS(_xlfn.UNIQUE(_xlfn._xlws.FILTER(Tabla3[PEDIDO],(Tabla3[STATUS]="COTIZANDO")*(Tabla3[NUM ECONOMICO]=B29)*(Tabla3[TEMA]<>"SERVICIO DE FILTROS")))),0))} -> 0 | F29: =IF(B29="",0,COUNTIFS(Tabla3[STATUS],"COTIZANDO",Tabla3[NUM ECONOMICO],B29,Tabla3[TEMA],"<>SERVICIO DE FILTROS")) -> 0 | G29: =IF(B29="",0,SUMIFS(Tabla3[COSTO TOTAL SIN IVA PESOS EN MATCO],Tabla3[STATUS],"COTIZANDO",Tabla3[NUM ECONOMICO],B29,Tabla3[TEMA],"<>SERVICIO DE FILTROS")) -> 0 | H29: =IF(B29="",0,SUMIFS(Tabla3[COSTO TOTAL DOLARES EN HAWTHORNE],Tabla3[STATUS],"COTIZANDO",Tabla3[NUM ECONOMICO],B29,Tabla3[TEMA],"<>SERVICIO DE FILTROS")) -> 0 | I29: =IF(B29="","",_xlfn.LET(_xlpm.totalUSD,SUMIFS(Tabla3[COSTO TOTAL DOLARES EN HAWTHORNE],Tabla3[STATUS],"COTIZANDO",Tabla3[NUM ECONOMICO],B29,Tabla3[TEMA],"<>SERVICIO DE FILTROS"),IF(OR(TC="",_xlpm.totalUSD=0),"—",_xlpm.totalUSD*TC))) -> — | J29: =IF(B29="",0,SUMIFS(Tabla3[COSTO TOTAL DOLARES CTP],Tabla3[STATUS],"COTIZANDO",Tabla3[NUM ECONOMICO],B29,Tabla3[TEMA],"<>SERVICIO DE FILTROS")) -> 0 | K29: =IF(B29="","",_xlfn.LET(_xlpm.totalUSD,SUMIFS(Tabla3[COSTO TOTAL DOLARES CTP],Tabla3[STATUS],"COTIZANDO",Tabla3[NUM ECONOMICO],B29,Tabla3[TEMA],"<>SERVICIO DE FILTROS"),IF(OR(TC="",_xlpm.totalUSD=0),"—",_xlpm.totalUSD*TC))) -> — | L29: {=IF(B29="",0,IFERROR(MAX(_xlfn._xlws.FILTER(Tabla3[DIAS DE ENTREGA TENTATIVO EN MATCO],(Tabla3[STATUS]="COTIZANDO")*(Tabla3[NUM ECONOMICO]=B29)*(Tabla3[TEMA]<>"SERVICIO DE FILTROS"))),0))} -> 0
B30: =MAQUINARIA!B490 -> MB-01 | C30: =MAQUINARIA!H490 -> ACTIVA | D30: =IFERROR(TRIM(MAQUINARIA!C490&" "&MAQUINARIA!E490),"—") -> MOTOBOMBA PERKIN | E30: {=IF(B30="",0,IFERROR(ROWS(_xlfn.UNIQUE(_xlfn._xlws.FILTER(Tabla3[PEDIDO],(Tabla3[STATUS]="COTIZANDO")*(Tabla3[NUM ECONOMICO]=B30)*(Tabla3[TEMA]<>"SERVICIO DE FILTROS")))),0))} -> 0 | F30: =IF(B30="",0,COUNTIFS(Tabla3[STATUS],"COTIZANDO",Tabla3[NUM ECONOMICO],B30,Tabla3[TEMA],"<>SERVICIO DE FILTROS")) -> 0 | G30: =IF(B30="",0,SUMIFS(Tabla3[COSTO TOTAL SIN IVA PESOS EN MATCO],Tabla3[STATUS],"COTIZANDO",Tabla3[NUM ECONOMICO],B30,Tabla3[TEMA],"<>SERVICIO DE FILTROS")) -> 0 | H30: =IF(B30="",0,SUMIFS(Tabla3[COSTO TOTAL DOLARES EN HAWTHORNE],Tabla3[STATUS],"COTIZANDO",Tabla3[NUM ECONOMICO],B30,Tabla3[TEMA],"<>SERVICIO DE FILTROS")) -> 0 | I30: =IF(B30="","",_xlfn.LET(_xlpm.totalUSD,SUMIFS(Tabla3[COSTO TOTAL DOLARES EN HAWTHORNE],Tabla3[STATUS],"COTIZANDO",Tabla3[NUM ECONOMICO],B30,Tabla3[TEMA],"<>SERVICIO DE FILTROS"),IF(OR(TC="",_xlpm.totalUSD=0),"—",_xlpm.totalUSD*TC))) -> — | J30: =IF(B30="",0,SUMIFS(Tabla3[COSTO TOTAL DOLARES CTP],Tabla3[STATUS],"COTIZANDO",Tabla3[NUM ECONOMICO],B30,Tabla3[TEMA],"<>SERVICIO DE FILTROS")) -> 0 | K30: =IF(B30="","",_xlfn.LET(_xlpm.totalUSD,SUMIFS(Tabla3[COSTO TOTAL DOLARES CTP],Tabla3[STATUS],"COTIZANDO",Tabla3[NUM ECONOMICO],B30,Tabla3[TEMA],"<>SERVICIO DE FILTROS"),IF(OR(TC="",_xlpm.totalUSD=0),"—",_xlpm.totalUSD*TC))) -> — | L30: {=IF(B30="",0,IFERROR(MAX(_xlfn._xlws.FILTER(Tabla3[DIAS DE ENTREGA TENTATIVO EN MATCO],(Tabla3[STATUS]="COTIZANDO")*(Tabla3[NUM ECONOMICO]=B30)*(Tabla3[TEMA]<>"SERVICIO DE FILTROS"))),0))} -> 0
B31: =MAQUINARIA!B491 -> MB-02 | C31: =MAQUINARIA!H491 -> ACTIVA | D31: =IFERROR(TRIM(MAQUINARIA!C491&" "&MAQUINARIA!E491),"—") -> MOTOBOMBA PERKIN | E31: {=IF(B31="",0,IFERROR(ROWS(_xlfn.UNIQUE(_xlfn._xlws.FILTER(Tabla3[PEDIDO],(Tabla3[STATUS]="COTIZANDO")*(Tabla3[NUM ECONOMICO]=B31)*(Tabla3[TEMA]<>"SERVICIO DE FILTROS")))),0))} -> 0 | F31: =IF(B31="",0,COUNTIFS(Tabla3[STATUS],"COTIZANDO",Tabla3[NUM ECONOMICO],B31,Tabla3[TEMA],"<>SERVICIO DE FILTROS")) -> 0 | G31: =IF(B31="",0,SUMIFS(Tabla3[COSTO TOTAL SIN IVA PESOS EN MATCO],Tabla3[STATUS],"COTIZANDO",Tabla3[NUM ECONOMICO],B31,Tabla3[TEMA],"<>SERVICIO DE FILTROS")) -> 0 | H31: =IF(B31="",0,SUMIFS(Tabla3[COSTO TOTAL DOLARES EN HAWTHORNE],Tabla3[STATUS],"COTIZANDO",Tabla3[NUM ECONOMICO],B31,Tabla3[TEMA],"<>SERVICIO DE FILTROS")) -> 0 | I31: =IF(B31="","",_xlfn.LET(_xlpm.totalUSD,SUMIFS(Tabla3[COSTO TOTAL DOLARES EN HAWTHORNE],Tabla3[STATUS],"COTIZANDO",Tabla3[NUM ECONOMICO],B31,Tabla3[TEMA],"<>SERVICIO DE FILTROS"),IF(OR(TC="",_xlpm.totalUSD=0),"—",_xlpm.totalUSD*TC))) -> — | J31: =IF(B31="",0,SUMIFS(Tabla3[COSTO TOTAL DOLARES CTP],Tabla3[STATUS],"COTIZANDO",Tabla3[NUM ECONOMICO],B31,Tabla3[TEMA],"<>SERVICIO DE FILTROS")) -> 0 | K31: =IF(B31="","",_xlfn.LET(_xlpm.totalUSD,SUMIFS(Tabla3[COSTO TOTAL DOLARES CTP],Tabla3[STATUS],"COTIZANDO",Tabla3[NUM ECONOMICO],B31,Tabla3[TEMA],"<>SERVICIO DE FILTROS"),IF(OR(TC="",_xlpm.totalUSD=0),"—",_xlpm.totalUSD*TC))) -> — | L31: {=IF(B31="",0,IFERROR(MAX(_xlfn._xlws.FILTER(Tabla3[DIAS DE ENTREGA TENTATIVO EN MATCO],(Tabla3[STATUS]="COTIZANDO")*(Tabla3[NUM ECONOMICO]=B31)*(Tabla3[TEMA]<>"SERVICIO DE FILTROS"))),0))} -> 0
B32: =MAQUINARIA!B492 -> MB-03 | C32: =MAQUINARIA!H492 -> INACTIVA | D32: =IFERROR(TRIM(MAQUINARIA!C492&" "&MAQUINARIA!E492),"—") -> MOTOBOMBA PERKIN | E32: {=IF(B32="",0,IFERROR(ROWS(_xlfn.UNIQUE(_xlfn._xlws.FILTER(Tabla3[PEDIDO],(Tabla3[STATUS]="COTIZANDO")*(Tabla3[NUM ECONOMICO]=B32)*(Tabla3[TEMA]<>"SERVICIO DE FILTROS")))),0))} -> 0 | F32: =IF(B32="",0,COUNTIFS(Tabla3[STATUS],"COTIZANDO",Tabla3[NUM ECONOMICO],B32,Tabla3[TEMA],"<>SERVICIO DE FILTROS")) -> 0 | G32: =IF(B32="",0,SUMIFS(Tabla3[COSTO TOTAL SIN IVA PESOS EN MATCO],Tabla3[STATUS],"COTIZANDO",Tabla3[NUM ECONOMICO],B32,Tabla3[TEMA],"<>SERVICIO DE FILTROS")) -> 0 | H32: =IF(B32="",0,SUMIFS(Tabla3[COSTO TOTAL DOLARES EN HAWTHORNE],Tabla3[STATUS],"COTIZANDO",Tabla3[NUM ECONOMICO],B32,Tabla3[TEMA],"<>SERVICIO DE FILTROS")) -> 0 | I32: =IF(B32="","",_xlfn.LET(_xlpm.totalUSD,SUMIFS(Tabla3[COSTO TOTAL DOLARES EN HAWTHORNE],Tabla3[STATUS],"COTIZANDO",Tabla3[NUM ECONOMICO],B32,Tabla3[TEMA],"<>SERVICIO DE FILTROS"),IF(OR(TC="",_xlpm.totalUSD=0),"—",_xlpm.totalUSD*TC))) -> — | J32: =IF(B32="",0,SUMIFS(Tabla3[COSTO TOTAL DOLARES CTP],Tabla3[STATUS],"COTIZANDO",Tabla3[NUM ECONOMICO],B32,Tabla3[TEMA],"<>SERVICIO DE FILTROS")) -> 0 | K32: =IF(B32="","",_xlfn.LET(_xlpm.totalUSD,SUMIFS(Tabla3[COSTO TOTAL DOLARES CTP],Tabla3[STATUS],"COTIZANDO",Tabla3[NUM ECONOMICO],B32,Tabla3[TEMA],"<>SERVICIO DE FILTROS"),IF(OR(TC="",_xlpm.totalUSD=0),"—",_xlpm.totalUSD*TC))) -> — | L32: {=IF(B32="",0,IFERROR(MAX(_xlfn._xlws.FILTER(Tabla3[DIAS DE ENTREGA TENTATIVO EN MATCO],(Tabla3[STATUS]="COTIZANDO")*(Tabla3[NUM ECONOMICO]=B32)*(Tabla3[TEMA]<>"SERVICIO DE FILTROS"))),0))} -> 0
B33: =MAQUINARIA!B270 -> MC-01 | C33: =MAQUINARIA!H270 -> ACTIVA | D33: =IFERROR(TRIM(MAQUINARIA!C270&" "&MAQUINARIA!E270),"—") -> TRACTOCOMPACTADOR 815 F | E33: {=IF(B33="",0,IFERROR(ROWS(_xlfn.UNIQUE(_xlfn._xlws.FILTER(Tabla3[PEDIDO],(Tabla3[STATUS]="COTIZANDO")*(Tabla3[NUM ECONOMICO]=B33)*(Tabla3[TEMA]<>"SERVICIO DE FILTROS")))),0))} -> 0 | F33: =IF(B33="",0,COUNTIFS(Tabla3[STATUS],"COTIZANDO",Tabla3[NUM ECONOMICO],B33,Tabla3[TEMA],"<>SERVICIO DE FILTROS")) -> 0 | G33: =IF(B33="",0,SUMIFS(Tabla3[COSTO TOTAL SIN IVA PESOS EN MATCO],Tabla3[STATUS],"COTIZANDO",Tabla3[NUM ECONOMICO],B33,Tabla3[TEMA],"<>SERVICIO DE FILTROS")) -> 0 | H33: =IF(B33="",0,SUMIFS(Tabla3[COSTO TOTAL DOLARES EN HAWTHORNE],Tabla3[STATUS],"COTIZANDO",Tabla3[NUM ECONOMICO],B33,Tabla3[TEMA],"<>SERVICIO DE FILTROS")) -> 0 | I33: =IF(B33="","",_xlfn.LET(_xlpm.totalUSD,SUMIFS(Tabla3[COSTO TOTAL DOLARES EN HAWTHORNE],Tabla3[STATUS],"COTIZANDO",Tabla3[NUM ECONOMICO],B33,Tabla3[TEMA],"<>SERVICIO DE FILTROS"),IF(OR(TC="",_xlpm.totalUSD=0),"—",_xlpm.totalUSD*TC))) -> — | J33: =IF(B33="",0,SUMIFS(Tabla3[COSTO TOTAL DOLARES CTP],Tabla3[STATUS],"COTIZANDO",Tabla3[NUM ECONOMICO],B33,Tabla3[TEMA],"<>SERVICIO DE FILTROS")) -> 0 | K33: =IF(B33="","",_xlfn.LET(_xlpm.totalUSD,SUMIFS(Tabla3[COSTO TOTAL DOLARES CTP],Tabla3[STATUS],"COTIZANDO",Tabla3[NUM ECONOMICO],B33,Tabla3[TEMA],"<>SERVICIO DE FILTROS"),IF(OR(TC="",_xlpm.totalUSD=0),"—",_xlpm.totalUSD*TC))) -> — | L33: {=IF(B33="",0,IFERROR(MAX(_xlfn._xlws.FILTER(Tabla3[DIAS DE ENTREGA TENTATIVO EN MATCO],(Tabla3[STATUS]="COTIZANDO")*(Tabla3[NUM ECONOMICO]=B33)*(Tabla3[TEMA]<>"SERVICIO DE FILTROS"))),0))} -> 0
B34: =MAQUINARIA!B278 -> MC-02 | C34: =MAQUINARIA!H278 -> ACTIVA | D34: =IFERROR(TRIM(MAQUINARIA!C278&" "&MAQUINARIA!E278),"—") -> TRACTOCOMPACTADOR 815 F | E34: {=IF(B34="",0,IFERROR(ROWS(_xlfn.UNIQUE(_xlfn._xlws.FILTER(Tabla3[PEDIDO],(Tabla3[STATUS]="COTIZANDO")*(Tabla3[NUM ECONOMICO]=B34)*(Tabla3[TEMA]<>"SERVICIO DE FILTROS")))),0))} -> 0 | F34: =IF(B34="",0,COUNTIFS(Tabla3[STATUS],"COTIZANDO",Tabla3[NUM ECONOMICO],B34,Tabla3[TEMA],"<>SERVICIO DE FILTROS")) -> 0 | G34: =IF(B34="",0,SUMIFS(Tabla3[COSTO TOTAL SIN IVA PESOS EN MATCO],Tabla3[STATUS],"COTIZANDO",Tabla3[NUM ECONOMICO],B34,Tabla3[TEMA],"<>SERVICIO DE FILTROS")) -> 0 | H34: =IF(B34="",0,SUMIFS(Tabla3[COSTO TOTAL DOLARES EN HAWTHORNE],Tabla3[STATUS],"COTIZANDO",Tabla3[NUM ECONOMICO],B34,Tabla3[TEMA],"<>SERVICIO DE FILTROS")) -> 0 | I34: =IF(B34="","",_xlfn.LET(_xlpm.totalUSD,SUMIFS(Tabla3[COSTO TOTAL DOLARES EN HAWTHORNE],Tabla3[STATUS],"COTIZANDO",Tabla3[NUM ECONOMICO],B34,Tabla3[TEMA],"<>SERVICIO DE FILTROS"),IF(OR(TC="",_xlpm.totalUSD=0),"—",_xlpm.totalUSD*TC))) -> — | J34: =IF(B34="",0,SUMIFS(Tabla3[COSTO TOTAL DOLARES CTP],Tabla3[STATUS],"COTIZANDO",Tabla3[NUM ECONOMICO],B34,Tabla3[TEMA],"<>SERVICIO DE FILTROS")) -> 0 | K34: =IF(B34="","",_xlfn.LET(_xlpm.totalUSD,SUMIFS(Tabla3[COSTO TOTAL DOLARES CTP],Tabla3[STATUS],"COTIZANDO",Tabla3[NUM ECONOMICO],B34,Tabla3[TEMA],"<>SERVICIO DE FILTROS"),IF(OR(TC="",_xlpm.totalUSD=0),"—",_xlpm.totalUSD*TC))) -> — | L34: {=IF(B34="",0,IFERROR(MAX(_xlfn._xlws.FILTER(Tabla3[DIAS DE ENTREGA TENTATIVO EN MATCO],(Tabla3[STATUS]="COTIZANDO")*(Tabla3[NUM ECONOMICO]=B34)*(Tabla3[TEMA]<>"SERVICIO DE FILTROS"))),0))} -> 0
B35: =MAQUINARIA!B281 -> MC-03 | C35: =MAQUINARIA!H281 -> INACTIVA | D35: =IFERROR(TRIM(MAQUINARIA!C281&" "&MAQUINARIA!E281),"—") -> TRACTOCOMPACTADOR 825 C | E35: {=IF(B35="",0,IFERROR(ROWS(_xlfn.UNIQUE(_xlfn._xlws.FILTER(Tabla3[PEDIDO],(Tabla3[STATUS]="COTIZANDO")*(Tabla3[NUM ECONOMICO]=B35)*(Tabla3[TEMA]<>"SERVICIO DE FILTROS")))),0))} -> 0 | F35: =IF(B35="",0,COUNTIFS(Tabla3[STATUS],"COTIZANDO",Tabla3[NUM ECONOMICO],B35,Tabla3[TEMA],"<>SERVICIO DE FILTROS")) -> 0 | G35: =IF(B35="",0,SUMIFS(Tabla3[COSTO TOTAL SIN IVA PESOS EN MATCO],Tabla3[STATUS],"COTIZANDO",Tabla3[NUM ECONOMICO],B35,Tabla3[TEMA],"<>SERVICIO DE FILTROS")) -> 0 | H35: =IF(B35="",0,SUMIFS(Tabla3[COSTO TOTAL DOLARES EN HAWTHORNE],Tabla3[STATUS],"COTIZANDO",Tabla3[NUM ECONOMICO],B35,Tabla3[TEMA],"<>SERVICIO DE FILTROS")) -> 0 | I35: =IF(B35="","",_xlfn.LET(_xlpm.totalUSD,SUMIFS(Tabla3[COSTO TOTAL DOLARES EN HAWTHORNE],Tabla3[STATUS],"COTIZANDO",Tabla3[NUM ECONOMICO],B35,Tabla3[TEMA],"<>SERVICIO DE FILTROS"),IF(OR(TC="",_xlpm.totalUSD=0),"—",_xlpm.totalUSD*TC))) -> — | J35: =IF(B35="",0,SUMIFS(Tabla3[COSTO TOTAL DOLARES CTP],Tabla3[STATUS],"COTIZANDO",Tabla3[NUM ECONOMICO],B35,Tabla3[TEMA],"<>SERVICIO DE FILTROS")) -> 0 | K35: =IF(B35="","",_xlfn.LET(_xlpm.totalUSD,SUMIFS(Tabla3[COSTO TOTAL DOLARES CTP],Tabla3[STATUS],"COTIZANDO",Tabla3[NUM ECONOMICO],B35,Tabla3[TEMA],"<>SERVICIO DE FILTROS"),IF(OR(TC="",_xlpm.totalUSD=0),"—",_xlpm.totalUSD*TC))) -> — | L35: {=IF(B35="",0,IFERROR(MAX(_xlfn._xlws.FILTER(Tabla3[DIAS DE ENTREGA TENTATIVO EN MATCO],(Tabla3[STATUS]="COTIZANDO")*(Tabla3[NUM ECONOMICO]=B35)*(Tabla3[TEMA]<>"SERVICIO DE FILTROS"))),0))} -> 0
B36: =MAQUINARIA!B285 -> MC-04 | C36: =MAQUINARIA!H285 -> ACTIVA | D36: =IFERROR(TRIM(MAQUINARIA!C285&" "&MAQUINARIA!E285),"—") -> TRACTOCOMPACTADOR 825 G | E36: {=IF(B36="",0,IFERROR(ROWS(_xlfn.UNIQUE(_xlfn._xlws.FILTER(Tabla3[PEDIDO],(Tabla3[STATUS]="COTIZANDO")*(Tabla3[NUM ECONOMICO]=B36)*(Tabla3[TEMA]<>"SERVICIO DE FILTROS")))),0))} -> 0 | F36: =IF(B36="",0,COUNTIFS(Tabla3[STATUS],"COTIZANDO",Tabla3[NUM ECONOMICO],B36,Tabla3[TEMA],"<>SERVICIO DE FILTROS")) -> 0 | G36: =IF(B36="",0,SUMIFS(Tabla3[COSTO TOTAL SIN IVA PESOS EN MATCO],Tabla3[STATUS],"COTIZANDO",Tabla3[NUM ECONOMICO],B36,Tabla3[TEMA],"<>SERVICIO DE FILTROS")) -> 0 | H36: =IF(B36="",0,SUMIFS(Tabla3[COSTO TOTAL DOLARES EN HAWTHORNE],Tabla3[STATUS],"COTIZANDO",Tabla3[NUM ECONOMICO],B36,Tabla3[TEMA],"<>SERVICIO DE FILTROS")) -> 0 | I36: =IF(B36="","",_xlfn.LET(_xlpm.totalUSD,SUMIFS(Tabla3[COSTO TOTAL DOLARES EN HAWTHORNE],Tabla3[STATUS],"COTIZANDO",Tabla3[NUM ECONOMICO],B36,Tabla3[TEMA],"<>SERVICIO DE FILTROS"),IF(OR(TC="",_xlpm.totalUSD=0),"—",_xlpm.totalUSD*TC))) -> — | J36: =IF(B36="",0,SUMIFS(Tabla3[COSTO TOTAL DOLARES CTP],Tabla3[STATUS],"COTIZANDO",Tabla3[NUM ECONOMICO],B36,Tabla3[TEMA],"<>SERVICIO DE FILTROS")) -> 0 | K36: =IF(B36="","",_xlfn.LET(_xlpm.totalUSD,SUMIFS(Tabla3[COSTO TOTAL DOLARES CTP],Tabla3[STATUS],"COTIZANDO",Tabla3[NUM ECONOMICO],B36,Tabla3[TEMA],"<>SERVICIO DE FILTROS"),IF(OR(TC="",_xlpm.totalUSD=0),"—",_xlpm.totalUSD*TC))) -> — | L36: {=IF(B36="",0,IFERROR(MAX(_xlfn._xlws.FILTER(Tabla3[DIAS DE ENTREGA TENTATIVO EN MATCO],(Tabla3[STATUS]="COTIZANDO")*(Tabla3[NUM ECONOMICO]=B36)*(Tabla3[TEMA]<>"SERVICIO DE FILTROS"))),0))} -> 0
B37: =MAQUINARIA!B300 -> MC-05 | C37: =MAQUINARIA!H300 -> INACTIVA | D37: =IFERROR(TRIM(MAQUINARIA!C300&" "&MAQUINARIA!E300),"—") -> TRACTOCOMPACTADOR 815 B | E37: {=IF(B37="",0,IFERROR(ROWS(_xlfn.UNIQUE(_xlfn._xlws.FILTER(Tabla3[PEDIDO],(Tabla3[STATUS]="COTIZANDO")*(Tabla3[NUM ECONOMICO]=B37)*(Tabla3[TEMA]<>"SERVICIO DE FILTROS")))),0))} -> 0 | F37: =IF(B37="",0,COUNTIFS(Tabla3[STATUS],"COTIZANDO",Tabla3[NUM ECONOMICO],B37,Tabla3[TEMA],"<>SERVICIO DE FILTROS")) -> 0 | G37: =IF(B37="",0,SUMIFS(Tabla3[COSTO TOTAL SIN IVA PESOS EN MATCO],Tabla3[STATUS],"COTIZANDO",Tabla3[NUM ECONOMICO],B37,Tabla3[TEMA],"<>SERVICIO DE FILTROS")) -> 0 | H37: =IF(B37="",0,SUMIFS(Tabla3[COSTO TOTAL DOLARES EN HAWTHORNE],Tabla3[STATUS],"COTIZANDO",Tabla3[NUM ECONOMICO],B37,Tabla3[TEMA],"<>SERVICIO DE FILTROS")) -> 0 | I37: =IF(B37="","",_xlfn.LET(_xlpm.totalUSD,SUMIFS(Tabla3[COSTO TOTAL DOLARES EN HAWTHORNE],Tabla3[STATUS],"COTIZANDO",Tabla3[NUM ECONOMICO],B37,Tabla3[TEMA],"<>SERVICIO DE FILTROS"),IF(OR(TC="",_xlpm.totalUSD=0),"—",_xlpm.totalUSD*TC))) -> — | J37: =IF(B37="",0,SUMIFS(Tabla3[COSTO TOTAL DOLARES CTP],Tabla3[STATUS],"COTIZANDO",Tabla3[NUM ECONOMICO],B37,Tabla3[TEMA],"<>SERVICIO DE FILTROS")) -> 0 | K37: =IF(B37="","",_xlfn.LET(_xlpm.totalUSD,SUMIFS(Tabla3[COSTO TOTAL DOLARES CTP],Tabla3[STATUS],"COTIZANDO",Tabla3[NUM ECONOMICO],B37,Tabla3[TEMA],"<>SERVICIO DE FILTROS"),IF(OR(TC="",_xlpm.totalUSD=0),"—",_xlpm.totalUSD*TC))) -> — | L37: {=IF(B37="",0,IFERROR(MAX(_xlfn._xlws.FILTER(Tabla3[DIAS DE ENTREGA TENTATIVO EN MATCO],(Tabla3[STATUS]="COTIZANDO")*(Tabla3[NUM ECONOMICO]=B37)*(Tabla3[TEMA]<>"SERVICIO DE FILTROS"))),0))} -> 0
B38: =MAQUINARIA!B307 -> MC-06 | C38: =MAQUINARIA!H307 -> ACTIVA | D38: =IFERROR(TRIM(MAQUINARIA!C307&" "&MAQUINARIA!E307),"—") -> TRACTOCOMPACTADOR 815 | E38: {=IF(B38="",0,IFERROR(ROWS(_xlfn.UNIQUE(_xlfn._xlws.FILTER(Tabla3[PEDIDO],(Tabla3[STATUS]="COTIZANDO")*(Tabla3[NUM ECONOMICO]=B38)*(Tabla3[TEMA]<>"SERVICIO DE FILTROS")))),0))} -> 0 | F38: =IF(B38="",0,COUNTIFS(Tabla3[STATUS],"COTIZANDO",Tabla3[NUM ECONOMICO],B38,Tabla3[TEMA],"<>SERVICIO DE FILTROS")) -> 0 | G38: =IF(B38="",0,SUMIFS(Tabla3[COSTO TOTAL SIN IVA PESOS EN MATCO],Tabla3[STATUS],"COTIZANDO",Tabla3[NUM ECONOMICO],B38,Tabla3[TEMA],"<>SERVICIO DE FILTROS")) -> 0 | H38: =IF(B38="",0,SUMIFS(Tabla3[COSTO TOTAL DOLARES EN HAWTHORNE],Tabla3[STATUS],"COTIZANDO",Tabla3[NUM ECONOMICO],B38,Tabla3[TEMA],"<>SERVICIO DE FILTROS")) -> 0 | I38: =IF(B38="","",_xlfn.LET(_xlpm.totalUSD,SUMIFS(Tabla3[COSTO TOTAL DOLARES EN HAWTHORNE],Tabla3[STATUS],"COTIZANDO",Tabla3[NUM ECONOMICO],B38,Tabla3[TEMA],"<>SERVICIO DE FILTROS"),IF(OR(TC="",_xlpm.totalUSD=0),"—",_xlpm.totalUSD*TC))) -> — | J38: =IF(B38="",0,SUMIFS(Tabla3[COSTO TOTAL DOLARES CTP],Tabla3[STATUS],"COTIZANDO",Tabla3[NUM ECONOMICO],B38,Tabla3[TEMA],"<>SERVICIO DE FILTROS")) -> 0 | K38: =IF(B38="","",_xlfn.LET(_xlpm.totalUSD,SUMIFS(Tabla3[COSTO TOTAL DOLARES CTP],Tabla3[STATUS],"COTIZANDO",Tabla3[NUM ECONOMICO],B38,Tabla3[TEMA],"<>SERVICIO DE FILTROS"),IF(OR(TC="",_xlpm.totalUSD=0),"—",_xlpm.totalUSD*TC))) -> — | L38: {=IF(B38="",0,IFERROR(MAX(_xlfn._xlws.FILTER(Tabla3[DIAS DE ENTREGA TENTATIVO EN MATCO],(Tabla3[STATUS]="COTIZANDO")*(Tabla3[NUM ECONOMICO]=B38)*(Tabla3[TEMA]<>"SERVICIO DE FILTROS"))),0))} -> 0
B39: =MAQUINARIA!B308 -> MCF-01 | C39: =MAQUINARIA!H308 -> ACTIVA | D39: =IFERROR(TRIM(MAQUINARIA!C308&" "&MAQUINARIA!E308),"—") -> CARGADOR FRONTAL 950 GC | E39: {=IF(B39="",0,IFERROR(ROWS(_xlfn.UNIQUE(_xlfn._xlws.FILTER(Tabla3[PEDIDO],(Tabla3[STATUS]="COTIZANDO")*(Tabla3[NUM ECONOMICO]=B39)*(Tabla3[TEMA]<>"SERVICIO DE FILTROS")))),0))} -> 0 | F39: =IF(B39="",0,COUNTIFS(Tabla3[STATUS],"COTIZANDO",Tabla3[NUM ECONOMICO],B39,Tabla3[TEMA],"<>SERVICIO DE FILTROS")) -> 0 | G39: =IF(B39="",0,SUMIFS(Tabla3[COSTO TOTAL SIN IVA PESOS EN MATCO],Tabla3[STATUS],"COTIZANDO",Tabla3[NUM ECONOMICO],B39,Tabla3[TEMA],"<>SERVICIO DE FILTROS")) -> 0 | H39: =IF(B39="",0,SUMIFS(Tabla3[COSTO TOTAL DOLARES EN HAWTHORNE],Tabla3[STATUS],"COTIZANDO",Tabla3[NUM ECONOMICO],B39,Tabla3[TEMA],"<>SERVICIO DE FILTROS")) -> 0 | I39: =IF(B39="","",_xlfn.LET(_xlpm.totalUSD,SUMIFS(Tabla3[COSTO TOTAL DOLARES EN HAWTHORNE],Tabla3[STATUS],"COTIZANDO",Tabla3[NUM ECONOMICO],B39,Tabla3[TEMA],"<>SERVICIO DE FILTROS"),IF(OR(TC="",_xlpm.totalUSD=0),"—",_xlpm.totalUSD*TC))) -> — | J39: =IF(B39="",0,SUMIFS(Tabla3[COSTO TOTAL DOLARES CTP],Tabla3[STATUS],"COTIZANDO",Tabla3[NUM ECONOMICO],B39,Tabla3[TEMA],"<>SERVICIO DE FILTROS")) -> 0 | K39: =IF(B39="","",_xlfn.LET(_xlpm.totalUSD,SUMIFS(Tabla3[COSTO TOTAL DOLARES CTP],Tabla3[STATUS],"COTIZANDO",Tabla3[NUM ECONOMICO],B39,Tabla3[TEMA],"<>SERVICIO DE FILTROS"),IF(OR(TC="",_xlpm.totalUSD=0),"—",_xlpm.totalUSD*TC))) -> — | L39: {=IF(B39="",0,IFERROR(MAX(_xlfn._xlws.FILTER(Tabla3[DIAS DE ENTREGA TENTATIVO EN MATCO],(Tabla3[STATUS]="COTIZANDO")*(Tabla3[NUM ECONOMICO]=B39)*(Tabla3[TEMA]<>"SERVICIO DE FILTROS"))),0))} -> 0
B40: =MAQUINARIA!B110 -> ME-02 | C40: =MAQUINARIA!H110 -> INACTIVA | D40: =IFERROR(TRIM(MAQUINARIA!C110&" "&MAQUINARIA!E110),"—") -> ESCREPA 631 E | E40: {=IF(B40="",0,IFERROR(ROWS(_xlfn.UNIQUE(_xlfn._xlws.FILTER(Tabla3[PEDIDO],(Tabla3[STATUS]="COTIZANDO")*(Tabla3[NUM ECONOMICO]=B40)*(Tabla3[TEMA]<>"SERVICIO DE FILTROS")))),0))} -> 0 | F40: =IF(B40="",0,COUNTIFS(Tabla3[STATUS],"COTIZANDO",Tabla3[NUM ECONOMICO],B40,Tabla3[TEMA],"<>SERVICIO DE FILTROS")) -> 0 | G40: =IF(B40="",0,SUMIFS(Tabla3[COSTO TOTAL SIN IVA PESOS EN MATCO],Tabla3[STATUS],"COTIZANDO",Tabla3[NUM ECONOMICO],B40,Tabla3[TEMA],"<>SERVICIO DE FILTROS")) -> 0 | H40: =IF(B40="",0,SUMIFS(Tabla3[COSTO TOTAL DOLARES EN HAWTHORNE],Tabla3[STATUS],"COTIZANDO",Tabla3[NUM ECONOMICO],B40,Tabla3[TEMA],"<>SERVICIO DE FILTROS")) -> 0 | I40: =IF(B40="","",_xlfn.LET(_xlpm.totalUSD,SUMIFS(Tabla3[COSTO TOTAL DOLARES EN HAWTHORNE],Tabla3[STATUS],"COTIZANDO",Tabla3[NUM ECONOMICO],B40,Tabla3[TEMA],"<>SERVICIO DE FILTROS"),IF(OR(TC="",_xlpm.totalUSD=0),"—",_xlpm.totalUSD*TC))) -> — | J40: =IF(B40="",0,SUMIFS(Tabla3[COSTO TOTAL DOLARES CTP],Tabla3[STATUS],"COTIZANDO",Tabla3[NUM ECONOMICO],B40,Tabla3[TEMA],"<>SERVICIO DE FILTROS")) -> 0 | K40: =IF(B40="","",_xlfn.LET(_xlpm.totalUSD,SUMIFS(Tabla3[COSTO TOTAL DOLARES CTP],Tabla3[STATUS],"COTIZANDO",Tabla3[NUM ECONOMICO],B40,Tabla3[TEMA],"<>SERVICIO DE FILTROS"),IF(OR(TC="",_xlpm.totalUSD=0),"—",_xlpm.totalUSD*TC))) -> — | L40: {=IF(B40="",0,IFERROR(MAX(_xlfn._xlws.FILTER(Tabla3[DIAS DE ENTREGA TENTATIVO EN MATCO],(Tabla3[STATUS]="COTIZANDO")*(Tabla3[NUM ECONOMICO]=B40)*(Tabla3[TEMA]<>"SERVICIO DE FILTROS"))),0))} -> 0
B41: =MAQUINARIA!B114 -> ME-03 | C41: =MAQUINARIA!H114 -> ACTIVA | D41: =IFERROR(TRIM(MAQUINARIA!C114&" "&MAQUINARIA!E114),"—") -> ESCREPA 631 E | E41: {=IF(B41="",0,IFERROR(ROWS(_xlfn.UNIQUE(_xlfn._xlws.FILTER(Tabla3[PEDIDO],(Tabla3[STATUS]="COTIZANDO")*(Tabla3[NUM ECONOMICO]=B41)*(Tabla3[TEMA]<>"SERVICIO DE FILTROS")))),0))} -> 0 | F41: =IF(B41="",0,COUNTIFS(Tabla3[STATUS],"COTIZANDO",Tabla3[NUM ECONOMICO],B41,Tabla3[TEMA],"<>SERVICIO DE FILTROS")) -> 0 | G41: =IF(B41="",0,SUMIFS(Tabla3[COSTO TOTAL SIN IVA PESOS EN MATCO],Tabla3[STATUS],"COTIZANDO",Tabla3[NUM ECONOMICO],B41,Tabla3[TEMA],"<>SERVICIO DE FILTROS")) -> 0 | H41: =IF(B41="",0,SUMIFS(Tabla3[COSTO TOTAL DOLARES EN HAWTHORNE],Tabla3[STATUS],"COTIZANDO",Tabla3[NUM ECONOMICO],B41,Tabla3[TEMA],"<>SERVICIO DE FILTROS")) -> 0 | I41: =IF(B41="","",_xlfn.LET(_xlpm.totalUSD,SUMIFS(Tabla3[COSTO TOTAL DOLARES EN HAWTHORNE],Tabla3[STATUS],"COTIZANDO",Tabla3[NUM ECONOMICO],B41,Tabla3[TEMA],"<>SERVICIO DE FILTROS"),IF(OR(TC="",_xlpm.totalUSD=0),"—",_xlpm.totalUSD*TC))) -> — | J41: =IF(B41="",0,SUMIFS(Tabla3[COSTO TOTAL DOLARES CTP],Tabla3[STATUS],"COTIZANDO",Tabla3[NUM ECONOMICO],B41,Tabla3[TEMA],"<>SERVICIO DE FILTROS")) -> 0 | K41: =IF(B41="","",_xlfn.LET(_xlpm.totalUSD,SUMIFS(Tabla3[COSTO TOTAL DOLARES CTP],Tabla3[STATUS],"COTIZANDO",Tabla3[NUM ECONOMICO],B41,Tabla3[TEMA],"<>SERVICIO DE FILTROS"),IF(OR(TC="",_xlpm.totalUSD=0),"—",_xlpm.totalUSD*TC))) -> — | L41: {=IF(B41="",0,IFERROR(MAX(_xlfn._xlws.FILTER(Tabla3[DIAS DE ENTREGA TENTATIVO EN MATCO],(Tabla3[STATUS]="COTIZANDO")*(Tabla3[NUM ECONOMICO]=B41)*(Tabla3[TEMA]<>"SERVICIO DE FILTROS"))),0))} -> 0
B42: =MAQUINARIA!B117 -> ME-05 | C42: =MAQUINARIA!H117 -> ACTIVA | D42: =IFERROR(TRIM(MAQUINARIA!C117&" "&MAQUINARIA!E117),"—") -> ESCREPA 631 E | E42: {=IF(B42="",0,IFERROR(ROWS(_xlfn.UNIQUE(_xlfn._xlws.FILTER(Tabla3[PEDIDO],(Tabla3[STATUS]="COTIZANDO")*(Tabla3[NUM ECONOMICO]=B42)*(Tabla3[TEMA]<>"SERVICIO DE FILTROS")))),0))} -> 0 | F42: =IF(B42="",0,COUNTIFS(Tabla3[STATUS],"COTIZANDO",Tabla3[NUM ECONOMICO],B42,Tabla3[TEMA],"<>SERVICIO DE FILTROS")) -> 0 | G42: =IF(B42="",0,SUMIFS(Tabla3[COSTO TOTAL SIN IVA PESOS EN MATCO],Tabla3[STATUS],"COTIZANDO",Tabla3[NUM ECONOMICO],B42,Tabla3[TEMA],"<>SERVICIO DE FILTROS")) -> 0 | H42: =IF(B42="",0,SUMIFS(Tabla3[COSTO TOTAL DOLARES EN HAWTHORNE],Tabla3[STATUS],"COTIZANDO",Tabla3[NUM ECONOMICO],B42,Tabla3[TEMA],"<>SERVICIO DE FILTROS")) -> 0 | I42: =IF(B42="","",_xlfn.LET(_xlpm.totalUSD,SUMIFS(Tabla3[COSTO TOTAL DOLARES EN HAWTHORNE],Tabla3[STATUS],"COTIZANDO",Tabla3[NUM ECONOMICO],B42,Tabla3[TEMA],"<>SERVICIO DE FILTROS"),IF(OR(TC="",_xlpm.totalUSD=0),"—",_xlpm.totalUSD*TC))) -> — | J42: =IF(B42="",0,SUMIFS(Tabla3[COSTO TOTAL DOLARES CTP],Tabla3[STATUS],"COTIZANDO",Tabla3[NUM ECONOMICO],B42,Tabla3[TEMA],"<>SERVICIO DE FILTROS")) -> 0 | K42: =IF(B42="","",_xlfn.LET(_xlpm.totalUSD,SUMIFS(Tabla3[COSTO TOTAL DOLARES CTP],Tabla3[STATUS],"COTIZANDO",Tabla3[NUM ECONOMICO],B42,Tabla3[TEMA],"<>SERVICIO DE FILTROS"),IF(OR(TC="",_xlpm.totalUSD=0),"—",_xlpm.totalUSD*TC))) -> — | L42: {=IF(B42="",0,IFERROR(MAX(_xlfn._xlws.FILTER(Tabla3[DIAS DE ENTREGA TENTATIVO EN MATCO],(Tabla3[STATUS]="COTIZANDO")*(Tabla3[NUM ECONOMICO]=B42)*(Tabla3[TEMA]<>"SERVICIO DE FILTROS"))),0))} -> 0
B43: =MAQUINARIA!B124 -> ME-07 | C43: =MAQUINARIA!H124 -> INACTIVA | D43: =IFERROR(TRIM(MAQUINARIA!C124&" "&MAQUINARIA!E124),"—") -> ESCREPA 631 D | E43: {=IF(B43="",0,IFERROR(ROWS(_xlfn.UNIQUE(_xlfn._xlws.FILTER(Tabla3[PEDIDO],(Tabla3[STATUS]="COTIZANDO")*(Tabla3[NUM ECONOMICO]=B43)*(Tabla3[TEMA]<>"SERVICIO DE FILTROS")))),0))} -> 0 | F43: =IF(B43="",0,COUNTIFS(Tabla3[STATUS],"COTIZANDO",Tabla3[NUM ECONOMICO],B43,Tabla3[TEMA],"<>SERVICIO DE FILTROS")) -> 0 | G43: =IF(B43="",0,SUMIFS(Tabla3[COSTO TOTAL SIN IVA PESOS EN MATCO],Tabla3[STATUS],"COTIZANDO",Tabla3[NUM ECONOMICO],B43,Tabla3[TEMA],"<>SERVICIO DE FILTROS")) -> 0 | H43: =IF(B43="",0,SUMIFS(Tabla3[COSTO TOTAL DOLARES EN HAWTHORNE],Tabla3[STATUS],"COTIZANDO",Tabla3[NUM ECONOMICO],B43,Tabla3[TEMA],"<>SERVICIO DE FILTROS")) -> 0 | I43: =IF(B43="","",_xlfn.LET(_xlpm.totalUSD,SUMIFS(Tabla3[COSTO TOTAL DOLARES EN HAWTHORNE],Tabla3[STATUS],"COTIZANDO",Tabla3[NUM ECONOMICO],B43,Tabla3[TEMA],"<>SERVICIO DE FILTROS"),IF(OR(TC="",_xlpm.totalUSD=0),"—",_xlpm.totalUSD*TC))) -> — | J43: =IF(B43="",0,SUMIFS(Tabla3[COSTO TOTAL DOLARES CTP],Tabla3[STATUS],"COTIZANDO",Tabla3[NUM ECONOMICO],B43,Tabla3[TEMA],"<>SERVICIO DE FILTROS")) -> 0 | K43: =IF(B43="","",_xlfn.LET(_xlpm.totalUSD,SUMIFS(Tabla3[COSTO TOTAL DOLARES CTP],Tabla3[STATUS],"COTIZANDO",Tabla3[NUM ECONOMICO],B43,Tabla3[TEMA],"<>SERVICIO DE FILTROS"),IF(OR(TC="",_xlpm.totalUSD=0),"—",_xlpm.totalUSD*TC))) -> — | L43: {=IF(B43="",0,IFERROR(MAX(_xlfn._xlws.FILTER(Tabla3[DIAS DE ENTREGA TENTATIVO EN MATCO],(Tabla3[STATUS]="COTIZANDO")*(Tabla3[NUM ECONOMICO]=B43)*(Tabla3[TEMA]<>"SERVICIO DE FILTROS"))),0))} -> 0
B44: =MAQUINARIA!B128 -> ME-08 | C44: =MAQUINARIA!H128 -> INACTIVA | D44: =IFERROR(TRIM(MAQUINARIA!C128&" "&MAQUINARIA!E128),"—") -> ESCREPA 631 E | E44: {=IF(B44="",0,IFERROR(ROWS(_xlfn.UNIQUE(_xlfn._xlws.FILTER(Tabla3[PEDIDO],(Tabla3[STATUS]="COTIZANDO")*(Tabla3[NUM ECONOMICO]=B44)*(Tabla3[TEMA]<>"SERVICIO DE FILTROS")))),0))} -> 0 | F44: =IF(B44="",0,COUNTIFS(Tabla3[STATUS],"COTIZANDO",Tabla3[NUM ECONOMICO],B44,Tabla3[TEMA],"<>SERVICIO DE FILTROS")) -> 0 | G44: =IF(B44="",0,SUMIFS(Tabla3[COSTO TOTAL SIN IVA PESOS EN MATCO],Tabla3[STATUS],"COTIZANDO",Tabla3[NUM ECONOMICO],B44,Tabla3[TEMA],"<>SERVICIO DE FILTROS")) -> 0 | H44: =IF(B44="",0,SUMIFS(Tabla3[COSTO TOTAL DOLARES EN HAWTHORNE],Tabla3[STATUS],"COTIZANDO",Tabla3[NUM ECONOMICO],B44,Tabla3[TEMA],"<>SERVICIO DE FILTROS")) -> 0 | I44: =IF(B44="","",_xlfn.LET(_xlpm.totalUSD,SUMIFS(Tabla3[COSTO TOTAL DOLARES EN HAWTHORNE],Tabla3[STATUS],"COTIZANDO",Tabla3[NUM ECONOMICO],B44,Tabla3[TEMA],"<>SERVICIO DE FILTROS"),IF(OR(TC="",_xlpm.totalUSD=0),"—",_xlpm.totalUSD*TC))) -> — | J44: =IF(B44="",0,SUMIFS(Tabla3[COSTO TOTAL DOLARES CTP],Tabla3[STATUS],"COTIZANDO",Tabla3[NUM ECONOMICO],B44,Tabla3[TEMA],"<>SERVICIO DE FILTROS")) -> 0 | K44: =IF(B44="","",_xlfn.LET(_xlpm.totalUSD,SUMIFS(Tabla3[COSTO TOTAL DOLARES CTP],Tabla3[STATUS],"COTIZANDO",Tabla3[NUM ECONOMICO],B44,Tabla3[TEMA],"<>SERVICIO DE FILTROS"),IF(OR(TC="",_xlpm.totalUSD=0),"—",_xlpm.totalUSD*TC))) -> — | L44: {=IF(B44="",0,IFERROR(MAX(_xlfn._xlws.FILTER(Tabla3[DIAS DE ENTREGA TENTATIVO EN MATCO],(Tabla3[STATUS]="COTIZANDO")*(Tabla3[NUM ECONOMICO]=B44)*(Tabla3[TEMA]<>"SERVICIO DE FILTROS"))),0))} -> 0
B45: =MAQUINARIA!B134 -> ME-09 | C45: =MAQUINARIA!H134 -> ACTIVA | D45: =IFERROR(TRIM(MAQUINARIA!C134&" "&MAQUINARIA!E134),"—") -> ESCREPA 631 E | E45: {=IF(B45="",0,IFERROR(ROWS(_xlfn.UNIQUE(_xlfn._xlws.FILTER(Tabla3[PEDIDO],(Tabla3[STATUS]="COTIZANDO")*(Tabla3[NUM ECONOMICO]=B45)*(Tabla3[TEMA]<>"SERVICIO DE FILTROS")))),0))} -> 0 | F45: =IF(B45="",0,COUNTIFS(Tabla3[STATUS],"COTIZANDO",Tabla3[NUM ECONOMICO],B45,Tabla3[TEMA],"<>SERVICIO DE FILTROS")) -> 0 | G45: =IF(B45="",0,SUMIFS(Tabla3[COSTO TOTAL SIN IVA PESOS EN MATCO],Tabla3[STATUS],"COTIZANDO",Tabla3[NUM ECONOMICO],B45,Tabla3[TEMA],"<>SERVICIO DE FILTROS")) -> 0 | H45: =IF(B45="",0,SUMIFS(Tabla3[COSTO TOTAL DOLARES EN HAWTHORNE],Tabla3[STATUS],"COTIZANDO",Tabla3[NUM ECONOMICO],B45,Tabla3[TEMA],"<>SERVICIO DE FILTROS")) -> 0 | I45: =IF(B45="","",_xlfn.LET(_xlpm.totalUSD,SUMIFS(Tabla3[COSTO TOTAL DOLARES EN HAWTHORNE],Tabla3[STATUS],"COTIZANDO",Tabla3[NUM ECONOMICO],B45,Tabla3[TEMA],"<>SERVICIO DE FILTROS"),IF(OR(TC="",_xlpm.totalUSD=0),"—",_xlpm.totalUSD*TC))) -> — | J45: =IF(B45="",0,SUMIFS(Tabla3[COSTO TOTAL DOLARES CTP],Tabla3[STATUS],"COTIZANDO",Tabla3[NUM ECONOMICO],B45,Tabla3[TEMA],"<>SERVICIO DE FILTROS")) -> 0 | K45: =IF(B45="","",_xlfn.LET(_xlpm.totalUSD,SUMIFS(Tabla3[COSTO TOTAL DOLARES CTP],Tabla3[STATUS],"COTIZANDO",Tabla3[NUM ECONOMICO],B45,Tabla3[TEMA],"<>SERVICIO DE FILTROS"),IF(OR(TC="",_xlpm.totalUSD=0),"—",_xlpm.totalUSD*TC))) -> — | L45: {=IF(B45="",0,IFERROR(MAX(_xlfn._xlws.FILTER(Tabla3[DIAS DE ENTREGA TENTATIVO EN MATCO],(Tabla3[STATUS]="COTIZANDO")*(Tabla3[NUM ECONOMICO]=B45)*(Tabla3[TEMA]<>"SERVICIO DE FILTROS"))),0))} -> 0
B46: =MAQUINARIA!B142 -> ME-11 | C46: =MAQUINARIA!H142 -> INACTIVA | D46: =IFERROR(TRIM(MAQUINARIA!C142&" "&MAQUINARIA!E142),"—") -> ESCREPA 631 E | E46: {=IF(B46="",0,IFERROR(ROWS(_xlfn.UNIQUE(_xlfn._xlws.FILTER(Tabla3[PEDIDO],(Tabla3[STATUS]="COTIZANDO")*(Tabla3[NUM ECONOMICO]=B46)*(Tabla3[TEMA]<>"SERVICIO DE FILTROS")))),0))} -> 1 | F46: =IF(B46="",0,COUNTIFS(Tabla3[STATUS],"COTIZANDO",Tabla3[NUM ECONOMICO],B46,Tabla3[TEMA],"<>SERVICIO DE FILTROS")) -> 170 | G46: =IF(B46="",0,SUMIFS(Tabla3[COSTO TOTAL SIN IVA PESOS EN MATCO],Tabla3[STATUS],"COTIZANDO",Tabla3[NUM ECONOMICO],B46,Tabla3[TEMA],"<>SERVICIO DE FILTROS")) -> 675447.06 | H46: =IF(B46="",0,SUMIFS(Tabla3[COSTO TOTAL DOLARES EN HAWTHORNE],Tabla3[STATUS],"COTIZANDO",Tabla3[NUM ECONOMICO],B46,Tabla3[TEMA],"<>SERVICIO DE FILTROS")) -> 0 | I46: =IF(B46="","",_xlfn.LET(_xlpm.totalUSD,SUMIFS(Tabla3[COSTO TOTAL DOLARES EN HAWTHORNE],Tabla3[STATUS],"COTIZANDO",Tabla3[NUM ECONOMICO],B46,Tabla3[TEMA],"<>SERVICIO DE FILTROS"),IF(OR(TC="",_xlpm.totalUSD=0),"—",_xlpm.totalUSD*TC))) -> — | J46: =IF(B46="",0,SUMIFS(Tabla3[COSTO TOTAL DOLARES CTP],Tabla3[STATUS],"COTIZANDO",Tabla3[NUM ECONOMICO],B46,Tabla3[TEMA],"<>SERVICIO DE FILTROS")) -> 0 | K46: =IF(B46="","",_xlfn.LET(_xlpm.totalUSD,SUMIFS(Tabla3[COSTO TOTAL DOLARES CTP],Tabla3[STATUS],"COTIZANDO",Tabla3[NUM ECONOMICO],B46,Tabla3[TEMA],"<>SERVICIO DE FILTROS"),IF(OR(TC="",_xlpm.totalUSD=0),"—",_xlpm.totalUSD*TC))) -> — | L46: {=IF(B46="",0,IFERROR(MAX(_xlfn._xlws.FILTER(Tabla3[DIAS DE ENTREGA TENTATIVO EN MATCO],(Tabla3[STATUS]="COTIZANDO")*(Tabla3[NUM ECONOMICO]=B46)*(Tabla3[TEMA]<>"SERVICIO DE FILTROS"))),0))} -> 0
B47: =MAQUINARIA!B147 -> ME-12 | C47: =MAQUINARIA!H147 -> ACTIVA | D47: =IFERROR(TRIM(MAQUINARIA!C147&" "&MAQUINARIA!E147),"—") -> ESCREPA 631 E | E47: {=IF(B47="",0,IFERROR(ROWS(_xlfn.UNIQUE(_xlfn._xlws.FILTER(Tabla3[PEDIDO],(Tabla3[STATUS]="COTIZANDO")*(Tabla3[NUM ECONOMICO]=B47)*(Tabla3[TEMA]<>"SERVICIO DE FILTROS")))),0))} -> 0 | F47: =IF(B47="",0,COUNTIFS(Tabla3[STATUS],"COTIZANDO",Tabla3[NUM ECONOMICO],B47,Tabla3[TEMA],"<>SERVICIO DE FILTROS")) -> 0 | G47: =IF(B47="",0,SUMIFS(Tabla3[COSTO TOTAL SIN IVA PESOS EN MATCO],Tabla3[STATUS],"COTIZANDO",Tabla3[NUM ECONOMICO],B47,Tabla3[TEMA],"<>SERVICIO DE FILTROS")) -> 0 | H47: =IF(B47="",0,SUMIFS(Tabla3[COSTO TOTAL DOLARES EN HAWTHORNE],Tabla3[STATUS],"COTIZANDO",Tabla3[NUM ECONOMICO],B47,Tabla3[TEMA],"<>SERVICIO DE FILTROS")) -> 0 | I47: =IF(B47="","",_xlfn.LET(_xlpm.totalUSD,SUMIFS(Tabla3[COSTO TOTAL DOLARES EN HAWTHORNE],Tabla3[STATUS],"COTIZANDO",Tabla3[NUM ECONOMICO],B47,Tabla3[TEMA],"<>SERVICIO DE FILTROS"),IF(OR(TC="",_xlpm.totalUSD=0),"—",_xlpm.totalUSD*TC))) -> — | J47: =IF(B47="",0,SUMIFS(Tabla3[COSTO TOTAL DOLARES CTP],Tabla3[STATUS],"COTIZANDO",Tabla3[NUM ECONOMICO],B47,Tabla3[TEMA],"<>SERVICIO DE FILTROS")) -> 0 | K47: =IF(B47="","",_xlfn.LET(_xlpm.totalUSD,SUMIFS(Tabla3[COSTO TOTAL DOLARES CTP],Tabla3[STATUS],"COTIZANDO",Tabla3[NUM ECONOMICO],B47,Tabla3[TEMA],"<>SERVICIO DE FILTROS"),IF(OR(TC="",_xlpm.totalUSD=0),"—",_xlpm.totalUSD*TC))) -> — | L47: {=IF(B47="",0,IFERROR(MAX(_xlfn._xlws.FILTER(Tabla3[DIAS DE ENTREGA TENTATIVO EN MATCO],(Tabla3[STATUS]="COTIZANDO")*(Tabla3[NUM ECONOMICO]=B47)*(Tabla3[TEMA]<>"SERVICIO DE FILTROS"))),0))} -> 0
B48: =MAQUINARIA!B154 -> ME-14 | C48: =MAQUINARIA!H154 -> ACTIVA | D48: =IFERROR(TRIM(MAQUINARIA!C154&" "&MAQUINARIA!E154),"—") -> ESCREPA 631 E | E48: {=IF(B48="",0,IFERROR(ROWS(_xlfn.UNIQUE(_xlfn._xlws.FILTER(Tabla3[PEDIDO],(Tabla3[STATUS]="COTIZANDO")*(Tabla3[NUM ECONOMICO]=B48)*(Tabla3[TEMA]<>"SERVICIO DE FILTROS")))),0))} -> 0 | F48: =IF(B48="",0,COUNTIFS(Tabla3[STATUS],"COTIZANDO",Tabla3[NUM ECONOMICO],B48,Tabla3[TEMA],"<>SERVICIO DE FILTROS")) -> 0 | G48: =IF(B48="",0,SUMIFS(Tabla3[COSTO TOTAL SIN IVA PESOS EN MATCO],Tabla3[STATUS],"COTIZANDO",Tabla3[NUM ECONOMICO],B48,Tabla3[TEMA],"<>SERVICIO DE FILTROS")) -> 0 | H48: =IF(B48="",0,SUMIFS(Tabla3[COSTO TOTAL DOLARES EN HAWTHORNE],Tabla3[STATUS],"COTIZANDO",Tabla3[NUM ECONOMICO],B48,Tabla3[TEMA],"<>SERVICIO DE FILTROS")) -> 0 | I48: =IF(B48="","",_xlfn.LET(_xlpm.totalUSD,SUMIFS(Tabla3[COSTO TOTAL DOLARES EN HAWTHORNE],Tabla3[STATUS],"COTIZANDO",Tabla3[NUM ECONOMICO],B48,Tabla3[TEMA],"<>SERVICIO DE FILTROS"),IF(OR(TC="",_xlpm.totalUSD=0),"—",_xlpm.totalUSD*TC))) -> — | J48: =IF(B48="",0,SUMIFS(Tabla3[COSTO TOTAL DOLARES CTP],Tabla3[STATUS],"COTIZANDO",Tabla3[NUM ECONOMICO],B48,Tabla3[TEMA],"<>SERVICIO DE FILTROS")) -> 0 | K48: =IF(B48="","",_xlfn.LET(_xlpm.totalUSD,SUMIFS(Tabla3[COSTO TOTAL DOLARES CTP],Tabla3[STATUS],"COTIZANDO",Tabla3[NUM ECONOMICO],B48,Tabla3[TEMA],"<>SERVICIO DE FILTROS"),IF(OR(TC="",_xlpm.totalUSD=0),"—",_xlpm.totalUSD*TC))) -> — | L48: {=IF(B48="",0,IFERROR(MAX(_xlfn._xlws.FILTER(Tabla3[DIAS DE ENTREGA TENTATIVO EN MATCO],(Tabla3[STATUS]="COTIZANDO")*(Tabla3[NUM ECONOMICO]=B48)*(Tabla3[TEMA]<>"SERVICIO DE FILTROS"))),0))} -> 0
B49: =MAQUINARIA!B156 -> ME-15 | C49: =MAQUINARIA!H156 -> INACTIVA | D49: =IFERROR(TRIM(MAQUINARIA!C156&" "&MAQUINARIA!E156),"—") -> ESCREPA 631 E | E49: {=IF(B49="",0,IFERROR(ROWS(_xlfn.UNIQUE(_xlfn._xlws.FILTER(Tabla3[PEDIDO],(Tabla3[STATUS]="COTIZANDO")*(Tabla3[NUM ECONOMICO]=B49)*(Tabla3[TEMA]<>"SERVICIO DE FILTROS")))),0))} -> 1 | F49: =IF(B49="",0,COUNTIFS(Tabla3[STATUS],"COTIZANDO",Tabla3[NUM ECONOMICO],B49,Tabla3[TEMA],"<>SERVICIO DE FILTROS")) -> 170 | G49: =IF(B49="",0,SUMIFS(Tabla3[COSTO TOTAL SIN IVA PESOS EN MATCO],Tabla3[STATUS],"COTIZANDO",Tabla3[NUM ECONOMICO],B49,Tabla3[TEMA],"<>SERVICIO DE FILTROS")) -> 675447.06 | H49: =IF(B49="",0,SUMIFS(Tabla3[COSTO TOTAL DOLARES EN HAWTHORNE],Tabla3[STATUS],"COTIZANDO",Tabla3[NUM ECONOMICO],B49,Tabla3[TEMA],"<>SERVICIO DE FILTROS")) -> 0 | I49: =IF(B49="","",_xlfn.LET(_xlpm.totalUSD,SUMIFS(Tabla3[COSTO TOTAL DOLARES EN HAWTHORNE],Tabla3[STATUS],"COTIZANDO",Tabla3[NUM ECONOMICO],B49,Tabla3[TEMA],"<>SERVICIO DE FILTROS"),IF(OR(TC="",_xlpm.totalUSD=0),"—",_xlpm.totalUSD*TC))) -> — | J49: =IF(B49="",0,SUMIFS(Tabla3[COSTO TOTAL DOLARES CTP],Tabla3[STATUS],"COTIZANDO",Tabla3[NUM ECONOMICO],B49,Tabla3[TEMA],"<>SERVICIO DE FILTROS")) -> 0 | K49: =IF(B49="","",_xlfn.LET(_xlpm.totalUSD,SUMIFS(Tabla3[COSTO TOTAL DOLARES CTP],Tabla3[STATUS],"COTIZANDO",Tabla3[NUM ECONOMICO],B49,Tabla3[TEMA],"<>SERVICIO DE FILTROS"),IF(OR(TC="",_xlpm.totalUSD=0),"—",_xlpm.totalUSD*TC))) -> — | L49: {=IF(B49="",0,IFERROR(MAX(_xlfn._xlws.FILTER(Tabla3[DIAS DE ENTREGA TENTATIVO EN MATCO],(Tabla3[STATUS]="COTIZANDO")*(Tabla3[NUM ECONOMICO]=B49)*(Tabla3[TEMA]<>"SERVICIO DE FILTROS"))),0))} -> 0
B50: =MAQUINARIA!B160 -> ME-16 | C50: =MAQUINARIA!H160 -> INACTIVA | D50: =IFERROR(TRIM(MAQUINARIA!C160&" "&MAQUINARIA!E160),"—") -> ESCREPA 631 E | E50: {=IF(B50="",0,IFERROR(ROWS(_xlfn.UNIQUE(_xlfn._xlws.FILTER(Tabla3[PEDIDO],(Tabla3[STATUS]="COTIZANDO")*(Tabla3[NUM ECONOMICO]=B50)*(Tabla3[TEMA]<>"SERVICIO DE FILTROS")))),0))} -> 0 | F50: =IF(B50="",0,COUNTIFS(Tabla3[STATUS],"COTIZANDO",Tabla3[NUM ECONOMICO],B50,Tabla3[TEMA],"<>SERVICIO DE FILTROS")) -> 0 | G50: =IF(B50="",0,SUMIFS(Tabla3[COSTO TOTAL SIN IVA PESOS EN MATCO],Tabla3[STATUS],"COTIZANDO",Tabla3[NUM ECONOMICO],B50,Tabla3[TEMA],"<>SERVICIO DE FILTROS")) -> 0 | H50: =IF(B50="",0,SUMIFS(Tabla3[COSTO TOTAL DOLARES EN HAWTHORNE],Tabla3[STATUS],"COTIZANDO",Tabla3[NUM ECONOMICO],B50,Tabla3[TEMA],"<>SERVICIO DE FILTROS")) -> 0 | I50: =IF(B50="","",_xlfn.LET(_xlpm.totalUSD,SUMIFS(Tabla3[COSTO TOTAL DOLARES EN HAWTHORNE],Tabla3[STATUS],"COTIZANDO",Tabla3[NUM ECONOMICO],B50,Tabla3[TEMA],"<>SERVICIO DE FILTROS"),IF(OR(TC="",_xlpm.totalUSD=0),"—",_xlpm.totalUSD*TC))) -> — | J50: =IF(B50="",0,SUMIFS(Tabla3[COSTO TOTAL DOLARES CTP],Tabla3[STATUS],"COTIZANDO",Tabla3[NUM ECONOMICO],B50,Tabla3[TEMA],"<>SERVICIO DE FILTROS")) -> 0 | K50: =IF(B50="","",_xlfn.LET(_xlpm.totalUSD,SUMIFS(Tabla3[COSTO TOTAL DOLARES CTP],Tabla3[STATUS],"COTIZANDO",Tabla3[NUM ECONOMICO],B50,Tabla3[TEMA],"<>SERVICIO DE FILTROS"),IF(OR(TC="",_xlpm.totalUSD=0),"—",_xlpm.totalUSD*TC))) -> — | L50: {=IF(B50="",0,IFERROR(MAX(_xlfn._xlws.FILTER(Tabla3[DIAS DE ENTREGA TENTATIVO EN MATCO],(Tabla3[STATUS]="COTIZANDO")*(Tabla3[NUM ECONOMICO]=B50)*(Tabla3[TEMA]<>"SERVICIO DE FILTROS"))),0))} -> 0
B51: =MAQUINARIA!B167 -> ME-17 | C51: =MAQUINARIA!H167 -> INACTIVA | D51: =IFERROR(TRIM(MAQUINARIA!C167&" "&MAQUINARIA!E167),"—") -> ESCREPA 631 E | E51: {=IF(B51="",0,IFERROR(ROWS(_xlfn.UNIQUE(_xlfn._xlws.FILTER(Tabla3[PEDIDO],(Tabla3[STATUS]="COTIZANDO")*(Tabla3[NUM ECONOMICO]=B51)*(Tabla3[TEMA]<>"SERVICIO DE FILTROS")))),0))} -> 2 | F51: =IF(B51="",0,COUNTIFS(Tabla3[STATUS],"COTIZANDO",Tabla3[NUM ECONOMICO],B51,Tabla3[TEMA],"<>SERVICIO DE FILTROS")) -> 35 | G51: =IF(B51="",0,SUMIFS(Tabla3[COSTO TOTAL SIN IVA PESOS EN MATCO],Tabla3[STATUS],"COTIZANDO",Tabla3[NUM ECONOMICO],B51,Tabla3[TEMA],"<>SERVICIO DE FILTROS")) -> 256132.69 | H51: =IF(B51="",0,SUMIFS(Tabla3[COSTO TOTAL DOLARES EN HAWTHORNE],Tabla3[STATUS],"COTIZANDO",Tabla3[NUM ECONOMICO],B51,Tabla3[TEMA],"<>SERVICIO DE FILTROS")) -> 10643.18 | I51: =IF(B51="","",_xlfn.LET(_xlpm.totalUSD,SUMIFS(Tabla3[COSTO TOTAL DOLARES EN HAWTHORNE],Tabla3[STATUS],"COTIZANDO",Tabla3[NUM ECONOMICO],B51,Tabla3[TEMA],"<>SERVICIO DE FILTROS"),IF(OR(TC="",_xlpm.totalUSD=0),"—",_xlpm.totalUSD*TC))) -> 180934.06 | J51: =IF(B51="",0,SUMIFS(Tabla3[COSTO TOTAL DOLARES CTP],Tabla3[STATUS],"COTIZANDO",Tabla3[NUM ECONOMICO],B51,Tabla3[TEMA],"<>SERVICIO DE FILTROS")) -> 1013.98 | K51: =IF(B51="","",_xlfn.LET(_xlpm.totalUSD,SUMIFS(Tabla3[COSTO TOTAL DOLARES CTP],Tabla3[STATUS],"COTIZANDO",Tabla3[NUM ECONOMICO],B51,Tabla3[TEMA],"<>SERVICIO DE FILTROS"),IF(OR(TC="",_xlpm.totalUSD=0),"—",_xlpm.totalUSD*TC))) -> 17237.66 | L51: {=IF(B51="",0,IFERROR(MAX(_xlfn._xlws.FILTER(Tabla3[DIAS DE ENTREGA TENTATIVO EN MATCO],(Tabla3[STATUS]="COTIZANDO")*(Tabla3[NUM ECONOMICO]=B51)*(Tabla3[TEMA]<>"SERVICIO DE FILTROS"))),0))} -> 0
B52: =MAQUINARIA!B171 -> ME-18 | C52: =MAQUINARIA!H171 -> INACTIVA | D52: =IFERROR(TRIM(MAQUINARIA!C171&" "&MAQUINARIA!E171),"—") -> ESCREPA 631 E | E52: {=IF(B52="",0,IFERROR(ROWS(_xlfn.UNIQUE(_xlfn._xlws.FILTER(Tabla3[PEDIDO],(Tabla3[STATUS]="COTIZANDO")*(Tabla3[NUM ECONOMICO]=B52)*(Tabla3[TEMA]<>"SERVICIO DE FILTROS")))),0))} -> 0 | F52: =IF(B52="",0,COUNTIFS(Tabla3[STATUS],"COTIZANDO",Tabla3[NUM ECONOMICO],B52,Tabla3[TEMA],"<>SERVICIO DE FILTROS")) -> 0 | G52: =IF(B52="",0,SUMIFS(Tabla3[COSTO TOTAL SIN IVA PESOS EN MATCO],Tabla3[STATUS],"COTIZANDO",Tabla3[NUM ECONOMICO],B52,Tabla3[TEMA],"<>SERVICIO DE FILTROS")) -> 0 | H52: =IF(B52="",0,SUMIFS(Tabla3[COSTO TOTAL DOLARES EN HAWTHORNE],Tabla3[STATUS],"COTIZANDO",Tabla3[NUM ECONOMICO],B52,Tabla3[TEMA],"<>SERVICIO DE FILTROS")) -> 0 | I52: =IF(B52="","",_xlfn.LET(_xlpm.totalUSD,SUMIFS(Tabla3[COSTO TOTAL DOLARES EN HAWTHORNE],Tabla3[STATUS],"COTIZANDO",Tabla3[NUM ECONOMICO],B52,Tabla3[TEMA],"<>SERVICIO DE FILTROS"),IF(OR(TC="",_xlpm.totalUSD=0),"—",_xlpm.totalUSD*TC))) -> — | J52: =IF(B52="",0,SUMIFS(Tabla3[COSTO TOTAL DOLARES CTP],Tabla3[STATUS],"COTIZANDO",Tabla3[NUM ECONOMICO],B52,Tabla3[TEMA],"<>SERVICIO DE FILTROS")) -> 0 | K52: =IF(B52="","",_xlfn.LET(_xlpm.totalUSD,SUMIFS(Tabla3[COSTO TOTAL DOLARES CTP],Tabla3[STATUS],"COTIZANDO",Tabla3[NUM ECONOMICO],B52,Tabla3[TEMA],"<>SERVICIO DE FILTROS"),IF(OR(TC="",_xlpm.totalUSD=0),"—",_xlpm.totalUSD*TC))) -> — | L52: {=IF(B52="",0,IFERROR(MAX(_xlfn._xlws.FILTER(Tabla3[DIAS DE ENTREGA TENTATIVO EN MATCO],(Tabla3[STATUS]="COTIZANDO")*(Tabla3[NUM ECONOMICO]=B52)*(Tabla3[TEMA]<>"SERVICIO DE FILTROS"))),0))} -> 0
B53: =MAQUINARIA!B175 -> ME-19 | C53: =MAQUINARIA!H175 -> INACTIVA | D53: =IFERROR(TRIM(MAQUINARIA!C175&" "&MAQUINARIA!E175),"—") -> ESCREPA 631 E | E53: {=IF(B53="",0,IFERROR(ROWS(_xlfn.UNIQUE(_xlfn._xlws.FILTER(Tabla3[PEDIDO],(Tabla3[STATUS]="COTIZANDO")*(Tabla3[NUM ECONOMICO]=B53)*(Tabla3[TEMA]<>"SERVICIO DE FILTROS")))),0))} -> 1 | F53: =IF(B53="",0,COUNTIFS(Tabla3[STATUS],"COTIZANDO",Tabla3[NUM ECONOMICO],B53,Tabla3[TEMA],"<>SERVICIO DE FILTROS")) -> 170 | G53: =IF(B53="",0,SUMIFS(Tabla3[COSTO TOTAL SIN IVA PESOS EN MATCO],Tabla3[STATUS],"COTIZANDO",Tabla3[NUM ECONOMICO],B53,Tabla3[TEMA],"<>SERVICIO DE FILTROS")) -> 675447.06 | H53: =IF(B53="",0,SUMIFS(Tabla3[COSTO TOTAL DOLARES EN HAWTHORNE],Tabla3[STATUS],"COTIZANDO",Tabla3[NUM ECONOMICO],B53,Tabla3[TEMA],"<>SERVICIO DE FILTROS")) -> 0 | I53: =IF(B53="","",_xlfn.LET(_xlpm.totalUSD,SUMIFS(Tabla3[COSTO TOTAL DOLARES EN HAWTHORNE],Tabla3[STATUS],"COTIZANDO",Tabla3[NUM ECONOMICO],B53,Tabla3[TEMA],"<>SERVICIO DE FILTROS"),IF(OR(TC="",_xlpm.totalUSD=0),"—",_xlpm.totalUSD*TC))) -> — | J53: =IF(B53="",0,SUMIFS(Tabla3[COSTO TOTAL DOLARES CTP],Tabla3[STATUS],"COTIZANDO",Tabla3[NUM ECONOMICO],B53,Tabla3[TEMA],"<>SERVICIO DE FILTROS")) -> 0 | K53: =IF(B53="","",_xlfn.LET(_xlpm.totalUSD,SUMIFS(Tabla3[COSTO TOTAL DOLARES CTP],Tabla3[STATUS],"COTIZANDO",Tabla3[NUM ECONOMICO],B53,Tabla3[TEMA],"<>SERVICIO DE FILTROS"),IF(OR(TC="",_xlpm.totalUSD=0),"—",_xlpm.totalUSD*TC))) -> — | L53: {=IF(B53="",0,IFERROR(MAX(_xlfn._xlws.FILTER(Tabla3[DIAS DE ENTREGA TENTATIVO EN MATCO],(Tabla3[STATUS]="COTIZANDO")*(Tabla3[NUM ECONOMICO]=B53)*(Tabla3[TEMA]<>"SERVICIO DE FILTROS"))),0))} -> 0
B54: =MAQUINARIA!B183 -> ME-20 | C54: =MAQUINARIA!H183 -> ACTIVA | D54: =IFERROR(TRIM(MAQUINARIA!C183&" "&MAQUINARIA!E183),"—") -> ESCREPA 631 E | E54: {=IF(B54="",0,IFERROR(ROWS(_xlfn.UNIQUE(_xlfn._xlws.FILTER(Tabla3[PEDIDO],(Tabla3[STATUS]="COTIZANDO")*(Tabla3[NUM ECONOMICO]=B54)*(Tabla3[TEMA]<>"SERVICIO DE FILTROS")))),0))} -> 0 | F54: =IF(B54="",0,COUNTIFS(Tabla3[STATUS],"COTIZANDO",Tabla3[NUM ECONOMICO],B54,Tabla3[TEMA],"<>SERVICIO DE FILTROS")) -> 0 | G54: =IF(B54="",0,SUMIFS(Tabla3[COSTO TOTAL SIN IVA PESOS EN MATCO],Tabla3[STATUS],"COTIZANDO",Tabla3[NUM ECONOMICO],B54,Tabla3[TEMA],"<>SERVICIO DE FILTROS")) -> 0 | H54: =IF(B54="",0,SUMIFS(Tabla3[COSTO TOTAL DOLARES EN HAWTHORNE],Tabla3[STATUS],"COTIZANDO",Tabla3[NUM ECONOMICO],B54,Tabla3[TEMA],"<>SERVICIO DE FILTROS")) -> 0 | I54: =IF(B54="","",_xlfn.LET(_xlpm.totalUSD,SUMIFS(Tabla3[COSTO TOTAL DOLARES EN HAWTHORNE],Tabla3[STATUS],"COTIZANDO",Tabla3[NUM ECONOMICO],B54,Tabla3[TEMA],"<>SERVICIO DE FILTROS"),IF(OR(TC="",_xlpm.totalUSD=0),"—",_xlpm.totalUSD*TC))) -> — | J54: =IF(B54="",0,SUMIFS(Tabla3[COSTO TOTAL DOLARES CTP],Tabla3[STATUS],"COTIZANDO",Tabla3[NUM ECONOMICO],B54,Tabla3[TEMA],"<>SERVICIO DE FILTROS")) -> 0 | K54: =IF(B54="","",_xlfn.LET(_xlpm.totalUSD,SUMIFS(Tabla3[COSTO TOTAL DOLARES CTP],Tabla3[STATUS],"COTIZANDO",Tabla3[NUM ECONOMICO],B54,Tabla3[TEMA],"<>SERVICIO DE FILTROS"),IF(OR(TC="",_xlpm.totalUSD=0),"—",_xlpm.totalUSD*TC))) -> — | L54: {=IF(B54="",0,IFERROR(MAX(_xlfn._xlws.FILTER(Tabla3[DIAS DE ENTREGA TENTATIVO EN MATCO],(Tabla3[STATUS]="COTIZANDO")*(Tabla3[NUM ECONOMICO]=B54)*(Tabla3[TEMA]<>"SERVICIO DE FILTROS"))),0))} -> 0
B55: =MAQUINARIA!B186 -> ME-21 | C55: =MAQUINARIA!H186 -> INACTIVA | D55: =IFERROR(TRIM(MAQUINARIA!C186&" "&MAQUINARIA!E186),"—") -> ESCREPA 631 E | E55: {=IF(B55="",0,IFERROR(ROWS(_xlfn.UNIQUE(_xlfn._xlws.FILTER(Tabla3[PEDIDO],(Tabla3[STATUS]="COTIZANDO")*(Tabla3[NUM ECONOMICO]=B55)*(Tabla3[TEMA]<>"SERVICIO DE FILTROS")))),0))} -> 0 | F55: =IF(B55="",0,COUNTIFS(Tabla3[STATUS],"COTIZANDO",Tabla3[NUM ECONOMICO],B55,Tabla3[TEMA],"<>SERVICIO DE FILTROS")) -> 0 | G55: =IF(B55="",0,SUMIFS(Tabla3[COSTO TOTAL SIN IVA PESOS EN MATCO],Tabla3[STATUS],"COTIZANDO",Tabla3[NUM ECONOMICO],B55,Tabla3[TEMA],"<>SERVICIO DE FILTROS")) -> 0 | H55: =IF(B55="",0,SUMIFS(Tabla3[COSTO TOTAL DOLARES EN HAWTHORNE],Tabla3[STATUS],"COTIZANDO",Tabla3[NUM ECONOMICO],B55,Tabla3[TEMA],"<>SERVICIO DE FILTROS")) -> 0 | I55: =IF(B55="","",_xlfn.LET(_xlpm.totalUSD,SUMIFS(Tabla3[COSTO TOTAL DOLARES EN HAWTHORNE],Tabla3[STATUS],"COTIZANDO",Tabla3[NUM ECONOMICO],B55,Tabla3[TEMA],"<>SERVICIO DE FILTROS"),IF(OR(TC="",_xlpm.totalUSD=0),"—",_xlpm.totalUSD*TC))) -> — | J55: =IF(B55="",0,SUMIFS(Tabla3[COSTO TOTAL DOLARES CTP],Tabla3[STATUS],"COTIZANDO",Tabla3[NUM ECONOMICO],B55,Tabla3[TEMA],"<>SERVICIO DE FILTROS")) -> 0 | K55: =IF(B55="","",_xlfn.LET(_xlpm.totalUSD,SUMIFS(Tabla3[COSTO TOTAL DOLARES CTP],Tabla3[STATUS],"COTIZANDO",Tabla3[NUM ECONOMICO],B55,Tabla3[TEMA],"<>SERVICIO DE FILTROS"),IF(OR(TC="",_xlpm.totalUSD=0),"—",_xlpm.totalUSD*TC))) -> — | L55: {=IF(B55="",0,IFERROR(MAX(_xlfn._xlws.FILTER(Tabla3[DIAS DE ENTREGA TENTATIVO EN MATCO],(Tabla3[STATUS]="COTIZANDO")*(Tabla3[NUM ECONOMICO]=B55)*(Tabla3[TEMA]<>"SERVICIO DE FILTROS"))),0))} -> 0
B56: =MAQUINARIA!B190 -> ME-22 | C56: =MAQUINARIA!H190 -> ACTIVA | D56: =IFERROR(TRIM(MAQUINARIA!C190&" "&MAQUINARIA!E190),"—") -> ESCREPA 631 E | E56: {=IF(B56="",0,IFERROR(ROWS(_xlfn.UNIQUE(_xlfn._xlws.FILTER(Tabla3[PEDIDO],(Tabla3[STATUS]="COTIZANDO")*(Tabla3[NUM ECONOMICO]=B56)*(Tabla3[TEMA]<>"SERVICIO DE FILTROS")))),0))} -> 0 | F56: =IF(B56="",0,COUNTIFS(Tabla3[STATUS],"COTIZANDO",Tabla3[NUM ECONOMICO],B56,Tabla3[TEMA],"<>SERVICIO DE FILTROS")) -> 0 | G56: =IF(B56="",0,SUMIFS(Tabla3[COSTO TOTAL SIN IVA PESOS EN MATCO],Tabla3[STATUS],"COTIZANDO",Tabla3[NUM ECONOMICO],B56,Tabla3[TEMA],"<>SERVICIO DE FILTROS")) -> 0 | H56: =IF(B56="",0,SUMIFS(Tabla3[COSTO TOTAL DOLARES EN HAWTHORNE],Tabla3[STATUS],"COTIZANDO",Tabla3[NUM ECONOMICO],B56,Tabla3[TEMA],"<>SERVICIO DE FILTROS")) -> 0 | I56: =IF(B56="","",_xlfn.LET(_xlpm.totalUSD,SUMIFS(Tabla3[COSTO TOTAL DOLARES EN HAWTHORNE],Tabla3[STATUS],"COTIZANDO",Tabla3[NUM ECONOMICO],B56,Tabla3[TEMA],"<>SERVICIO DE FILTROS"),IF(OR(TC="",_xlpm.totalUSD=0),"—",_xlpm.totalUSD*TC))) -> — | J56: =IF(B56="",0,SUMIFS(Tabla3[COSTO TOTAL DOLARES CTP],Tabla3[STATUS],"COTIZANDO",Tabla3[NUM ECONOMICO],B56,Tabla3[TEMA],"<>SERVICIO DE FILTROS")) -> 0 | K56: =IF(B56="","",_xlfn.LET(_xlpm.totalUSD,SUMIFS(Tabla3[COSTO TOTAL DOLARES CTP],Tabla3[STATUS],"COTIZANDO",Tabla3[NUM ECONOMICO],B56,Tabla3[TEMA],"<>SERVICIO DE FILTROS"),IF(OR(TC="",_xlpm.totalUSD=0),"—",_xlpm.totalUSD*TC))) -> — | L56: {=IF(B56="",0,IFERROR(MAX(_xlfn._xlws.FILTER(Tabla3[DIAS DE ENTREGA TENTATIVO EN MATCO],(Tabla3[STATUS]="COTIZANDO")*(Tabla3[NUM ECONOMICO]=B56)*(Tabla3[TEMA]<>"SERVICIO DE FILTROS"))),0))} -> 0
B57: =MAQUINARIA!B194 -> ME-23 | C57: =MAQUINARIA!H194 -> ACTIVA | D57: =IFERROR(TRIM(MAQUINARIA!C194&" "&MAQUINARIA!E194),"—") -> ESCREPA 631 E | E57: {=IF(B57="",0,IFERROR(ROWS(_xlfn.UNIQUE(_xlfn._xlws.FILTER(Tabla3[PEDIDO],(Tabla3[STATUS]="COTIZANDO")*(Tabla3[NUM ECONOMICO]=B57)*(Tabla3[TEMA]<>"SERVICIO DE FILTROS")))),0))} -> 0 | F57: =IF(B57="",0,COUNTIFS(Tabla3[STATUS],"COTIZANDO",Tabla3[NUM ECONOMICO],B57,Tabla3[TEMA],"<>SERVICIO DE FILTROS")) -> 0 | G57: =IF(B57="",0,SUMIFS(Tabla3[COSTO TOTAL SIN IVA PESOS EN MATCO],Tabla3[STATUS],"COTIZANDO",Tabla3[NUM ECONOMICO],B57,Tabla3[TEMA],"<>SERVICIO DE FILTROS")) -> 0 | H57: =IF(B57="",0,SUMIFS(Tabla3[COSTO TOTAL DOLARES EN HAWTHORNE],Tabla3[STATUS],"COTIZANDO",Tabla3[NUM ECONOMICO],B57,Tabla3[TEMA],"<>SERVICIO DE FILTROS")) -> 0 | I57: =IF(B57="","",_xlfn.LET(_xlpm.totalUSD,SUMIFS(Tabla3[COSTO TOTAL DOLARES EN HAWTHORNE],Tabla3[STATUS],"COTIZANDO",Tabla3[NUM ECONOMICO],B57,Tabla3[TEMA],"<>SERVICIO DE FILTROS"),IF(OR(TC="",_xlpm.totalUSD=0),"—",_xlpm.totalUSD*TC))) -> — | J57: =IF(B57="",0,SUMIFS(Tabla3[COSTO TOTAL DOLARES CTP],Tabla3[STATUS],"COTIZANDO",Tabla3[NUM ECONOMICO],B57,Tabla3[TEMA],"<>SERVICIO DE FILTROS")) -> 0 | K57: =IF(B57="","",_xlfn.LET(_xlpm.totalUSD,SUMIFS(Tabla3[COSTO TOTAL DOLARES CTP],Tabla3[STATUS],"COTIZANDO",Tabla3[NUM ECONOMICO],B57,Tabla3[TEMA],"<>SERVICIO DE FILTROS"),IF(OR(TC="",_xlpm.totalUSD=0),"—",_xlpm.totalUSD*TC))) -> — | L57: {=IF(B57="",0,IFERROR(MAX(_xlfn._xlws.FILTER(Tabla3[DIAS DE ENTREGA TENTATIVO EN MATCO],(Tabla3[STATUS]="COTIZANDO")*(Tabla3[NUM ECONOMICO]=B57)*(Tabla3[TEMA]<>"SERVICIO DE FILTROS"))),0))} -> 0
B58: =MAQUINARIA!B197 -> ME-24 | C58: =MAQUINARIA!H197 -> ACTIVA | D58: =IFERROR(TRIM(MAQUINARIA!C197&" "&MAQUINARIA!E197),"—") -> ESCREPA 631 E | E58: {=IF(B58="",0,IFERROR(ROWS(_xlfn.UNIQUE(_xlfn._xlws.FILTER(Tabla3[PEDIDO],(Tabla3[STATUS]="COTIZANDO")*(Tabla3[NUM ECONOMICO]=B58)*(Tabla3[TEMA]<>"SERVICIO DE FILTROS")))),0))} -> 0 | F58: =IF(B58="",0,COUNTIFS(Tabla3[STATUS],"COTIZANDO",Tabla3[NUM ECONOMICO],B58,Tabla3[TEMA],"<>SERVICIO DE FILTROS")) -> 0 | G58: =IF(B58="",0,SUMIFS(Tabla3[COSTO TOTAL SIN IVA PESOS EN MATCO],Tabla3[STATUS],"COTIZANDO",Tabla3[NUM ECONOMICO],B58,Tabla3[TEMA],"<>SERVICIO DE FILTROS")) -> 0 | H58: =IF(B58="",0,SUMIFS(Tabla3[COSTO TOTAL DOLARES EN HAWTHORNE],Tabla3[STATUS],"COTIZANDO",Tabla3[NUM ECONOMICO],B58,Tabla3[TEMA],"<>SERVICIO DE FILTROS")) -> 0 | I58: =IF(B58="","",_xlfn.LET(_xlpm.totalUSD,SUMIFS(Tabla3[COSTO TOTAL DOLARES EN HAWTHORNE],Tabla3[STATUS],"COTIZANDO",Tabla3[NUM ECONOMICO],B58,Tabla3[TEMA],"<>SERVICIO DE FILTROS"),IF(OR(TC="",_xlpm.totalUSD=0),"—",_xlpm.totalUSD*TC))) -> — | J58: =IF(B58="",0,SUMIFS(Tabla3[COSTO TOTAL DOLARES CTP],Tabla3[STATUS],"COTIZANDO",Tabla3[NUM ECONOMICO],B58,Tabla3[TEMA],"<>SERVICIO DE FILTROS")) -> 0 | K58: =IF(B58="","",_xlfn.LET(_xlpm.totalUSD,SUMIFS(Tabla3[COSTO TOTAL DOLARES CTP],Tabla3[STATUS],"COTIZANDO",Tabla3[NUM ECONOMICO],B58,Tabla3[TEMA],"<>SERVICIO DE FILTROS"),IF(OR(TC="",_xlpm.totalUSD=0),"—",_xlpm.totalUSD*TC))) -> — | L58: {=IF(B58="",0,IFERROR(MAX(_xlfn._xlws.FILTER(Tabla3[DIAS DE ENTREGA TENTATIVO EN MATCO],(Tabla3[STATUS]="COTIZANDO")*(Tabla3[NUM ECONOMICO]=B58)*(Tabla3[TEMA]<>"SERVICIO DE FILTROS"))),0))} -> 0
B59: =MAQUINARIA!B198 -> ME-25 | C59: =MAQUINARIA!H198 -> ACTIVA | D59: =IFERROR(TRIM(MAQUINARIA!C198&" "&MAQUINARIA!E198),"—") -> ESCREPA 621 E | E59: {=IF(B59="",0,IFERROR(ROWS(_xlfn.UNIQUE(_xlfn._xlws.FILTER(Tabla3[PEDIDO],(Tabla3[STATUS]="COTIZANDO")*(Tabla3[NUM ECONOMICO]=B59)*(Tabla3[TEMA]<>"SERVICIO DE FILTROS")))),0))} -> 0 | F59: =IF(B59="",0,COUNTIFS(Tabla3[STATUS],"COTIZANDO",Tabla3[NUM ECONOMICO],B59,Tabla3[TEMA],"<>SERVICIO DE FILTROS")) -> 0 | G59: =IF(B59="",0,SUMIFS(Tabla3[COSTO TOTAL SIN IVA PESOS EN MATCO],Tabla3[STATUS],"COTIZANDO",Tabla3[NUM ECONOMICO],B59,Tabla3[TEMA],"<>SERVICIO DE FILTROS")) -> 0 | H59: =IF(B59="",0,SUMIFS(Tabla3[COSTO TOTAL DOLARES EN HAWTHORNE],Tabla3[STATUS],"COTIZANDO",Tabla3[NUM ECONOMICO],B59,Tabla3[TEMA],"<>SERVICIO DE FILTROS")) -> 0 | I59: =IF(B59="","",_xlfn.LET(_xlpm.totalUSD,SUMIFS(Tabla3[COSTO TOTAL DOLARES EN HAWTHORNE],Tabla3[STATUS],"COTIZANDO",Tabla3[NUM ECONOMICO],B59,Tabla3[TEMA],"<>SERVICIO DE FILTROS"),IF(OR(TC="",_xlpm.totalUSD=0),"—",_xlpm.totalUSD*TC))) -> — | J59: =IF(B59="",0,SUMIFS(Tabla3[COSTO TOTAL DOLARES CTP],Tabla3[STATUS],"COTIZANDO",Tabla3[NUM ECONOMICO],B59,Tabla3[TEMA],"<>SERVICIO DE FILTROS")) -> 0 | K59: =IF(B59="","",_xlfn.LET(_xlpm.totalUSD,SUMIFS(Tabla3[COSTO TOTAL DOLARES CTP],Tabla3[STATUS],"COTIZANDO",Tabla3[NUM ECONOMICO],B59,Tabla3[TEMA],"<>SERVICIO DE FILTROS"),IF(OR(TC="",_xlpm.totalUSD=0),"—",_xlpm.totalUSD*TC))) -> — | L59: {=IF(B59="",0,IFERROR(MAX(_xlfn._xlws.FILTER(Tabla3[DIAS DE ENTREGA TENTATIVO EN MATCO],(Tabla3[STATUS]="COTIZANDO")*(Tabla3[NUM ECONOMICO]=B59)*(Tabla3[TEMA]<>"SERVICIO DE FILTROS"))),0))} -> 0
B60: =MAQUINARIA!B203 -> ME-26 | C60: =MAQUINARIA!H203 -> ACTIVA | D60: =IFERROR(TRIM(MAQUINARIA!C203&" "&MAQUINARIA!E203),"—") -> ESCREPA 621 E | E60: {=IF(B60="",0,IFERROR(ROWS(_xlfn.UNIQUE(_xlfn._xlws.FILTER(Tabla3[PEDIDO],(Tabla3[STATUS]="COTIZANDO")*(Tabla3[NUM ECONOMICO]=B60)*(Tabla3[TEMA]<>"SERVICIO DE FILTROS")))),0))} -> 0 | F60: =IF(B60="",0,COUNTIFS(Tabla3[STATUS],"COTIZANDO",Tabla3[NUM ECONOMICO],B60,Tabla3[TEMA],"<>SERVICIO DE FILTROS")) -> 0 | G60: =IF(B60="",0,SUMIFS(Tabla3[COSTO TOTAL SIN IVA PESOS EN MATCO],Tabla3[STATUS],"COTIZANDO",Tabla3[NUM ECONOMICO],B60,Tabla3[TEMA],"<>SERVICIO DE FILTROS")) -> 0 | H60: =IF(B60="",0,SUMIFS(Tabla3[COSTO TOTAL DOLARES EN HAWTHORNE],Tabla3[STATUS],"COTIZANDO",Tabla3[NUM ECONOMICO],B60,Tabla3[TEMA],"<>SERVICIO DE FILTROS")) -> 0 | I60: =IF(B60="","",_xlfn.LET(_xlpm.totalUSD,SUMIFS(Tabla3[COSTO TOTAL DOLARES EN HAWTHORNE],Tabla3[STATUS],"COTIZANDO",Tabla3[NUM ECONOMICO],B60,Tabla3[TEMA],"<>SERVICIO DE FILTROS"),IF(OR(TC="",_xlpm.totalUSD=0),"—",_xlpm.totalUSD*TC))) -> — | J60: =IF(B60="",0,SUMIFS(Tabla3[COSTO TOTAL DOLARES CTP],Tabla3[STATUS],"COTIZANDO",Tabla3[NUM ECONOMICO],B60,Tabla3[TEMA],"<>SERVICIO DE FILTROS")) -> 0 | K60: =IF(B60="","",_xlfn.LET(_xlpm.totalUSD,SUMIFS(Tabla3[COSTO TOTAL DOLARES CTP],Tabla3[STATUS],"COTIZANDO",Tabla3[NUM ECONOMICO],B60,Tabla3[TEMA],"<>SERVICIO DE FILTROS"),IF(OR(TC="",_xlpm.totalUSD=0),"—",_xlpm.totalUSD*TC))) -> — | L60: {=IF(B60="",0,IFERROR(MAX(_xlfn._xlws.FILTER(Tabla3[DIAS DE ENTREGA TENTATIVO EN MATCO],(Tabla3[STATUS]="COTIZANDO")*(Tabla3[NUM ECONOMICO]=B60)*(Tabla3[TEMA]<>"SERVICIO DE FILTROS"))),0))} -> 0
B61: =MAQUINARIA!B209 -> ME-27 | C61: =MAQUINARIA!H209 -> ACTIVA | D61: =IFERROR(TRIM(MAQUINARIA!C209&" "&MAQUINARIA!E209),"—") -> ESCREPA 621 G | E61: {=IF(B61="",0,IFERROR(ROWS(_xlfn.UNIQUE(_xlfn._xlws.FILTER(Tabla3[PEDIDO],(Tabla3[STATUS]="COTIZANDO")*(Tabla3[NUM ECONOMICO]=B61)*(Tabla3[TEMA]<>"SERVICIO DE FILTROS")))),0))} -> 0 | F61: =IF(B61="",0,COUNTIFS(Tabla3[STATUS],"COTIZANDO",Tabla3[NUM ECONOMICO],B61,Tabla3[TEMA],"<>SERVICIO DE FILTROS")) -> 0 | G61: =IF(B61="",0,SUMIFS(Tabla3[COSTO TOTAL SIN IVA PESOS EN MATCO],Tabla3[STATUS],"COTIZANDO",Tabla3[NUM ECONOMICO],B61,Tabla3[TEMA],"<>SERVICIO DE FILTROS")) -> 0 | H61: =IF(B61="",0,SUMIFS(Tabla3[COSTO TOTAL DOLARES EN HAWTHORNE],Tabla3[STATUS],"COTIZANDO",Tabla3[NUM ECONOMICO],B61,Tabla3[TEMA],"<>SERVICIO DE FILTROS")) -> 0 | I61: =IF(B61="","",_xlfn.LET(_xlpm.totalUSD,SUMIFS(Tabla3[COSTO TOTAL DOLARES EN HAWTHORNE],Tabla3[STATUS],"COTIZANDO",Tabla3[NUM ECONOMICO],B61,Tabla3[TEMA],"<>SERVICIO DE FILTROS"),IF(OR(TC="",_xlpm.totalUSD=0),"—",_xlpm.totalUSD*TC))) -> — | J61: =IF(B61="",0,SUMIFS(Tabla3[COSTO TOTAL DOLARES CTP],Tabla3[STATUS],"COTIZANDO",Tabla3[NUM ECONOMICO],B61,Tabla3[TEMA],"<>SERVICIO DE FILTROS")) -> 0 | K61: =IF(B61="","",_xlfn.LET(_xlpm.totalUSD,SUMIFS(Tabla3[COSTO TOTAL DOLARES CTP],Tabla3[STATUS],"COTIZANDO",Tabla3[NUM ECONOMICO],B61,Tabla3[TEMA],"<>SERVICIO DE FILTROS"),IF(OR(TC="",_xlpm.totalUSD=0),"—",_xlpm.totalUSD*TC))) -> — | L61: {=IF(B61="",0,IFERROR(MAX(_xlfn._xlws.FILTER(Tabla3[DIAS DE ENTREGA TENTATIVO EN MATCO],(Tabla3[STATUS]="COTIZANDO")*(Tabla3[NUM ECONOMICO]=B61)*(Tabla3[TEMA]<>"SERVICIO DE FILTROS"))),0))} -> 0
B62: =MAQUINARIA!B217 -> ME-28 | C62: =MAQUINARIA!H217 -> INACTIVA | D62: =IFERROR(TRIM(MAQUINARIA!C217&" "&MAQUINARIA!E217),"—") -> ESCREPA 621 G | E62: {=IF(B62="",0,IFERROR(ROWS(_xlfn.UNIQUE(_xlfn._xlws.FILTER(Tabla3[PEDIDO],(Tabla3[STATUS]="COTIZANDO")*(Tabla3[NUM ECONOMICO]=B62)*(Tabla3[TEMA]<>"SERVICIO DE FILTROS")))),0))} -> 0 | F62: =IF(B62="",0,COUNTIFS(Tabla3[STATUS],"COTIZANDO",Tabla3[NUM ECONOMICO],B62,Tabla3[TEMA],"<>SERVICIO DE FILTROS")) -> 0 | G62: =IF(B62="",0,SUMIFS(Tabla3[COSTO TOTAL SIN IVA PESOS EN MATCO],Tabla3[STATUS],"COTIZANDO",Tabla3[NUM ECONOMICO],B62,Tabla3[TEMA],"<>SERVICIO DE FILTROS")) -> 0 | H62: =IF(B62="",0,SUMIFS(Tabla3[COSTO TOTAL DOLARES EN HAWTHORNE],Tabla3[STATUS],"COTIZANDO",Tabla3[NUM ECONOMICO],B62,Tabla3[TEMA],"<>SERVICIO DE FILTROS")) -> 0 | I62: =IF(B62="","",_xlfn.LET(_xlpm.totalUSD,SUMIFS(Tabla3[COSTO TOTAL DOLARES EN HAWTHORNE],Tabla3[STATUS],"COTIZANDO",Tabla3[NUM ECONOMICO],B62,Tabla3[TEMA],"<>SERVICIO DE FILTROS"),IF(OR(TC="",_xlpm.totalUSD=0),"—",_xlpm.totalUSD*TC))) -> — | J62: =IF(B62="",0,SUMIFS(Tabla3[COSTO TOTAL DOLARES CTP],Tabla3[STATUS],"COTIZANDO",Tabla3[NUM ECONOMICO],B62,Tabla3[TEMA],"<>SERVICIO DE FILTROS")) -> 0 | K62: =IF(B62="","",_xlfn.LET(_xlpm.totalUSD,SUMIFS(Tabla3[COSTO TOTAL DOLARES CTP],Tabla3[STATUS],"COTIZANDO",Tabla3[NUM ECONOMICO],B62,Tabla3[TEMA],"<>SERVICIO DE FILTROS"),IF(OR(TC="",_xlpm.totalUSD=0),"—",_xlpm.totalUSD*TC))) -> — | L62: {=IF(B62="",0,IFERROR(MAX(_xlfn._xlws.FILTER(Tabla3[DIAS DE ENTREGA TENTATIVO EN MATCO],(Tabla3[STATUS]="COTIZANDO")*(Tabla3[NUM ECONOMICO]=B62)*(Tabla3[TEMA]<>"SERVICIO DE FILTROS"))),0))} -> 0
B63: =MAQUINARIA!B224 -> ME-29 | C63: =MAQUINARIA!H224 -> ACTIVA | D63: =IFERROR(TRIM(MAQUINARIA!C224&" "&MAQUINARIA!E224),"—") -> ESCREPA 621 G | E63: {=IF(B63="",0,IFERROR(ROWS(_xlfn.UNIQUE(_xlfn._xlws.FILTER(Tabla3[PEDIDO],(Tabla3[STATUS]="COTIZANDO")*(Tabla3[NUM ECONOMICO]=B63)*(Tabla3[TEMA]<>"SERVICIO DE FILTROS")))),0))} -> 0 | F63: =IF(B63="",0,COUNTIFS(Tabla3[STATUS],"COTIZANDO",Tabla3[NUM ECONOMICO],B63,Tabla3[TEMA],"<>SERVICIO DE FILTROS")) -> 0 | G63: =IF(B63="",0,SUMIFS(Tabla3[COSTO TOTAL SIN IVA PESOS EN MATCO],Tabla3[STATUS],"COTIZANDO",Tabla3[NUM ECONOMICO],B63,Tabla3[TEMA],"<>SERVICIO DE FILTROS")) -> 0 | H63: =IF(B63="",0,SUMIFS(Tabla3[COSTO TOTAL DOLARES EN HAWTHORNE],Tabla3[STATUS],"COTIZANDO",Tabla3[NUM ECONOMICO],B63,Tabla3[TEMA],"<>SERVICIO DE FILTROS")) -> 0 | I63: =IF(B63="","",_xlfn.LET(_xlpm.totalUSD,SUMIFS(Tabla3[COSTO TOTAL DOLARES EN HAWTHORNE],Tabla3[STATUS],"COTIZANDO",Tabla3[NUM ECONOMICO],B63,Tabla3[TEMA],"<>SERVICIO DE FILTROS"),IF(OR(TC="",_xlpm.totalUSD=0),"—",_xlpm.totalUSD*TC))) -> — | J63: =IF(B63="",0,SUMIFS(Tabla3[COSTO TOTAL DOLARES CTP],Tabla3[STATUS],"COTIZANDO",Tabla3[NUM ECONOMICO],B63,Tabla3[TEMA],"<>SERVICIO DE FILTROS")) -> 0 | K63: =IF(B63="","",_xlfn.LET(_xlpm.totalUSD,SUMIFS(Tabla3[COSTO TOTAL DOLARES CTP],Tabla3[STATUS],"COTIZANDO",Tabla3[NUM ECONOMICO],B63,Tabla3[TEMA],"<>SERVICIO DE FILTROS"),IF(OR(TC="",_xlpm.totalUSD=0),"—",_xlpm.totalUSD*TC))) -> — | L63: {=IF(B63="",0,IFERROR(MAX(_xlfn._xlws.FILTER(Tabla3[DIAS DE ENTREGA TENTATIVO EN MATCO],(Tabla3[STATUS]="COTIZANDO")*(Tabla3[NUM ECONOMICO]=B63)*(Tabla3[TEMA]<>"SERVICIO DE FILTROS"))),0))} -> 0
B64: =MAQUINARIA!B229 -> ME-30 | C64: =MAQUINARIA!H229 -> ACTIVA | D64: =IFERROR(TRIM(MAQUINARIA!C229&" "&MAQUINARIA!E229),"—") -> ESCREPA 621 G | E64: {=IF(B64="",0,IFERROR(ROWS(_xlfn.UNIQUE(_xlfn._xlws.FILTER(Tabla3[PEDIDO],(Tabla3[STATUS]="COTIZANDO")*(Tabla3[NUM ECONOMICO]=B64)*(Tabla3[TEMA]<>"SERVICIO DE FILTROS")))),0))} -> 0 | F64: =IF(B64="",0,COUNTIFS(Tabla3[STATUS],"COTIZANDO",Tabla3[NUM ECONOMICO],B64,Tabla3[TEMA],"<>SERVICIO DE FILTROS")) -> 0 | G64: =IF(B64="",0,SUMIFS(Tabla3[COSTO TOTAL SIN IVA PESOS EN MATCO],Tabla3[STATUS],"COTIZANDO",Tabla3[NUM ECONOMICO],B64,Tabla3[TEMA],"<>SERVICIO DE FILTROS")) -> 0 | H64: =IF(B64="",0,SUMIFS(Tabla3[COSTO TOTAL DOLARES EN HAWTHORNE],Tabla3[STATUS],"COTIZANDO",Tabla3[NUM ECONOMICO],B64,Tabla3[TEMA],"<>SERVICIO DE FILTROS")) -> 0 | I64: =IF(B64="","",_xlfn.LET(_xlpm.totalUSD,SUMIFS(Tabla3[COSTO TOTAL DOLARES EN HAWTHORNE],Tabla3[STATUS],"COTIZANDO",Tabla3[NUM ECONOMICO],B64,Tabla3[TEMA],"<>SERVICIO DE FILTROS"),IF(OR(TC="",_xlpm.totalUSD=0),"—",_xlpm.totalUSD*TC))) -> — | J64: =IF(B64="",0,SUMIFS(Tabla3[COSTO TOTAL DOLARES CTP],Tabla3[STATUS],"COTIZANDO",Tabla3[NUM ECONOMICO],B64,Tabla3[TEMA],"<>SERVICIO DE FILTROS")) -> 0 | K64: =IF(B64="","",_xlfn.LET(_xlpm.totalUSD,SUMIFS(Tabla3[COSTO TOTAL DOLARES CTP],Tabla3[STATUS],"COTIZANDO",Tabla3[NUM ECONOMICO],B64,Tabla3[TEMA],"<>SERVICIO DE FILTROS"),IF(OR(TC="",_xlpm.totalUSD=0),"—",_xlpm.totalUSD*TC))) -> — | L64: {=IF(B64="",0,IFERROR(MAX(_xlfn._xlws.FILTER(Tabla3[DIAS DE ENTREGA TENTATIVO EN MATCO],(Tabla3[STATUS]="COTIZANDO")*(Tabla3[NUM ECONOMICO]=B64)*(Tabla3[TEMA]<>"SERVICIO DE FILTROS"))),0))} -> 0
B65: =MAQUINARIA!B231 -> ME-31 | C65: =MAQUINARIA!H231 -> ACTIVA | D65: =IFERROR(TRIM(MAQUINARIA!C231&" "&MAQUINARIA!E231),"—") -> ESCREPA 621 G | E65: {=IF(B65="",0,IFERROR(ROWS(_xlfn.UNIQUE(_xlfn._xlws.FILTER(Tabla3[PEDIDO],(Tabla3[STATUS]="COTIZANDO")*(Tabla3[NUM ECONOMICO]=B65)*(Tabla3[TEMA]<>"SERVICIO DE FILTROS")))),0))} -> 0 | F65: =IF(B65="",0,COUNTIFS(Tabla3[STATUS],"COTIZANDO",Tabla3[NUM ECONOMICO],B65,Tabla3[TEMA],"<>SERVICIO DE FILTROS")) -> 0 | G65: =IF(B65="",0,SUMIFS(Tabla3[COSTO TOTAL SIN IVA PESOS EN MATCO],Tabla3[STATUS],"COTIZANDO",Tabla3[NUM ECONOMICO],B65,Tabla3[TEMA],"<>SERVICIO DE FILTROS")) -> 0 | H65: =IF(B65="",0,SUMIFS(Tabla3[COSTO TOTAL DOLARES EN HAWTHORNE],Tabla3[STATUS],"COTIZANDO",Tabla3[NUM ECONOMICO],B65,Tabla3[TEMA],"<>SERVICIO DE FILTROS")) -> 0 | I65: =IF(B65="","",_xlfn.LET(_xlpm.totalUSD,SUMIFS(Tabla3[COSTO TOTAL DOLARES EN HAWTHORNE],Tabla3[STATUS],"COTIZANDO",Tabla3[NUM ECONOMICO],B65,Tabla3[TEMA],"<>SERVICIO DE FILTROS"),IF(OR(TC="",_xlpm.totalUSD=0),"—",_xlpm.totalUSD*TC))) -> — | J65: =IF(B65="",0,SUMIFS(Tabla3[COSTO TOTAL DOLARES CTP],Tabla3[STATUS],"COTIZANDO",Tabla3[NUM ECONOMICO],B65,Tabla3[TEMA],"<>SERVICIO DE FILTROS")) -> 0 | K65: =IF(B65="","",_xlfn.LET(_xlpm.totalUSD,SUMIFS(Tabla3[COSTO TOTAL DOLARES CTP],Tabla3[STATUS],"COTIZANDO",Tabla3[NUM ECONOMICO],B65,Tabla3[TEMA],"<>SERVICIO DE FILTROS"),IF(OR(TC="",_xlpm.totalUSD=0),"—",_xlpm.totalUSD*TC))) -> — | L65: {=IF(B65="",0,IFERROR(MAX(_xlfn._xlws.FILTER(Tabla3[DIAS DE ENTREGA TENTATIVO EN MATCO],(Tabla3[STATUS]="COTIZANDO")*(Tabla3[NUM ECONOMICO]=B65)*(Tabla3[TEMA]<>"SERVICIO DE FILTROS"))),0))} -> 0
B66: =MAQUINARIA!B233 -> ME-32 | C66: =MAQUINARIA!H233 -> ACTIVA | D66: =IFERROR(TRIM(MAQUINARIA!C233&" "&MAQUINARIA!E233),"—") -> ESCREPA 631 E | E66: {=IF(B66="",0,IFERROR(ROWS(_xlfn.UNIQUE(_xlfn._xlws.FILTER(Tabla3[PEDIDO],(Tabla3[STATUS]="COTIZANDO")*(Tabla3[NUM ECONOMICO]=B66)*(Tabla3[TEMA]<>"SERVICIO DE FILTROS")))),0))} -> 0 | F66: =IF(B66="",0,COUNTIFS(Tabla3[STATUS],"COTIZANDO",Tabla3[NUM ECONOMICO],B66,Tabla3[TEMA],"<>SERVICIO DE FILTROS")) -> 0 | G66: =IF(B66="",0,SUMIFS(Tabla3[COSTO TOTAL SIN IVA PESOS EN MATCO],Tabla3[STATUS],"COTIZANDO",Tabla3[NUM ECONOMICO],B66,Tabla3[TEMA],"<>SERVICIO DE FILTROS")) -> 0 | H66: =IF(B66="",0,SUMIFS(Tabla3[COSTO TOTAL DOLARES EN HAWTHORNE],Tabla3[STATUS],"COTIZANDO",Tabla3[NUM ECONOMICO],B66,Tabla3[TEMA],"<>SERVICIO DE FILTROS")) -> 0 | I66: =IF(B66="","",_xlfn.LET(_xlpm.totalUSD,SUMIFS(Tabla3[COSTO TOTAL DOLARES EN HAWTHORNE],Tabla3[STATUS],"COTIZANDO",Tabla3[NUM ECONOMICO],B66,Tabla3[TEMA],"<>SERVICIO DE FILTROS"),IF(OR(TC="",_xlpm.totalUSD=0),"—",_xlpm.totalUSD*TC))) -> — | J66: =IF(B66="",0,SUMIFS(Tabla3[COSTO TOTAL DOLARES CTP],Tabla3[STATUS],"COTIZANDO",Tabla3[NUM ECONOMICO],B66,Tabla3[TEMA],"<>SERVICIO DE FILTROS")) -> 0 | K66: =IF(B66="","",_xlfn.LET(_xlpm.totalUSD,SUMIFS(Tabla3[COSTO TOTAL DOLARES CTP],Tabla3[STATUS],"COTIZANDO",Tabla3[NUM ECONOMICO],B66,Tabla3[TEMA],"<>SERVICIO DE FILTROS"),IF(OR(TC="",_xlpm.totalUSD=0),"—",_xlpm.totalUSD*TC))) -> — | L66: {=IF(B66="",0,IFERROR(MAX(_xlfn._xlws.FILTER(Tabla3[DIAS DE ENTREGA TENTATIVO EN MATCO],(Tabla3[STATUS]="COTIZANDO")*(Tabla3[NUM ECONOMICO]=B66)*(Tabla3[TEMA]<>"SERVICIO DE FILTROS"))),0))} -> 0
B67: =MAQUINARIA!B235 -> ME-33 | C67: =MAQUINARIA!H235 -> ACTIVA | D67: =IFERROR(TRIM(MAQUINARIA!C235&" "&MAQUINARIA!E235),"—") -> ESCREPA 631 E | E67: {=IF(B67="",0,IFERROR(ROWS(_xlfn.UNIQUE(_xlfn._xlws.FILTER(Tabla3[PEDIDO],(Tabla3[STATUS]="COTIZANDO")*(Tabla3[NUM ECONOMICO]=B67)*(Tabla3[TEMA]<>"SERVICIO DE FILTROS")))),0))} -> 0 | F67: =IF(B67="",0,COUNTIFS(Tabla3[STATUS],"COTIZANDO",Tabla3[NUM ECONOMICO],B67,Tabla3[TEMA],"<>SERVICIO DE FILTROS")) -> 0 | G67: =IF(B67="",0,SUMIFS(Tabla3[COSTO TOTAL SIN IVA PESOS EN MATCO],Tabla3[STATUS],"COTIZANDO",Tabla3[NUM ECONOMICO],B67,Tabla3[TEMA],"<>SERVICIO DE FILTROS")) -> 0 | H67: =IF(B67="",0,SUMIFS(Tabla3[COSTO TOTAL DOLARES EN HAWTHORNE],Tabla3[STATUS],"COTIZANDO",Tabla3[NUM ECONOMICO],B67,Tabla3[TEMA],"<>SERVICIO DE FILTROS")) -> 0 | I67: =IF(B67="","",_xlfn.LET(_xlpm.totalUSD,SUMIFS(Tabla3[COSTO TOTAL DOLARES EN HAWTHORNE],Tabla3[STATUS],"COTIZANDO",Tabla3[NUM ECONOMICO],B67,Tabla3[TEMA],"<>SERVICIO DE FILTROS"),IF(OR(TC="",_xlpm.totalUSD=0),"—",_xlpm.totalUSD*TC))) -> — | J67: =IF(B67="",0,SUMIFS(Tabla3[COSTO TOTAL DOLARES CTP],Tabla3[STATUS],"COTIZANDO",Tabla3[NUM ECONOMICO],B67,Tabla3[TEMA],"<>SERVICIO DE FILTROS")) -> 0 | K67: =IF(B67="","",_xlfn.LET(_xlpm.totalUSD,SUMIFS(Tabla3[COSTO TOTAL DOLARES CTP],Tabla3[STATUS],"COTIZANDO",Tabla3[NUM ECONOMICO],B67,Tabla3[TEMA],"<>SERVICIO DE FILTROS"),IF(OR(TC="",_xlpm.totalUSD=0),"—",_xlpm.totalUSD*TC))) -> — | L67: {=IF(B67="",0,IFERROR(MAX(_xlfn._xlws.FILTER(Tabla3[DIAS DE ENTREGA TENTATIVO EN MATCO],(Tabla3[STATUS]="COTIZANDO")*(Tabla3[NUM ECONOMICO]=B67)*(Tabla3[TEMA]<>"SERVICIO DE FILTROS"))),0))} -> 0
B68: =MAQUINARIA!B237 -> ME-34 | C68: =MAQUINARIA!H237 -> INACTIVA | D68: =IFERROR(TRIM(MAQUINARIA!C237&" "&MAQUINARIA!E237),"—") -> ESCREPA 631 E | E68: {=IF(B68="",0,IFERROR(ROWS(_xlfn.UNIQUE(_xlfn._xlws.FILTER(Tabla3[PEDIDO],(Tabla3[STATUS]="COTIZANDO")*(Tabla3[NUM ECONOMICO]=B68)*(Tabla3[TEMA]<>"SERVICIO DE FILTROS")))),0))} -> 0 | F68: =IF(B68="",0,COUNTIFS(Tabla3[STATUS],"COTIZANDO",Tabla3[NUM ECONOMICO],B68,Tabla3[TEMA],"<>SERVICIO DE FILTROS")) -> 0 | G68: =IF(B68="",0,SUMIFS(Tabla3[COSTO TOTAL SIN IVA PESOS EN MATCO],Tabla3[STATUS],"COTIZANDO",Tabla3[NUM ECONOMICO],B68,Tabla3[TEMA],"<>SERVICIO DE FILTROS")) -> 0 | H68: =IF(B68="",0,SUMIFS(Tabla3[COSTO TOTAL DOLARES EN HAWTHORNE],Tabla3[STATUS],"COTIZANDO",Tabla3[NUM ECONOMICO],B68,Tabla3[TEMA],"<>SERVICIO DE FILTROS")) -> 0 | I68: =IF(B68="","",_xlfn.LET(_xlpm.totalUSD,SUMIFS(Tabla3[COSTO TOTAL DOLARES EN HAWTHORNE],Tabla3[STATUS],"COTIZANDO",Tabla3[NUM ECONOMICO],B68,Tabla3[TEMA],"<>SERVICIO DE FILTROS"),IF(OR(TC="",_xlpm.totalUSD=0),"—",_xlpm.totalUSD*TC))) -> — | J68: =IF(B68="",0,SUMIFS(Tabla3[COSTO TOTAL DOLARES CTP],Tabla3[STATUS],"COTIZANDO",Tabla3[NUM ECONOMICO],B68,Tabla3[TEMA],"<>SERVICIO DE FILTROS")) -> 0 | K68: =IF(B68="","",_xlfn.LET(_xlpm.totalUSD,SUMIFS(Tabla3[COSTO TOTAL DOLARES CTP],Tabla3[STATUS],"COTIZANDO",Tabla3[NUM ECONOMICO],B68,Tabla3[TEMA],"<>SERVICIO DE FILTROS"),IF(OR(TC="",_xlpm.totalUSD=0),"—",_xlpm.totalUSD*TC))) -> — | L68: {=IF(B68="",0,IFERROR(MAX(_xlfn._xlws.FILTER(Tabla3[DIAS DE ENTREGA TENTATIVO EN MATCO],(Tabla3[STATUS]="COTIZANDO")*(Tabla3[NUM ECONOMICO]=B68)*(Tabla3[TEMA]<>"SERVICIO DE FILTROS"))),0))} -> 0
B69: =MAQUINARIA!B242 -> ME-35 | C69: =MAQUINARIA!H242 -> ACTIVA | D69: =IFERROR(TRIM(MAQUINARIA!C242&" "&MAQUINARIA!E242),"—") -> ESCREPA 631 E | E69: {=IF(B69="",0,IFERROR(ROWS(_xlfn.UNIQUE(_xlfn._xlws.FILTER(Tabla3[PEDIDO],(Tabla3[STATUS]="COTIZANDO")*(Tabla3[NUM ECONOMICO]=B69)*(Tabla3[TEMA]<>"SERVICIO DE FILTROS")))),0))} -> 0 | F69: =IF(B69="",0,COUNTIFS(Tabla3[STATUS],"COTIZANDO",Tabla3[NUM ECONOMICO],B69,Tabla3[TEMA],"<>SERVICIO DE FILTROS")) -> 0 | G69: =IF(B69="",0,SUMIFS(Tabla3[COSTO TOTAL SIN IVA PESOS EN MATCO],Tabla3[STATUS],"COTIZANDO",Tabla3[NUM ECONOMICO],B69,Tabla3[TEMA],"<>SERVICIO DE FILTROS")) -> 0 | H69: =IF(B69="",0,SUMIFS(Tabla3[COSTO TOTAL DOLARES EN HAWTHORNE],Tabla3[STATUS],"COTIZANDO",Tabla3[NUM ECONOMICO],B69,Tabla3[TEMA],"<>SERVICIO DE FILTROS")) -> 0 | I69: =IF(B69="","",_xlfn.LET(_xlpm.totalUSD,SUMIFS(Tabla3[COSTO TOTAL DOLARES EN HAWTHORNE],Tabla3[STATUS],"COTIZANDO",Tabla3[NUM ECONOMICO],B69,Tabla3[TEMA],"<>SERVICIO DE FILTROS"),IF(OR(TC="",_xlpm.totalUSD=0),"—",_xlpm.totalUSD*TC))) -> — | J69: =IF(B69="",0,SUMIFS(Tabla3[COSTO TOTAL DOLARES CTP],Tabla3[STATUS],"COTIZANDO",Tabla3[NUM ECONOMICO],B69,Tabla3[TEMA],"<>SERVICIO DE FILTROS")) -> 0 | K69: =IF(B69="","",_xlfn.LET(_xlpm.totalUSD,SUMIFS(Tabla3[COSTO TOTAL DOLARES CTP],Tabla3[STATUS],"COTIZANDO",Tabla3[NUM ECONOMICO],B69,Tabla3[TEMA],"<>SERVICIO DE FILTROS"),IF(OR(TC="",_xlpm.totalUSD=0),"—",_xlpm.totalUSD*TC))) -> — | L69: {=IF(B69="",0,IFERROR(MAX(_xlfn._xlws.FILTER(Tabla3[DIAS DE ENTREGA TENTATIVO EN MATCO],(Tabla3[STATUS]="COTIZANDO")*(Tabla3[NUM ECONOMICO]=B69)*(Tabla3[TEMA]<>"SERVICIO DE FILTROS"))),0))} -> 0
B70: =MAQUINARIA!B320 -> MM-01 | C70: =MAQUINARIA!H320 -> ACTIVA | D70: =IFERROR(TRIM(MAQUINARIA!C320&" "&MAQUINARIA!E320),"—") -> MOTOCONFORMADORA 130 G | E70: {=IF(B70="",0,IFERROR(ROWS(_xlfn.UNIQUE(_xlfn._xlws.FILTER(Tabla3[PEDIDO],(Tabla3[STATUS]="COTIZANDO")*(Tabla3[NUM ECONOMICO]=B70)*(Tabla3[TEMA]<>"SERVICIO DE FILTROS")))),0))} -> 0 | F70: =IF(B70="",0,COUNTIFS(Tabla3[STATUS],"COTIZANDO",Tabla3[NUM ECONOMICO],B70,Tabla3[TEMA],"<>SERVICIO DE FILTROS")) -> 0 | G70: =IF(B70="",0,SUMIFS(Tabla3[COSTO TOTAL SIN IVA PESOS EN MATCO],Tabla3[STATUS],"COTIZANDO",Tabla3[NUM ECONOMICO],B70,Tabla3[TEMA],"<>SERVICIO DE FILTROS")) -> 0 | H70: =IF(B70="",0,SUMIFS(Tabla3[COSTO TOTAL DOLARES EN HAWTHORNE],Tabla3[STATUS],"COTIZANDO",Tabla3[NUM ECONOMICO],B70,Tabla3[TEMA],"<>SERVICIO DE FILTROS")) -> 0 | I70: =IF(B70="","",_xlfn.LET(_xlpm.totalUSD,SUMIFS(Tabla3[COSTO TOTAL DOLARES EN HAWTHORNE],Tabla3[STATUS],"COTIZANDO",Tabla3[NUM ECONOMICO],B70,Tabla3[TEMA],"<>SERVICIO DE FILTROS"),IF(OR(TC="",_xlpm.totalUSD=0),"—",_xlpm.totalUSD*TC))) -> — | J70: =IF(B70="",0,SUMIFS(Tabla3[COSTO TOTAL DOLARES CTP],Tabla3[STATUS],"COTIZANDO",Tabla3[NUM ECONOMICO],B70,Tabla3[TEMA],"<>SERVICIO DE FILTROS")) -> 0 | K70: =IF(B70="","",_xlfn.LET(_xlpm.totalUSD,SUMIFS(Tabla3[COSTO TOTAL DOLARES CTP],Tabla3[STATUS],"COTIZANDO",Tabla3[NUM ECONOMICO],B70,Tabla3[TEMA],"<>SERVICIO DE FILTROS"),IF(OR(TC="",_xlpm.totalUSD=0),"—",_xlpm.totalUSD*TC))) -> — | L70: {=IF(B70="",0,IFERROR(MAX(_xlfn._xlws.FILTER(Tabla3[DIAS DE ENTREGA TENTATIVO EN MATCO],(Tabla3[STATUS]="COTIZANDO")*(Tabla3[NUM ECONOMICO]=B70)*(Tabla3[TEMA]<>"SERVICIO DE FILTROS"))),0))} -> 0
B71: =MAQUINARIA!B329 -> MM-02 | C71: =MAQUINARIA!H329 -> ACTIVA | D71: =IFERROR(TRIM(MAQUINARIA!C329&" "&MAQUINARIA!E329),"—") -> MOTOCONFORMADORA 12 G | E71: {=IF(B71="",0,IFERROR(ROWS(_xlfn.UNIQUE(_xlfn._xlws.FILTER(Tabla3[PEDIDO],(Tabla3[STATUS]="COTIZANDO")*(Tabla3[NUM ECONOMICO]=B71)*(Tabla3[TEMA]<>"SERVICIO DE FILTROS")))),0))} -> 0 | F71: =IF(B71="",0,COUNTIFS(Tabla3[STATUS],"COTIZANDO",Tabla3[NUM ECONOMICO],B71,Tabla3[TEMA],"<>SERVICIO DE FILTROS")) -> 0 | G71: =IF(B71="",0,SUMIFS(Tabla3[COSTO TOTAL SIN IVA PESOS EN MATCO],Tabla3[STATUS],"COTIZANDO",Tabla3[NUM ECONOMICO],B71,Tabla3[TEMA],"<>SERVICIO DE FILTROS")) -> 0 | H71: =IF(B71="",0,SUMIFS(Tabla3[COSTO TOTAL DOLARES EN HAWTHORNE],Tabla3[STATUS],"COTIZANDO",Tabla3[NUM ECONOMICO],B71,Tabla3[TEMA],"<>SERVICIO DE FILTROS")) -> 0 | I71: =IF(B71="","",_xlfn.LET(_xlpm.totalUSD,SUMIFS(Tabla3[COSTO TOTAL DOLARES EN HAWTHORNE],Tabla3[STATUS],"COTIZANDO",Tabla3[NUM ECONOMICO],B71,Tabla3[TEMA],"<>SERVICIO DE FILTROS"),IF(OR(TC="",_xlpm.totalUSD=0),"—",_xlpm.totalUSD*TC))) -> — | J71: =IF(B71="",0,SUMIFS(Tabla3[COSTO TOTAL DOLARES CTP],Tabla3[STATUS],"COTIZANDO",Tabla3[NUM ECONOMICO],B71,Tabla3[TEMA],"<>SERVICIO DE FILTROS")) -> 0 | K71: =IF(B71="","",_xlfn.LET(_xlpm.totalUSD,SUMIFS(Tabla3[COSTO TOTAL DOLARES CTP],Tabla3[STATUS],"COTIZANDO",Tabla3[NUM ECONOMICO],B71,Tabla3[TEMA],"<>SERVICIO DE FILTROS"),IF(OR(TC="",_xlpm.totalUSD=0),"—",_xlpm.totalUSD*TC))) -> — | L71: {=IF(B71="",0,IFERROR(MAX(_xlfn._xlws.FILTER(Tabla3[DIAS DE ENTREGA TENTATIVO EN MATCO],(Tabla3[STATUS]="COTIZANDO")*(Tabla3[NUM ECONOMICO]=B71)*(Tabla3[TEMA]<>"SERVICIO DE FILTROS"))),0))} -> 0
B72: =MAQUINARIA!B337 -> MM-03 | C72: =MAQUINARIA!H337 -> INACTIVA | D72: =IFERROR(TRIM(MAQUINARIA!C337&" "&MAQUINARIA!E337),"—") -> MOTOCONFORMADORA 16 G | E72: {=IF(B72="",0,IFERROR(ROWS(_xlfn.UNIQUE(_xlfn._xlws.FILTER(Tabla3[PEDIDO],(Tabla3[STATUS]="COTIZANDO")*(Tabla3[NUM ECONOMICO]=B72)*(Tabla3[TEMA]<>"SERVICIO DE FILTROS")))),0))} -> 1 | F72: =IF(B72="",0,COUNTIFS(Tabla3[STATUS],"COTIZANDO",Tabla3[NUM ECONOMICO],B72,Tabla3[TEMA],"<>SERVICIO DE FILTROS")) -> 47 | G72: =IF(B72="",0,SUMIFS(Tabla3[COSTO TOTAL SIN IVA PESOS EN MATCO],Tabla3[STATUS],"COTIZANDO",Tabla3[NUM ECONOMICO],B72,Tabla3[TEMA],"<>SERVICIO DE FILTROS")) -> 566675.73 | H72: =IF(B72="",0,SUMIFS(Tabla3[COSTO TOTAL DOLARES EN HAWTHORNE],Tabla3[STATUS],"COTIZANDO",Tabla3[NUM ECONOMICO],B72,Tabla3[TEMA],"<>SERVICIO DE FILTROS")) -> 32144.74 | I72: =IF(B72="","",_xlfn.LET(_xlpm.totalUSD,SUMIFS(Tabla3[COSTO TOTAL DOLARES EN HAWTHORNE],Tabla3[STATUS],"COTIZANDO",Tabla3[NUM ECONOMICO],B72,Tabla3[TEMA],"<>SERVICIO DE FILTROS"),IF(OR(TC="",_xlpm.totalUSD=0),"—",_xlpm.totalUSD*TC))) -> 546460.58 | J72: =IF(B72="",0,SUMIFS(Tabla3[COSTO TOTAL DOLARES CTP],Tabla3[STATUS],"COTIZANDO",Tabla3[NUM ECONOMICO],B72,Tabla3[TEMA],"<>SERVICIO DE FILTROS")) -> 9212.63 | K72: =IF(B72="","",_xlfn.LET(_xlpm.totalUSD,SUMIFS(Tabla3[COSTO TOTAL DOLARES CTP],Tabla3[STATUS],"COTIZANDO",Tabla3[NUM ECONOMICO],B72,Tabla3[TEMA],"<>SERVICIO DE FILTROS"),IF(OR(TC="",_xlpm.totalUSD=0),"—",_xlpm.totalUSD*TC))) -> 156614.71 | L72: {=IF(B72="",0,IFERROR(MAX(_xlfn._xlws.FILTER(Tabla3[DIAS DE ENTREGA TENTATIVO EN MATCO],(Tabla3[STATUS]="COTIZANDO")*(Tabla3[NUM ECONOMICO]=B72)*(Tabla3[TEMA]<>"SERVICIO DE FILTROS"))),0))} -> 0
B73: =MAQUINARIA!B341 -> MM-04 | C73: =MAQUINARIA!H341 -> ACTIVA | D73: =IFERROR(TRIM(MAQUINARIA!C341&" "&MAQUINARIA!E341),"—") -> MOTOCONFORMADORA 16 M | E73: {=IF(B73="",0,IFERROR(ROWS(_xlfn.UNIQUE(_xlfn._xlws.FILTER(Tabla3[PEDIDO],(Tabla3[STATUS]="COTIZANDO")*(Tabla3[NUM ECONOMICO]=B73)*(Tabla3[TEMA]<>"SERVICIO DE FILTROS")))),0))} -> 0 | F73: =IF(B73="",0,COUNTIFS(Tabla3[STATUS],"COTIZANDO",Tabla3[NUM ECONOMICO],B73,Tabla3[TEMA],"<>SERVICIO DE FILTROS")) -> 0 | G73: =IF(B73="",0,SUMIFS(Tabla3[COSTO TOTAL SIN IVA PESOS EN MATCO],Tabla3[STATUS],"COTIZANDO",Tabla3[NUM ECONOMICO],B73,Tabla3[TEMA],"<>SERVICIO DE FILTROS")) -> 0 | H73: =IF(B73="",0,SUMIFS(Tabla3[COSTO TOTAL DOLARES EN HAWTHORNE],Tabla3[STATUS],"COTIZANDO",Tabla3[NUM ECONOMICO],B73,Tabla3[TEMA],"<>SERVICIO DE FILTROS")) -> 0 | I73: =IF(B73="","",_xlfn.LET(_xlpm.totalUSD,SUMIFS(Tabla3[COSTO TOTAL DOLARES EN HAWTHORNE],Tabla3[STATUS],"COTIZANDO",Tabla3[NUM ECONOMICO],B73,Tabla3[TEMA],"<>SERVICIO DE FILTROS"),IF(OR(TC="",_xlpm.totalUSD=0),"—",_xlpm.totalUSD*TC))) -> — | J73: =IF(B73="",0,SUMIFS(Tabla3[COSTO TOTAL DOLARES CTP],Tabla3[STATUS],"COTIZANDO",Tabla3[NUM ECONOMICO],B73,Tabla3[TEMA],"<>SERVICIO DE FILTROS")) -> 0 | K73: =IF(B73="","",_xlfn.LET(_xlpm.totalUSD,SUMIFS(Tabla3[COSTO TOTAL DOLARES CTP],Tabla3[STATUS],"COTIZANDO",Tabla3[NUM ECONOMICO],B73,Tabla3[TEMA],"<>SERVICIO DE FILTROS"),IF(OR(TC="",_xlpm.totalUSD=0),"—",_xlpm.totalUSD*TC))) -> — | L73: {=IF(B73="",0,IFERROR(MAX(_xlfn._xlws.FILTER(Tabla3[DIAS DE ENTREGA TENTATIVO EN MATCO],(Tabla3[STATUS]="COTIZANDO")*(Tabla3[NUM ECONOMICO]=B73)*(Tabla3[TEMA]<>"SERVICIO DE FILTROS"))),0))} -> 0
B74: =MAQUINARIA!B360 -> MN-01 | C74: =MAQUINARIA!H360 -> ACTIVA | D74: =IFERROR(TRIM(MAQUINARIA!C360&" "&MAQUINARIA!E360),"—") -> MINICARGADOR | E74: {=IF(B74="",0,IFERROR(ROWS(_xlfn.UNIQUE(_xlfn._xlws.FILTER(Tabla3[PEDIDO],(Tabla3[STATUS]="COTIZANDO")*(Tabla3[NUM ECONOMICO]=B74)*(Tabla3[TEMA]<>"SERVICIO DE FILTROS")))),0))} -> 0 | F74: =IF(B74="",0,COUNTIFS(Tabla3[STATUS],"COTIZANDO",Tabla3[NUM ECONOMICO],B74,Tabla3[TEMA],"<>SERVICIO DE FILTROS")) -> 0 | G74: =IF(B74="",0,SUMIFS(Tabla3[COSTO TOTAL SIN IVA PESOS EN MATCO],Tabla3[STATUS],"COTIZANDO",Tabla3[NUM ECONOMICO],B74,Tabla3[TEMA],"<>SERVICIO DE FILTROS")) -> 0 | H74: =IF(B74="",0,SUMIFS(Tabla3[COSTO TOTAL DOLARES EN HAWTHORNE],Tabla3[STATUS],"COTIZANDO",Tabla3[NUM ECONOMICO],B74,Tabla3[TEMA],"<>SERVICIO DE FILTROS")) -> 0 | I74: =IF(B74="","",_xlfn.LET(_xlpm.totalUSD,SUMIFS(Tabla3[COSTO TOTAL DOLARES EN HAWTHORNE],Tabla3[STATUS],"COTIZANDO",Tabla3[NUM ECONOMICO],B74,Tabla3[TEMA],"<>SERVICIO DE FILTROS"),IF(OR(TC="",_xlpm.totalUSD=0),"—",_xlpm.totalUSD*TC))) -> — | J74: =IF(B74="",0,SUMIFS(Tabla3[COSTO TOTAL DOLARES CTP],Tabla3[STATUS],"COTIZANDO",Tabla3[NUM ECONOMICO],B74,Tabla3[TEMA],"<>SERVICIO DE FILTROS")) -> 0 | K74: =IF(B74="","",_xlfn.LET(_xlpm.totalUSD,SUMIFS(Tabla3[COSTO TOTAL DOLARES CTP],Tabla3[STATUS],"COTIZANDO",Tabla3[NUM ECONOMICO],B74,Tabla3[TEMA],"<>SERVICIO DE FILTROS"),IF(OR(TC="",_xlpm.totalUSD=0),"—",_xlpm.totalUSD*TC))) -> — | L74: {=IF(B74="",0,IFERROR(MAX(_xlfn._xlws.FILTER(Tabla3[DIAS DE ENTREGA TENTATIVO EN MATCO],(Tabla3[STATUS]="COTIZANDO")*(Tabla3[NUM ECONOMICO]=B74)*(Tabla3[TEMA]<>"SERVICIO DE FILTROS"))),0))} -> 0
B75: =MAQUINARIA!B248 -> MP-01 | C75: =MAQUINARIA!H248 -> ACTIVA | D75: =IFERROR(TRIM(MAQUINARIA!C248&" "&MAQUINARIA!E248),"—") -> TORNAPIPA 631 B | E75: {=IF(B75="",0,IFERROR(ROWS(_xlfn.UNIQUE(_xlfn._xlws.FILTER(Tabla3[PEDIDO],(Tabla3[STATUS]="COTIZANDO")*(Tabla3[NUM ECONOMICO]=B75)*(Tabla3[TEMA]<>"SERVICIO DE FILTROS")))),0))} -> 0 | F75: =IF(B75="",0,COUNTIFS(Tabla3[STATUS],"COTIZANDO",Tabla3[NUM ECONOMICO],B75,Tabla3[TEMA],"<>SERVICIO DE FILTROS")) -> 0 | G75: =IF(B75="",0,SUMIFS(Tabla3[COSTO TOTAL SIN IVA PESOS EN MATCO],Tabla3[STATUS],"COTIZANDO",Tabla3[NUM ECONOMICO],B75,Tabla3[TEMA],"<>SERVICIO DE FILTROS")) -> 0 | H75: =IF(B75="",0,SUMIFS(Tabla3[COSTO TOTAL DOLARES EN HAWTHORNE],Tabla3[STATUS],"COTIZANDO",Tabla3[NUM ECONOMICO],B75,Tabla3[TEMA],"<>SERVICIO DE FILTROS")) -> 0 | I75: =IF(B75="","",_xlfn.LET(_xlpm.totalUSD,SUMIFS(Tabla3[COSTO TOTAL DOLARES EN HAWTHORNE],Tabla3[STATUS],"COTIZANDO",Tabla3[NUM ECONOMICO],B75,Tabla3[TEMA],"<>SERVICIO DE FILTROS"),IF(OR(TC="",_xlpm.totalUSD=0),"—",_xlpm.totalUSD*TC))) -> — | J75: =IF(B75="",0,SUMIFS(Tabla3[COSTO TOTAL DOLARES CTP],Tabla3[STATUS],"COTIZANDO",Tabla3[NUM ECONOMICO],B75,Tabla3[TEMA],"<>SERVICIO DE FILTROS")) -> 0 | K75: =IF(B75="","",_xlfn.LET(_xlpm.totalUSD,SUMIFS(Tabla3[COSTO TOTAL DOLARES CTP],Tabla3[STATUS],"COTIZANDO",Tabla3[NUM ECONOMICO],B75,Tabla3[TEMA],"<>SERVICIO DE FILTROS"),IF(OR(TC="",_xlpm.totalUSD=0),"—",_xlpm.totalUSD*TC))) -> — | L75: {=IF(B75="",0,IFERROR(MAX(_xlfn._xlws.FILTER(Tabla3[DIAS DE ENTREGA TENTATIVO EN MATCO],(Tabla3[STATUS]="COTIZANDO")*(Tabla3[NUM ECONOMICO]=B75)*(Tabla3[TEMA]<>"SERVICIO DE FILTROS"))),0))} -> 0
B76: =MAQUINARIA!B256 -> MP-02 | C76: =MAQUINARIA!H256 -> INACTIVA | D76: =IFERROR(TRIM(MAQUINARIA!C256&" "&MAQUINARIA!E256),"—") -> TORNAPIPA 631 D | E76: {=IF(B76="",0,IFERROR(ROWS(_xlfn.UNIQUE(_xlfn._xlws.FILTER(Tabla3[PEDIDO],(Tabla3[STATUS]="COTIZANDO")*(Tabla3[NUM ECONOMICO]=B76)*(Tabla3[TEMA]<>"SERVICIO DE FILTROS")))),0))} -> 0 | F76: =IF(B76="",0,COUNTIFS(Tabla3[STATUS],"COTIZANDO",Tabla3[NUM ECONOMICO],B76,Tabla3[TEMA],"<>SERVICIO DE FILTROS")) -> 0 | G76: =IF(B76="",0,SUMIFS(Tabla3[COSTO TOTAL SIN IVA PESOS EN MATCO],Tabla3[STATUS],"COTIZANDO",Tabla3[NUM ECONOMICO],B76,Tabla3[TEMA],"<>SERVICIO DE FILTROS")) -> 0 | H76: =IF(B76="",0,SUMIFS(Tabla3[COSTO TOTAL DOLARES EN HAWTHORNE],Tabla3[STATUS],"COTIZANDO",Tabla3[NUM ECONOMICO],B76,Tabla3[TEMA],"<>SERVICIO DE FILTROS")) -> 0 | I76: =IF(B76="","",_xlfn.LET(_xlpm.totalUSD,SUMIFS(Tabla3[COSTO TOTAL DOLARES EN HAWTHORNE],Tabla3[STATUS],"COTIZANDO",Tabla3[NUM ECONOMICO],B76,Tabla3[TEMA],"<>SERVICIO DE FILTROS"),IF(OR(TC="",_xlpm.totalUSD=0),"—",_xlpm.totalUSD*TC))) -> — | J76: =IF(B76="",0,SUMIFS(Tabla3[COSTO TOTAL DOLARES CTP],Tabla3[STATUS],"COTIZANDO",Tabla3[NUM ECONOMICO],B76,Tabla3[TEMA],"<>SERVICIO DE FILTROS")) -> 0 | K76: =IF(B76="","",_xlfn.LET(_xlpm.totalUSD,SUMIFS(Tabla3[COSTO TOTAL DOLARES CTP],Tabla3[STATUS],"COTIZANDO",Tabla3[NUM ECONOMICO],B76,Tabla3[TEMA],"<>SERVICIO DE FILTROS"),IF(OR(TC="",_xlpm.totalUSD=0),"—",_xlpm.totalUSD*TC))) -> — | L76: {=IF(B76="",0,IFERROR(MAX(_xlfn._xlws.FILTER(Tabla3[DIAS DE ENTREGA TENTATIVO EN MATCO],(Tabla3[STATUS]="COTIZANDO")*(Tabla3[NUM ECONOMICO]=B76)*(Tabla3[TEMA]<>"SERVICIO DE FILTROS"))),0))} -> 0
B77: =MAQUINARIA!B260 -> MP-03 | C77: =MAQUINARIA!H260 -> ACTIVA | D77: =IFERROR(TRIM(MAQUINARIA!C260&" "&MAQUINARIA!E260),"—") -> TORNAPIPA 631 D | E77: {=IF(B77="",0,IFERROR(ROWS(_xlfn.UNIQUE(_xlfn._xlws.FILTER(Tabla3[PEDIDO],(Tabla3[STATUS]="COTIZANDO")*(Tabla3[NUM ECONOMICO]=B77)*(Tabla3[TEMA]<>"SERVICIO DE FILTROS")))),0))} -> 1 | F77: =IF(B77="",0,COUNTIFS(Tabla3[STATUS],"COTIZANDO",Tabla3[NUM ECONOMICO],B77,Tabla3[TEMA],"<>SERVICIO DE FILTROS")) -> 1 | G77: =IF(B77="",0,SUMIFS(Tabla3[COSTO TOTAL SIN IVA PESOS EN MATCO],Tabla3[STATUS],"COTIZANDO",Tabla3[NUM ECONOMICO],B77,Tabla3[TEMA],"<>SERVICIO DE FILTROS")) -> 387 | H77: =IF(B77="",0,SUMIFS(Tabla3[COSTO TOTAL DOLARES EN HAWTHORNE],Tabla3[STATUS],"COTIZANDO",Tabla3[NUM ECONOMICO],B77,Tabla3[TEMA],"<>SERVICIO DE FILTROS")) -> 21.41 | I77: =IF(B77="","",_xlfn.LET(_xlpm.totalUSD,SUMIFS(Tabla3[COSTO TOTAL DOLARES EN HAWTHORNE],Tabla3[STATUS],"COTIZANDO",Tabla3[NUM ECONOMICO],B77,Tabla3[TEMA],"<>SERVICIO DE FILTROS"),IF(OR(TC="",_xlpm.totalUSD=0),"—",_xlpm.totalUSD*TC))) -> 363.97 | J77: =IF(B77="",0,SUMIFS(Tabla3[COSTO TOTAL DOLARES CTP],Tabla3[STATUS],"COTIZANDO",Tabla3[NUM ECONOMICO],B77,Tabla3[TEMA],"<>SERVICIO DE FILTROS")) -> 9.34 | K77: =IF(B77="","",_xlfn.LET(_xlpm.totalUSD,SUMIFS(Tabla3[COSTO TOTAL DOLARES CTP],Tabla3[STATUS],"COTIZANDO",Tabla3[NUM ECONOMICO],B77,Tabla3[TEMA],"<>SERVICIO DE FILTROS"),IF(OR(TC="",_xlpm.totalUSD=0),"—",_xlpm.totalUSD*TC))) -> 158.78 | L77: {=IF(B77="",0,IFERROR(MAX(_xlfn._xlws.FILTER(Tabla3[DIAS DE ENTREGA TENTATIVO EN MATCO],(Tabla3[STATUS]="COTIZANDO")*(Tabla3[NUM ECONOMICO]=B77)*(Tabla3[TEMA]<>"SERVICIO DE FILTROS"))),0))} -> 0
B78: =MAQUINARIA!B262 -> MP-04 | C78: =MAQUINARIA!H262 -> INACTIVA | D78: =IFERROR(TRIM(MAQUINARIA!C262&" "&MAQUINARIA!E262),"—") -> TORNAPIPA 627 B | E78: {=IF(B78="",0,IFERROR(ROWS(_xlfn.UNIQUE(_xlfn._xlws.FILTER(Tabla3[PEDIDO],(Tabla3[STATUS]="COTIZANDO")*(Tabla3[NUM ECONOMICO]=B78)*(Tabla3[TEMA]<>"SERVICIO DE FILTROS")))),0))} -> 0 | F78: =IF(B78="",0,COUNTIFS(Tabla3[STATUS],"COTIZANDO",Tabla3[NUM ECONOMICO],B78,Tabla3[TEMA],"<>SERVICIO DE FILTROS")) -> 0 | G78: =IF(B78="",0,SUMIFS(Tabla3[COSTO TOTAL SIN IVA PESOS EN MATCO],Tabla3[STATUS],"COTIZANDO",Tabla3[NUM ECONOMICO],B78,Tabla3[TEMA],"<>SERVICIO DE FILTROS")) -> 0 | H78: =IF(B78="",0,SUMIFS(Tabla3[COSTO TOTAL DOLARES EN HAWTHORNE],Tabla3[STATUS],"COTIZANDO",Tabla3[NUM ECONOMICO],B78,Tabla3[TEMA],"<>SERVICIO DE FILTROS")) -> 0 | I78: =IF(B78="","",_xlfn.LET(_xlpm.totalUSD,SUMIFS(Tabla3[COSTO TOTAL DOLARES EN HAWTHORNE],Tabla3[STATUS],"COTIZANDO",Tabla3[NUM ECONOMICO],B78,Tabla3[TEMA],"<>SERVICIO DE FILTROS"),IF(OR(TC="",_xlpm.totalUSD=0),"—",_xlpm.totalUSD*TC))) -> — | J78: =IF(B78="",0,SUMIFS(Tabla3[COSTO TOTAL DOLARES CTP],Tabla3[STATUS],"COTIZANDO",Tabla3[NUM ECONOMICO],B78,Tabla3[TEMA],"<>SERVICIO DE FILTROS")) -> 0 | K78: =IF(B78="","",_xlfn.LET(_xlpm.totalUSD,SUMIFS(Tabla3[COSTO TOTAL DOLARES CTP],Tabla3[STATUS],"COTIZANDO",Tabla3[NUM ECONOMICO],B78,Tabla3[TEMA],"<>SERVICIO DE FILTROS"),IF(OR(TC="",_xlpm.totalUSD=0),"—",_xlpm.totalUSD*TC))) -> — | L78: {=IF(B78="",0,IFERROR(MAX(_xlfn._xlws.FILTER(Tabla3[DIAS DE ENTREGA TENTATIVO EN MATCO],(Tabla3[STATUS]="COTIZANDO")*(Tabla3[NUM ECONOMICO]=B78)*(Tabla3[TEMA]<>"SERVICIO DE FILTROS"))),0))} -> 0
B79: =MAQUINARIA!B309 -> MR-01 | C79: =MAQUINARIA!H309 -> ACTIVA | D79: =IFERROR(TRIM(MAQUINARIA!C309&" "&MAQUINARIA!E309),"—") -> RETROEXCAVADORA 430 | E79: {=IF(B79="",0,IFERROR(ROWS(_xlfn.UNIQUE(_xlfn._xlws.FILTER(Tabla3[PEDIDO],(Tabla3[STATUS]="COTIZANDO")*(Tabla3[NUM ECONOMICO]=B79)*(Tabla3[TEMA]<>"SERVICIO DE FILTROS")))),0))} -> 0 | F79: =IF(B79="",0,COUNTIFS(Tabla3[STATUS],"COTIZANDO",Tabla3[NUM ECONOMICO],B79,Tabla3[TEMA],"<>SERVICIO DE FILTROS")) -> 0 | G79: =IF(B79="",0,SUMIFS(Tabla3[COSTO TOTAL SIN IVA PESOS EN MATCO],Tabla3[STATUS],"COTIZANDO",Tabla3[NUM ECONOMICO],B79,Tabla3[TEMA],"<>SERVICIO DE FILTROS")) -> 0 | H79: =IF(B79="",0,SUMIFS(Tabla3[COSTO TOTAL DOLARES EN HAWTHORNE],Tabla3[STATUS],"COTIZANDO",Tabla3[NUM ECONOMICO],B79,Tabla3[TEMA],"<>SERVICIO DE FILTROS")) -> 0 | I79: =IF(B79="","",_xlfn.LET(_xlpm.totalUSD,SUMIFS(Tabla3[COSTO TOTAL DOLARES EN HAWTHORNE],Tabla3[STATUS],"COTIZANDO",Tabla3[NUM ECONOMICO],B79,Tabla3[TEMA],"<>SERVICIO DE FILTROS"),IF(OR(TC="",_xlpm.totalUSD=0),"—",_xlpm.totalUSD*TC))) -> — | J79: =IF(B79="",0,SUMIFS(Tabla3[COSTO TOTAL DOLARES CTP],Tabla3[STATUS],"COTIZANDO",Tabla3[NUM ECONOMICO],B79,Tabla3[TEMA],"<>SERVICIO DE FILTROS")) -> 0 | K79: =IF(B79="","",_xlfn.LET(_xlpm.totalUSD,SUMIFS(Tabla3[COSTO TOTAL DOLARES CTP],Tabla3[STATUS],"COTIZANDO",Tabla3[NUM ECONOMICO],B79,Tabla3[TEMA],"<>SERVICIO DE FILTROS"),IF(OR(TC="",_xlpm.totalUSD=0),"—",_xlpm.totalUSD*TC))) -> — | L79: {=IF(B79="",0,IFERROR(MAX(_xlfn._xlws.FILTER(Tabla3[DIAS DE ENTREGA TENTATIVO EN MATCO],(Tabla3[STATUS]="COTIZANDO")*(Tabla3[NUM ECONOMICO]=B79)*(Tabla3[TEMA]<>"SERVICIO DE FILTROS"))),0))} -> 0
B80: =MAQUINARIA!B312 -> MR-02 | C80: =MAQUINARIA!H312 -> ACTIVA | D80: =IFERROR(TRIM(MAQUINARIA!C312&" "&MAQUINARIA!E312),"—") -> RETROEXCAVADORA 430 | E80: {=IF(B80="",0,IFERROR(ROWS(_xlfn.UNIQUE(_xlfn._xlws.FILTER(Tabla3[PEDIDO],(Tabla3[STATUS]="COTIZANDO")*(Tabla3[NUM ECONOMICO]=B80)*(Tabla3[TEMA]<>"SERVICIO DE FILTROS")))),0))} -> 0 | F80: =IF(B80="",0,COUNTIFS(Tabla3[STATUS],"COTIZANDO",Tabla3[NUM ECONOMICO],B80,Tabla3[TEMA],"<>SERVICIO DE FILTROS")) -> 0 | G80: =IF(B80="",0,SUMIFS(Tabla3[COSTO TOTAL SIN IVA PESOS EN MATCO],Tabla3[STATUS],"COTIZANDO",Tabla3[NUM ECONOMICO],B80,Tabla3[TEMA],"<>SERVICIO DE FILTROS")) -> 0 | H80: =IF(B80="",0,SUMIFS(Tabla3[COSTO TOTAL DOLARES EN HAWTHORNE],Tabla3[STATUS],"COTIZANDO",Tabla3[NUM ECONOMICO],B80,Tabla3[TEMA],"<>SERVICIO DE FILTROS")) -> 0 | I80: =IF(B80="","",_xlfn.LET(_xlpm.totalUSD,SUMIFS(Tabla3[COSTO TOTAL DOLARES EN HAWTHORNE],Tabla3[STATUS],"COTIZANDO",Tabla3[NUM ECONOMICO],B80,Tabla3[TEMA],"<>SERVICIO DE FILTROS"),IF(OR(TC="",_xlpm.totalUSD=0),"—",_xlpm.totalUSD*TC))) -> — | J80: =IF(B80="",0,SUMIFS(Tabla3[COSTO TOTAL DOLARES CTP],Tabla3[STATUS],"COTIZANDO",Tabla3[NUM ECONOMICO],B80,Tabla3[TEMA],"<>SERVICIO DE FILTROS")) -> 0 | K80: =IF(B80="","",_xlfn.LET(_xlpm.totalUSD,SUMIFS(Tabla3[COSTO TOTAL DOLARES CTP],Tabla3[STATUS],"COTIZANDO",Tabla3[NUM ECONOMICO],B80,Tabla3[TEMA],"<>SERVICIO DE FILTROS"),IF(OR(TC="",_xlpm.totalUSD=0),"—",_xlpm.totalUSD*TC))) -> — | L80: {=IF(B80="",0,IFERROR(MAX(_xlfn._xlws.FILTER(Tabla3[DIAS DE ENTREGA TENTATIVO EN MATCO],(Tabla3[STATUS]="COTIZANDO")*(Tabla3[NUM ECONOMICO]=B80)*(Tabla3[TEMA]<>"SERVICIO DE FILTROS"))),0))} -> 0
B81: =MAQUINARIA!B313 -> MR-03 | C81: =MAQUINARIA!H313 -> ACTIVA | D81: =IFERROR(TRIM(MAQUINARIA!C313&" "&MAQUINARIA!E313),"—") -> RETROEXCAVADORA 580 | E81: {=IF(B81="",0,IFERROR(ROWS(_xlfn.UNIQUE(_xlfn._xlws.FILTER(Tabla3[PEDIDO],(Tabla3[STATUS]="COTIZANDO")*(Tabla3[NUM ECONOMICO]=B81)*(Tabla3[TEMA]<>"SERVICIO DE FILTROS")))),0))} -> 0 | F81: =IF(B81="",0,COUNTIFS(Tabla3[STATUS],"COTIZANDO",Tabla3[NUM ECONOMICO],B81,Tabla3[TEMA],"<>SERVICIO DE FILTROS")) -> 0 | G81: =IF(B81="",0,SUMIFS(Tabla3[COSTO TOTAL SIN IVA PESOS EN MATCO],Tabla3[STATUS],"COTIZANDO",Tabla3[NUM ECONOMICO],B81,Tabla3[TEMA],"<>SERVICIO DE FILTROS")) -> 0 | H81: =IF(B81="",0,SUMIFS(Tabla3[COSTO TOTAL DOLARES EN HAWTHORNE],Tabla3[STATUS],"COTIZANDO",Tabla3[NUM ECONOMICO],B81,Tabla3[TEMA],"<>SERVICIO DE FILTROS")) -> 0 | I81: =IF(B81="","",_xlfn.LET(_xlpm.totalUSD,SUMIFS(Tabla3[COSTO TOTAL DOLARES EN HAWTHORNE],Tabla3[STATUS],"COTIZANDO",Tabla3[NUM ECONOMICO],B81,Tabla3[TEMA],"<>SERVICIO DE FILTROS"),IF(OR(TC="",_xlpm.totalUSD=0),"—",_xlpm.totalUSD*TC))) -> — | J81: =IF(B81="",0,SUMIFS(Tabla3[COSTO TOTAL DOLARES CTP],Tabla3[STATUS],"COTIZANDO",Tabla3[NUM ECONOMICO],B81,Tabla3[TEMA],"<>SERVICIO DE FILTROS")) -> 0 | K81: =IF(B81="","",_xlfn.LET(_xlpm.totalUSD,SUMIFS(Tabla3[COSTO TOTAL DOLARES CTP],Tabla3[STATUS],"COTIZANDO",Tabla3[NUM ECONOMICO],B81,Tabla3[TEMA],"<>SERVICIO DE FILTROS"),IF(OR(TC="",_xlpm.totalUSD=0),"—",_xlpm.totalUSD*TC))) -> — | L81: {=IF(B81="",0,IFERROR(MAX(_xlfn._xlws.FILTER(Tabla3[DIAS DE ENTREGA TENTATIVO EN MATCO],(Tabla3[STATUS]="COTIZANDO")*(Tabla3[NUM ECONOMICO]=B81)*(Tabla3[TEMA]<>"SERVICIO DE FILTROS"))),0))} -> 0
B82: =MAQUINARIA!B3 -> MT-01 | C82: =MAQUINARIA!H3 -> INACTIVA | D82: =IFERROR(TRIM(MAQUINARIA!C3&" "&MAQUINARIA!E3),"—") -> TRACTOR D9T | E82: {=IF(B82="",0,IFERROR(ROWS(_xlfn.UNIQUE(_xlfn._xlws.FILTER(Tabla3[PEDIDO],(Tabla3[STATUS]="COTIZANDO")*(Tabla3[NUM ECONOMICO]=B82)*(Tabla3[TEMA]<>"SERVICIO DE FILTROS")))),0))} -> 2 | F82: =IF(B82="",0,COUNTIFS(Tabla3[STATUS],"COTIZANDO",Tabla3[NUM ECONOMICO],B82,Tabla3[TEMA],"<>SERVICIO DE FILTROS")) -> 47 | G82: =IF(B82="",0,SUMIFS(Tabla3[COSTO TOTAL SIN IVA PESOS EN MATCO],Tabla3[STATUS],"COTIZANDO",Tabla3[NUM ECONOMICO],B82,Tabla3[TEMA],"<>SERVICIO DE FILTROS")) -> 2013891.2 | H82: =IF(B82="",0,SUMIFS(Tabla3[COSTO TOTAL DOLARES EN HAWTHORNE],Tabla3[STATUS],"COTIZANDO",Tabla3[NUM ECONOMICO],B82,Tabla3[TEMA],"<>SERVICIO DE FILTROS")) -> 93062.13 | I82: =IF(B82="","",_xlfn.LET(_xlpm.totalUSD,SUMIFS(Tabla3[COSTO TOTAL DOLARES EN HAWTHORNE],Tabla3[STATUS],"COTIZANDO",Tabla3[NUM ECONOMICO],B82,Tabla3[TEMA],"<>SERVICIO DE FILTROS"),IF(OR(TC="",_xlpm.totalUSD=0),"—",_xlpm.totalUSD*TC))) -> 1582056.2 | J82: =IF(B82="",0,SUMIFS(Tabla3[COSTO TOTAL DOLARES CTP],Tabla3[STATUS],"COTIZANDO",Tabla3[NUM ECONOMICO],B82,Tabla3[TEMA],"<>SERVICIO DE FILTROS")) -> 7817.02 | K82: =IF(B82="","",_xlfn.LET(_xlpm.totalUSD,SUMIFS(Tabla3[COSTO TOTAL DOLARES CTP],Tabla3[STATUS],"COTIZANDO",Tabla3[NUM ECONOMICO],B82,Tabla3[TEMA],"<>SERVICIO DE FILTROS"),IF(OR(TC="",_xlpm.totalUSD=0),"—",_xlpm.totalUSD*TC))) -> 132889.34 | L82: {=IF(B82="",0,IFERROR(MAX(_xlfn._xlws.FILTER(Tabla3[DIAS DE ENTREGA TENTATIVO EN MATCO],(Tabla3[STATUS]="COTIZANDO")*(Tabla3[NUM ECONOMICO]=B82)*(Tabla3[TEMA]<>"SERVICIO DE FILTROS"))),0))} -> 0
B83: =MAQUINARIA!B8 -> MT-02 | C83: =MAQUINARIA!H8 -> ACTIVA | D83: =IFERROR(TRIM(MAQUINARIA!C8&" "&MAQUINARIA!E8),"—") -> TRACTOR D9T | E83: {=IF(B83="",0,IFERROR(ROWS(_xlfn.UNIQUE(_xlfn._xlws.FILTER(Tabla3[PEDIDO],(Tabla3[STATUS]="COTIZANDO")*(Tabla3[NUM ECONOMICO]=B83)*(Tabla3[TEMA]<>"SERVICIO DE FILTROS")))),0))} -> 2 | F83: =IF(B83="",0,COUNTIFS(Tabla3[STATUS],"COTIZANDO",Tabla3[NUM ECONOMICO],B83,Tabla3[TEMA],"<>SERVICIO DE FILTROS")) -> 5 | G83: =IF(B83="",0,SUMIFS(Tabla3[COSTO TOTAL SIN IVA PESOS EN MATCO],Tabla3[STATUS],"COTIZANDO",Tabla3[NUM ECONOMICO],B83,Tabla3[TEMA],"<>SERVICIO DE FILTROS")) -> 86146.53 | H83: =IF(B83="",0,SUMIFS(Tabla3[COSTO TOTAL DOLARES EN HAWTHORNE],Tabla3[STATUS],"COTIZANDO",Tabla3[NUM ECONOMICO],B83,Tabla3[TEMA],"<>SERVICIO DE FILTROS")) -> 3357.28 | I83: =IF(B83="","",_xlfn.LET(_xlpm.totalUSD,SUMIFS(Tabla3[COSTO TOTAL DOLARES EN HAWTHORNE],Tabla3[STATUS],"COTIZANDO",Tabla3[NUM ECONOMICO],B83,Tabla3[TEMA],"<>SERVICIO DE FILTROS"),IF(OR(TC="",_xlpm.totalUSD=0),"—",_xlpm.totalUSD*TC))) -> 57073.76 | J83: =IF(B83="",0,SUMIFS(Tabla3[COSTO TOTAL DOLARES CTP],Tabla3[STATUS],"COTIZANDO",Tabla3[NUM ECONOMICO],B83,Tabla3[TEMA],"<>SERVICIO DE FILTROS")) -> 3.82 | K83: =IF(B83="","",_xlfn.LET(_xlpm.totalUSD,SUMIFS(Tabla3[COSTO TOTAL DOLARES CTP],Tabla3[STATUS],"COTIZANDO",Tabla3[NUM ECONOMICO],B83,Tabla3[TEMA],"<>SERVICIO DE FILTROS"),IF(OR(TC="",_xlpm.totalUSD=0),"—",_xlpm.totalUSD*TC))) -> 64.94 | L83: {=IF(B83="",0,IFERROR(MAX(_xlfn._xlws.FILTER(Tabla3[DIAS DE ENTREGA TENTATIVO EN MATCO],(Tabla3[STATUS]="COTIZANDO")*(Tabla3[NUM ECONOMICO]=B83)*(Tabla3[TEMA]<>"SERVICIO DE FILTROS"))),0))} -> 0
B84: =MAQUINARIA!B16 -> MT-03 | C84: =MAQUINARIA!H16 -> ACTIVA | D84: =IFERROR(TRIM(MAQUINARIA!C16&" "&MAQUINARIA!E16),"—") -> TRACTOR D9T | E84: {=IF(B84="",0,IFERROR(ROWS(_xlfn.UNIQUE(_xlfn._xlws.FILTER(Tabla3[PEDIDO],(Tabla3[STATUS]="COTIZANDO")*(Tabla3[NUM ECONOMICO]=B84)*(Tabla3[TEMA]<>"SERVICIO DE FILTROS")))),0))} -> 3 | F84: =IF(B84="",0,COUNTIFS(Tabla3[STATUS],"COTIZANDO",Tabla3[NUM ECONOMICO],B84,Tabla3[TEMA],"<>SERVICIO DE FILTROS")) -> 15 | G84: =IF(B84="",0,SUMIFS(Tabla3[COSTO TOTAL SIN IVA PESOS EN MATCO],Tabla3[STATUS],"COTIZANDO",Tabla3[NUM ECONOMICO],B84,Tabla3[TEMA],"<>SERVICIO DE FILTROS")) -> 67991.26 | H84: =IF(B84="",0,SUMIFS(Tabla3[COSTO TOTAL DOLARES EN HAWTHORNE],Tabla3[STATUS],"COTIZANDO",Tabla3[NUM ECONOMICO],B84,Tabla3[TEMA],"<>SERVICIO DE FILTROS")) -> 3100.27 | I84: =IF(B84="","",_xlfn.LET(_xlpm.totalUSD,SUMIFS(Tabla3[COSTO TOTAL DOLARES EN HAWTHORNE],Tabla3[STATUS],"COTIZANDO",Tabla3[NUM ECONOMICO],B84,Tabla3[TEMA],"<>SERVICIO DE FILTROS"),IF(OR(TC="",_xlpm.totalUSD=0),"—",_xlpm.totalUSD*TC))) -> 52704.59 | J84: =IF(B84="",0,SUMIFS(Tabla3[COSTO TOTAL DOLARES CTP],Tabla3[STATUS],"COTIZANDO",Tabla3[NUM ECONOMICO],B84,Tabla3[TEMA],"<>SERVICIO DE FILTROS")) -> 799.61 | K84: =IF(B84="","",_xlfn.LET(_xlpm.totalUSD,SUMIFS(Tabla3[COSTO TOTAL DOLARES CTP],Tabla3[STATUS],"COTIZANDO",Tabla3[NUM ECONOMICO],B84,Tabla3[TEMA],"<>SERVICIO DE FILTROS"),IF(OR(TC="",_xlpm.totalUSD=0),"—",_xlpm.totalUSD*TC))) -> 13593.37 | L84: {=IF(B84="",0,IFERROR(MAX(_xlfn._xlws.FILTER(Tabla3[DIAS DE ENTREGA TENTATIVO EN MATCO],(Tabla3[STATUS]="COTIZANDO")*(Tabla3[NUM ECONOMICO]=B84)*(Tabla3[TEMA]<>"SERVICIO DE FILTROS"))),0))} -> 0
B85: =MAQUINARIA!B22 -> MT-04 | C85: =MAQUINARIA!H22 -> INACTIVA | D85: =IFERROR(TRIM(MAQUINARIA!C22&" "&MAQUINARIA!E22),"—") -> TRACTOR D9R | E85: {=IF(B85="",0,IFERROR(ROWS(_xlfn.UNIQUE(_xlfn._xlws.FILTER(Tabla3[PEDIDO],(Tabla3[STATUS]="COTIZANDO")*(Tabla3[NUM ECONOMICO]=B85)*(Tabla3[TEMA]<>"SERVICIO DE FILTROS")))),0))} -> 1 | F85: =IF(B85="",0,COUNTIFS(Tabla3[STATUS],"COTIZANDO",Tabla3[NUM ECONOMICO],B85,Tabla3[TEMA],"<>SERVICIO DE FILTROS")) -> 1 | G85: =IF(B85="",0,SUMIFS(Tabla3[COSTO TOTAL SIN IVA PESOS EN MATCO],Tabla3[STATUS],"COTIZANDO",Tabla3[NUM ECONOMICO],B85,Tabla3[TEMA],"<>SERVICIO DE FILTROS")) -> 22788.31 | H85: =IF(B85="",0,SUMIFS(Tabla3[COSTO TOTAL DOLARES EN HAWTHORNE],Tabla3[STATUS],"COTIZANDO",Tabla3[NUM ECONOMICO],B85,Tabla3[TEMA],"<>SERVICIO DE FILTROS")) -> 0 | I85: =IF(B85="","",_xlfn.LET(_xlpm.totalUSD,SUMIFS(Tabla3[COSTO TOTAL DOLARES EN HAWTHORNE],Tabla3[STATUS],"COTIZANDO",Tabla3[NUM ECONOMICO],B85,Tabla3[TEMA],"<>SERVICIO DE FILTROS"),IF(OR(TC="",_xlpm.totalUSD=0),"—",_xlpm.totalUSD*TC))) -> — | J85: =IF(B85="",0,SUMIFS(Tabla3[COSTO TOTAL DOLARES CTP],Tabla3[STATUS],"COTIZANDO",Tabla3[NUM ECONOMICO],B85,Tabla3[TEMA],"<>SERVICIO DE FILTROS")) -> 0 | K85: =IF(B85="","",_xlfn.LET(_xlpm.totalUSD,SUMIFS(Tabla3[COSTO TOTAL DOLARES CTP],Tabla3[STATUS],"COTIZANDO",Tabla3[NUM ECONOMICO],B85,Tabla3[TEMA],"<>SERVICIO DE FILTROS"),IF(OR(TC="",_xlpm.totalUSD=0),"—",_xlpm.totalUSD*TC))) -> — | L85: {=IF(B85="",0,IFERROR(MAX(_xlfn._xlws.FILTER(Tabla3[DIAS DE ENTREGA TENTATIVO EN MATCO],(Tabla3[STATUS]="COTIZANDO")*(Tabla3[NUM ECONOMICO]=B85)*(Tabla3[TEMA]<>"SERVICIO DE FILTROS"))),0))} -> 0
B86: =MAQUINARIA!B30 -> MT-05 | C86: =MAQUINARIA!H30 -> ACTIVA | D86: =IFERROR(TRIM(MAQUINARIA!C30&" "&MAQUINARIA!E30),"—") -> TRACTOR D9R | E86: {=IF(B86="",0,IFERROR(ROWS(_xlfn.UNIQUE(_xlfn._xlws.FILTER(Tabla3[PEDIDO],(Tabla3[STATUS]="COTIZANDO")*(Tabla3[NUM ECONOMICO]=B86)*(Tabla3[TEMA]<>"SERVICIO DE FILTROS")))),0))} -> 1 | F86: =IF(B86="",0,COUNTIFS(Tabla3[STATUS],"COTIZANDO",Tabla3[NUM ECONOMICO],B86,Tabla3[TEMA],"<>SERVICIO DE FILTROS")) -> 1 | G86: =IF(B86="",0,SUMIFS(Tabla3[COSTO TOTAL SIN IVA PESOS EN MATCO],Tabla3[STATUS],"COTIZANDO",Tabla3[NUM ECONOMICO],B86,Tabla3[TEMA],"<>SERVICIO DE FILTROS")) -> 3526.92 | H86: =IF(B86="",0,SUMIFS(Tabla3[COSTO TOTAL DOLARES EN HAWTHORNE],Tabla3[STATUS],"COTIZANDO",Tabla3[NUM ECONOMICO],B86,Tabla3[TEMA],"<>SERVICIO DE FILTROS")) -> 166.66 | I86: =IF(B86="","",_xlfn.LET(_xlpm.totalUSD,SUMIFS(Tabla3[COSTO TOTAL DOLARES EN HAWTHORNE],Tabla3[STATUS],"COTIZANDO",Tabla3[NUM ECONOMICO],B86,Tabla3[TEMA],"<>SERVICIO DE FILTROS"),IF(OR(TC="",_xlpm.totalUSD=0),"—",_xlpm.totalUSD*TC))) -> 2833.22 | J86: =IF(B86="",0,SUMIFS(Tabla3[COSTO TOTAL DOLARES CTP],Tabla3[STATUS],"COTIZANDO",Tabla3[NUM ECONOMICO],B86,Tabla3[TEMA],"<>SERVICIO DE FILTROS")) -> 143.26 | K86: =IF(B86="","",_xlfn.LET(_xlpm.totalUSD,SUMIFS(Tabla3[COSTO TOTAL DOLARES CTP],Tabla3[STATUS],"COTIZANDO",Tabla3[NUM ECONOMICO],B86,Tabla3[TEMA],"<>SERVICIO DE FILTROS"),IF(OR(TC="",_xlpm.totalUSD=0),"—",_xlpm.totalUSD*TC))) -> 2435.42 | L86: {=IF(B86="",0,IFERROR(MAX(_xlfn._xlws.FILTER(Tabla3[DIAS DE ENTREGA TENTATIVO EN MATCO],(Tabla3[STATUS]="COTIZANDO")*(Tabla3[NUM ECONOMICO]=B86)*(Tabla3[TEMA]<>"SERVICIO DE FILTROS"))),0))} -> 0
